Workbook

Sheet 药品通数据
A1: 药品名称 | B1: 指导价 | C1: 处方药 | D1: 成分 | E1: 性状 | F1: 适应症 | G1: 用法用量 | H1: 不良反应 | I1: 禁忌 | J1: 注意事项 | K1: 特殊人群用药 | L1: 药物相互作用 | M1: 药理作用 | N1: 贮藏 | O1: 规格 | P1: 包装规格 | Q1: 有效期
A2: 通用名称：小儿氨酚黄那敏颗粒 商品名称：护彤 英文名称：Pediatric Paracetamol，Atificial Cow-bezoar and Chlorphenamine Maleate Granules 汉语拼音：Xiaoer Anfennamin Keli | B2: 8.4 | C2: =IF(ISNUMBER(MATCH(#REF!,非处方药名称!A:A,0)),"非处方药","处方药") -> 处方药 | D2: 本品为复方制剂，每袋含对乙酰氨基酚125毫克，马来酸氯苯那敏0.5毫克，人工牛黄5毫克。辅料为：蔗糖、阿司帕坦、甜菊素、食用香精 | E2: 本品为淡黄色至黄色或淡橙黄色颗粒。 | F2: 适用于缓解儿童普通感冒及流行性感冒引起的发热、头痛、四肢酸痛、打喷嚏、流鼻涕、鼻塞、咽痛等症状。 | G2: 温开水冲服。12岁以下儿童用量见下表：2～3岁， 12～14公斤， 0.5～1片/次， 一日3次4～6岁， 16～20公斤， 1～1.5片/次， 一日3次7～9岁， 22～26公斤， 1.5～2片/次， 一日3次10～12岁， 28～32公斤，2～2.5片/次， 一日3次 | H2: 有时有轻度头晕、乏力、恶心、上腹不适、口干、食欲缺乏和皮疹等，可自行恢复。 | I2: 严重肝肾功能不全者禁用。 | J2: 1.用药3-7天，症状未缓解，请咨询医师或药师。 2.服用本品期间不得饮酒或含有酒精的饮料。 3.1岁以下儿童应在医师指导下使用。 4.不能同时服用与本品成份相似的其他抗感冒药。 5.肝、肾功能不全者慎用。 6.如服用过量或出现严重不良反应，应立即就医。 7.对本品过敏者禁用，过敏体质者慎用。 8.本品性状发生改变时禁止使用。 9.请将本品放在儿童不能接触的地方。 10.儿童必须在成人监护下使用。 11.如正在使用其他药品，使用本品前请咨询医师或药师。 | K2: 儿童注意事项： 新生儿或早产儿禁用。 妊娠与哺乳期注意事项： 本品中对乙酰氨基酚，人工牛黄均可通过胎盘，可能会对胎儿造成不良影响，对胚胎有毒性且能致畸；除人工牛黄不详外，均能通过乳汁分泌，故孕妇及哺乳期妇女禁用。 老人注意事项： 尚不明确。 | L2: 1.与其他解热镇痛药同用，可增加肾毒性的危险。2.本品不宜与氨酶素等并用。3.如与其他药物同时使用可能会发生药物相互作用，详情请咨询医师或药师。 | M2: 本品中对乙酰氨基酚能抑制前列腺素合成，有解热镇痛作用；马来酸氯苯那敏为抗组胺药，能减轻流涕、鼻塞、打喷嚏等症状；人工牛黄有解热镇惊作用。 | N2: 密封，在阴凉干燥处保存。 | O2: 对乙酰氨基酚0.125克,人工牛黄5毫克,马来酸氯苯那敏0.5毫克 | Q2: 24个月。
A3: 通用名称：复方氨酚烷胺片 商品名称：感叹号 英文名称：Compound Paracetamol and Amantadine Hydrochloride Tablets 汉语拼音：Fu Fang An Fen Wan An Pian | B3: 10.6 | C3: =IF(ISNUMBER(MATCH(#REF!,非处方药名称!A:A,0)),"非处方药","处方药") -> 处方药 | D3: 本品为复方制剂，每片含对乙酰氨基酚250毫克，盐酸金刚烷胺100毫克，人工牛黄10毫克，咖啡因15毫克，马来酸氯苯那敏2毫克，辅料为：淀粉、硬脂酸镁。 | E3: 本品为淡黄色片。 | F3: 用于缓解普通感冒或流行性感冒引起的发热、头痛、咽痛、鼻塞、打喷嚏等症状。 | G3: 口服。成人，一次1片，一日2次。 | H3: 偶见粒细胞、血小板减少、厌食、恶心、呕吐、皮疹等不良反应。 | I3: 1对本品过敏者禁用。 2.活动性消化道溃疡患者禁用。 3.孕妇、哺乳期妇女禁用。 4.1岁以下儿童禁用。 | J3: 1. 用药3-7天，症状未缓解，请咨询医师或药师。 2. 服用本品期间不得饮酒或含有酒精的饮料。 3. 不能同时服用与本品成份相似的其他抗感冒药。 4. 肝功能不全、肾功能不全、脑血管病史、精神病史或癫痫病史患者慎用。 5. 前列腺肥大、青光眼等患者以及老年人应在医师指导下使用。 6. 孕妇及哺乳期妇女慎用。 7. 服药期间不得驾驶机、车、船、从事高空作业、机械作业及操作精密仪器。 8. 如服用过量或出现严重不良反应，应立即就医。 9. 对本品过敏者禁用，过敏体质者慎用。 10. 本品性状发生改变时禁止使用。 11. 请将本品放在儿童不能接触的地方。 12. 儿童必须在成人监护下使用。 13. 如正在使用其他药品，使用本品前请咨询医师或药师。 | K3: 儿童注意事项： 1岁以下儿童禁用。 妊娠与哺乳期注意事项： 本品中金刚烷胺、对乙酰氨基酚、人工牛黄均可通过胎盘，对胚胎有毒性且能致畸，可能会对胎儿造成不良影响;除人工牛黄不详外，均能通过乳汁分泌，故孕妇及哺乳期妇女禁用。 老人注意事项： 慎用或适当减量。 | L3: 1 与其他解热镇痛药同用，可增加肾毒性的危险; 2 本品不宜与氯霉素、巴比妥类(如苯巴比妥)等并用; 3 如与其他药物同时使用可能会发生药物相互作用，详情请咨询医师或药师。 | M3: 对乙酰氨基酚能抑制前列腺素合成，有解热镇痛的作用；金刚烷胺可抗“亚一甲型”流感病毒，抑制病毒繁殖；咖啡因为中枢兴奋药，能增强对乙酰氨基酚的解热镇痛效果，并能减轻其他药物所致的嗜睡、头晕等中枢抑制作用；马来酸氯苯那敏为抗过敏药，能减轻流涕、鼻塞、打喷嚏等症状；人工牛黄具有解热、镇惊作用。上述诸药配伍制成复方，可增强解热、镇痛效果，解除或改善感冒所引起的各种症状。 | N3: 密闭，阴凉干燥处保存。 | P3: 12s | Q3: 36个月
A4: 通用名称：苄达赖氨酸滴眼液 商品名称：莎普爱思 英文名称：Bendazac Lysine Eye Drops 汉语拼音：Biɑndɑlɑiɑnsuɑn Diyɑnye | B4: 106.6 | C4: =IF(ISNUMBER(MATCH(#REF!,非处方药名称!A:A,0)),"非处方药","处方药") -> 处方药 | D4: 本品每瓶含苄达赖氨酸25毫克。辅料为羟丙甲纤维素、磷酸二氢钠、磷酸氢二钠、氯化钠、硫柳汞（汞类化合物，0.001%）。 | E4: 本品为无色或几乎无色的澄明液体 | F4: 早期老年性白内障 | G4: 滴眼，一日3次，一次1～2滴或遵医嘱。 | H4: 一过性灼烧感，流泪等反应，但能随着用药时间延长而适应。极少可有吞咽困难，恶心，呕吐，腹泻,流泪，接触性皮炎等。 | I4: 眼外伤及严重感染时，暂不使用，或遵医嘱 | J4: 1、滴眼时请勿使管口接触手和眼睛，避免污染瓶内眼药水。2、使用后请控紧瓶盖，以防污染。3、部分病例出现一过性刺激感，如灼热感、刺痛等，但不影响使用。实验证明本品经冰箱冷藏(4℃左右)后可以降低刺激性的发生率和强度。建议使用时有刺激的患者，将本品放入冰箱冷藏后使用以降低刺激。若发现药水污染或混浊请弃去不用。4、据报导，一过性刺激的发生率和强度与眼部的其他感染或炎症有关，建议眼部有感染或炎症的白内障患者在使用本品时，最好在医师指导下同时治疗上述眼疾。5、对本品过敏者禁用，过敏体质者慎用。6、本品性状发生改变时禁止使用。7、请将本品放在儿童不能接触的地方。8、如正在使用其他药品，使用本品前请咨询医师或药师。 | K4: 儿童注意事项： 尚未明确。 妊娠与哺乳期注意事项： 尚未明确。 老人注意事项： 尚未明确。 | L4: 如与其他药物同时使用可能会发生药物相互作用，详情请咨询医师或药师 | M4: 本品是醛糖还原酶（AR）抑制剂，文献报告对晶状体醛糖还原酶（AR）有抑制作用，所以用苄达赖氨酸（BDZL）滴眼液抑制眼睛中AR的活性，达到预防或治疗白内障的目的。 | N4: 避光，密闭保存。 | O4: 5毫升:25毫克 | Q4: 36个月
A5: 通用名称：小儿感冒颗粒 英文名称：XiaoErGanMaoKeLi 汉语拼音：Xiaoer Ganmao Keli | C5: =IF(ISNUMBER(MATCH(#REF!,非处方药名称!A:A,0)),"非处方药","处方药") -> 处方药 | D5: 广藿香、菊花、连翘、大青叶、板蓝根、地黄、地骨皮、白薇、薄荷、石膏；辅料为蔗糖、糊精。 | E5: 本品为浅棕色的颗粒；味甜、微苦。 | F5: 疏风解表，清热解毒。用于小儿风热感冒，症见发热、头胀痛、咳嗽痰黏、咽喉肿痛；流感见上述证候者。 | G5: 开水冲服。一岁以内一次6克，一岁至三岁一次612克，四岁至七岁一次12-18克，八岁至十二岁一次24克，一日2次。 | H5: 尚不明确。 | I5: 尚不明确。 | J5: 1.忌辛辣、生冷、油腻食物。2.不宜在服药期间同时服用滋补性中药。3.婴儿应在医师指导下服用。4.风寒感冒者不适用。5.糖尿病患儿、脾虚易腹泻者应在医师指导下服用。6.发热体温超过38．5℃的患者，应去医院就诊。7.服药3天症状无缓解，应去医院就诊。8.对本品过敏者禁用，过敏体质者慎用。9.本品性状发生改变时禁止使用。10.儿童必须在成人监护下使用。11.请将本品放在儿童不能接触的地方。12.如正在使用其他药品，使用本品前请咨询医师或药师。13.开水冲泡，搅拌呈混悬状服用。 | L5: 如与其他药物同时使用可能会发生药物相互作用，详情请咨询医师或药师。 | M5: 疏风解表，清热解毒。 | N5: [02]药品阴凉贮存区(20℃以下) | O5: 12克/袋;6克/袋 | P5: 盒装，内小袋装。
A6: 通用名称：清咽滴丸 商品名称：松栢 英文名称：QingYanDiWan(SongBai) 汉语拼音：Qing Yan Di Wan | B6: 32 | C6: =IF(ISNUMBER(MATCH(#REF!,非处方药名称!A:A,0)),"非处方药","处方药") -> 处方药 | D6: 薄荷脑、青黛、冰片、诃子、甘草、人工牛黄。辅料为聚乙二醇。 | E6: 本品为棕褐色至黑褐色的滴丸；味微苦涩，气辛凉。 | F6: 疏风清热，解毒利咽。用于风热喉痹，咽痛，咽干，口渴；或微恶风，发热，咽部红肿，急性咽炎见上述证候者。 | G6: 含服。一次4～6粒，日3次。 | H6: 尚不明确。 | I6: 尚不明确。 | J6: 1.忌辛辣、鱼腥食物。 2.孕妇慎用。 3.不宜在服药期间同时服用温补性中成药。 4.服药三天后症状无改善，或出现其他症状，应去医院就诊。 5.按照用法用量服用，儿童应在医师指导下服用。 6.药品性状发生改变时禁止服用。 7.儿童必须在成人的监护下使用。 8.请将此药品放在儿童不能接触的地方。 9.如正在服用其他药物，使用本品前请咨询医师或药师。 10.对本品过敏者禁用，过敏体质者慎用。 | K6: 妊娠与哺乳期注意事项： 孕妇慎用。 | L6: 如与其他药物同时使用可能会发生药物相互作用，详情请咨询医师或药师。 | M6: 研究证实，清咽滴丸确有明显的抗炎和镇痛作用，对金黄色葡萄球菌等8株菌有一定的抑制作用。抗炎、镇痛、抑菌是本品治疗急性咽喉炎的药理基础。 | N6: 密封，置阴凉干燥处。 | O6: 每丸重20毫克 | P6: 瓷瓶装，50丸×2瓶。 | Q6: 36个月。
A7: 通用名称：感冒清片 英文名称：GanMaoQingPian 汉语拼音：Ganmaoqing Pian | B7: 3.1 | C7: =IF(ISNUMBER(MATCH(#REF!,非处方药名称!A:A,0)),"非处方药","处方药") -> 处方药 | D7: 南板蓝根、大青叶、金盏银盘、岗梅、山芝麻、对乙酰氨基酚、穿心莲叶、盐酸吗啉胍、马来酸氯苯那敏。 | E7: 本品为薄膜衣片，除去包衣后显灰绿色或灰褐色；味苦。 | F7: 疏风解表，清热解毒。用于风热感冒，发烧，头痛，鼻塞流涕，喷嚏，咽喉肿痛，全身酸痛等症。 | G7: 口服。一次3～4片，一日3次。 | H7: 尚不明确。 | I7: 尚不明确。 | J7: 用药期间不宜驾驶车辆、管理机器及高空作业等。 | L7: 如正在服用其他药品，使用本品前请咨询医师或药师。 | N7: 密封。 | O7: 每素片重0.22g(含对乙酰氨基酚12mg) | Q7: 24月
A8: 通用名称：口炎清颗粒 商品名称：大神 英文名称：KouYanQingKeLi(BaiYunShan) 汉语拼音：Kouyanqing Keli | B8: 18.3 | C8: =IF(ISNUMBER(MATCH(#REF!,非处方药名称!A:A,0)),"非处方药","处方药") -> 处方药 | D8: 天冬、麦冬、玄参、山银花、甘草。 | E8: 本品为棕黄色的颗粒；味甜、微苦。 | F8: 滋阴清热，解毒消肿。用于阴虚火旺所致的口腔炎症。 | G8: 口服。一次2袋，一日1～2次。 | H8: 尚不明确。 | I8: 尚不明确。 | J8: 1.忌烟、酒及辛辣、油腻食物。 2.糖尿病患者及有高血压、心脏病、肝病、肾病等慢性病严重者应在医师指导下服用。 3.儿童、孕妇、哺乳期妇女、年老体弱、脾虚便溏者应在医师指导下服用。 4.服药3天症状无缓解，应去医院就诊。 5.对本品过敏者禁用，过敏体质者慎用。 6.本品性状发生改变时禁止使用。 7.儿童必须在成人监护下使用。 8.请将本品放在儿童不能接触的地方。 9.如正在使用其他药品，使用本品前请咨询医师或药师。 | L8: 如与其他药物同时使用可能会发生药物相互作用，详情请咨询医师或药师。 | N8: 密封。 | O8: 每袋装3g(无蔗糖) | P8: 3克×10袋。 | Q8: 24个月。
A9: 通用名称：清开灵颗粒 商品名称：白云山 英文名称：QingKaiLingKeLi(BaiYunShan) 汉语拼音：Qing Kai Ling Ke Li | B9: 13 | C9: =IF(ISNUMBER(MATCH(#REF!,非处方药名称!A:A,0)),"非处方药","处方药") -> 处方药 | D9: 胆酸、珍珠母、猪去氧胆酸、栀子、水牛角、板蓝根、黄芩苷、金银花。 | E9: 本品为棕色的颗粒;味甜，微苦。 | F9: 清热解毒，镇静安神。对温热病引起的高热不退，烦燥不安，咽喉肿痛，舌红或绛，苔黄，脉数者适宜；多用于湿热型肝炎和上呼吸道感染症。 | G9: 口服。一次1～2袋，一日2～3次。 | H9: 尚不明确。 | I9: 孕妇禁用；糖尿病患者禁服。 | J9: 1.忌烟、酒及辛辣、生冷、油腻食物。 2.不宜在服药期间同时服滋补性中药。 3.发高烧体温超过38.5℃的患者，请上医院就诊；脾胃虚寒泄泻者慎服。 4.风寒感冒者不适用，其表现为恶寒重，发热轻，无汗，头痛，鼻塞，流清涕，喉痒咳嗽。 5.高血压、心脏病、肝病、肾病、糖尿病等慢性病严重者应在医生指导下服用。 6.服药3天症状无缓解，应去医院就诊。 7.儿童、年老体弱者应在医师指导下服用。 8.对本品过敏者禁用，过敏体质者慎用。 9.本品性状发生改变时禁止使用。 10.儿童必须在成人监护下使用。 11.请将本品 | L9: 如与其他药物同时使用可能会发生药物相互作用，详情请咨询医师或药师。 | M9: 经动物试验表明，清开灵有良好的退热和抗感染作用，并且能增加肝脏酶类的活性，提高肝脏解毒能力，起到治疗肝脏疾病的作用。 | N9: 密封。 | O9: 每袋装3克；10克(含黄芩苷20毫克) | P9: 3g*12袋
A10: 通用名称：连花清瘟胶囊 商品名称：以岭 英文名称：LianHuaQingWenJiaoNang(YiLing) 汉语拼音：Lianhua Qingwen Jiaonang | B10: 15 | C10: =IF(ISNUMBER(MATCH(#REF!,非处方药名称!A:A,0)),"非处方药","处方药") -> 处方药 | D10: 连翘、金银花、炙麻黄、炒苦杏仁、石膏、板蓝根、绵马贯众、鱼腥草、广藿香、大黄、红景天、薄荷脑、甘草。辅料为：淀粉。 | E10: 本品为胶囊剂，内容物为棕黄色至黄褐色的颗粒和粉末：气微香，味微苦。 | F10: 清瘟解毒，宣肺泄热。用于治疗流行性感冒属热毒袭肺证，症见：发热或高热，恶寒，肌肉酸痛，鼻塞流涕，咳嗽，头痛，咽干咽痛，舌偏红，苔黄或黄腻等。 | G10: 口服。一次4粒，一日3次。 | H10: 尚不明确。 | I10: 尚不明确。 | J10: 1.忌烟、酒及辛辣、生冷、油腻食物。 2.不宜在服药期间同时服用滋补性中药。 3.风寒感冒者不适用。 4.高血压、心脏病患者慎用。有肝病、糖尿病、肾病等慢性病严重者应在医师指导下服用。 5.儿童、孕妇、哺乳期妇女、年老体弱及脾虚便溏者应在医师指导下服用。 6.发热体温超过38.5℃的患者，应去医院就诊。 7.严格按用法用量服用，本品不宜长期服用。 8.服药3天症状无缓解，应去医院就诊。 9.对本品过敏者禁用，过敏体质者慎用。 10.本品性状发生改变时禁止使用。 11.儿童必须在成人监护下使用。 12.请将 | L10: 如与其他药物同时使用可能会发生药物相互作用，详情请咨询医师或药师。 | N10: 密封，置阴凉干燥处(不超过20℃)。 | O10: 每粒装0.35克 | P10: 铝塑板装。每盒24粒。 | Q10: 24个月
A11: 通用名称：止咳宝片 商品名称：特一 英文名称：ZhiKeBaoPian(TeYi) 汉语拼音：Zhikebao Pian | B11: 22 | C11: =IF(ISNUMBER(MATCH(#REF!,非处方药名称!A:A,0)),"非处方药","处方药") -> 处方药 | D11: 紫菀、橘红、桔梗、前胡、枳壳、百部、五味子、罂粟壳浸膏、甘草、薄荷素油、氯化铵等味。 | E11: 本品为包衣片，除去包衣后，显棕黑色；味微苦、咸。 | F11: 宣肺祛痰，止咳平喘。用于外感风寒所致的咳嗽、痰多清稀、咳甚而喘；慢性支气管炎、上呼吸道感染见上述证候者。 | G11: 口服。一次2片，一日3次；或遵医嘱。该药品连服七日为一疗程，可以连续服用三至五个疗程。 | H11: 尚不明确。 | I11: 孕妇、婴儿及哺乳期妇女忌服。 | J11: 1.忌烟、酒及辛辣、生冷、油腻食物。 2.服药期间不宜再受风寒。 3.不宜在服药期间同时服用滋补性中药。 4.肺热、肺燥之干咳及咳痰带血者慎用。 5.该药品含氯化铵，肝肾功能异常者及老年患者慎用。消化性溃疡患者应在医师指导下使用。 6.支气管扩张、肺脓疡、肺心病、肺结核患者出现咳嗽时应去医院就诊。 7.有高血压、心脏病、糖尿病等慢性病严重者应在医师指导下服用。 8.儿童应在医师指导下服用。 9.服药期间，若患者发热体温超过38.5℃，或出现喘促气急者，或咳嗽加重、痰量明显增多者应去医院就诊 | L11: 如与其他药物同时使用可能会发生药物相互作用，详情请咨询医师或药师。 | N11: 密封，置阴凉干燥处 | O11: 每片重0.35克 | Q11: 24月
A12: 通用名称：感冒灵胶囊 商品名称：999 英文名称：GanMaoLingJiaoNang(999) 汉语拼音：Ganmaoling Jiaonang | B12: 15.8 | C12: =IF(ISNUMBER(MATCH(#REF!,非处方药名称!A:A,0)),"非处方药","处方药") -> 处方药 | D12: 三叉苦、岗梅、金盏银盘、薄荷油、野菊花、马来酸氯苯那敏、咖啡因、对乙酰氨基酚。 | E12: 本品为胶囊剂，内容物为棕褐色颗粒；味苦。 | F12: 用于感冒引起的头痛，发热，鼻塞，流涕，咽痛等。 | G12: 口服。一次2粒，一日3次。 | H12: 可见困倦、嗜睡、口渴、虚弱感；偶见皮疹、荨麻疹、药热及粒细胞减少；长期大量用药会导致肝肾功能异常。 | I12: 严重肝肾功能不全者禁用。 | J12: 1.忌烟、酒及辛辣、生冷、油腻食物。 2.不宜在服药期间同时服用滋补性中成药。 3.本品含对乙酰氨基酚、马来酸氯苯那敏、咖啡因。服用本品期间不得饮酒或含有酒精的饮料；不能同时服用与本品成份相似的其他抗感冒药；肝、肾功能不全者慎用；膀胱颈梗阻、甲状腺功能亢进、青光眼、高血压和前列腺肥大者慎用；孕妇及哺乳期妇女慎用；服药期间不得驾驶机、车、船、从事高空作业、机械作业及操作精密仪器。 4.脾胃虚寒，症见腹痛、喜暖、泄泻者慎用。 5.心脏病、糖尿病等慢性病严重者应在医师指导下服用。 6.儿童、年老体弱者应在医师指导下服用。 7.服药3天后症状无改善，或症状加重，或出现新的严重症状如胸闷、心悸等应立即停药，并去医院就诊。 8.对本品过敏者禁用，过敏体质者慎用。 9.本品性状发生改变时禁止使用。 10.儿童必须在成人监护下使用。 11.请将本品放在儿童不能接触的地方。 12.如正在使用其他药品，使用本品前请咨询医师或药师。 | L12: 1 与其他解热镇痛药并用，有增加肾毒性的危险。2 如与其他药物同时使用可能会发生药物相互作用，详情请咨询医师或药师。 | M12: 解热镇痛。 | N12: 密封 | O12: 每粒装0.5g(含对乙酰氨基酚0.1g) | P12: 12粒
A13: 通用名称：补肾固齿丸 商品名称：九芝堂 英文名称：BuShenGuChiWan(JiuZhiTang) 汉语拼音：Bushen Guchi Wan | B13: 45.2 | C13: =IF(ISNUMBER(MATCH(#REF!,非处方药名称!A:A,0)),"非处方药","处方药") -> 处方药 | D13: 熟地黄、地黄、鸡血藤、紫河车、盐骨碎补、漏芦、酒丹参、酒五味子、山药、醋郁金、炙黄芪、牛膝、野菊花、茯苓、枸杞子、牡丹皮、盐泽泻、肉桂。辅料：食盐、薄膜包衣剂。 | E13: 本品为薄膜衣水丸，除去包衣后显棕褐色；味咸、微苦、辛。 | F13: 补肾固齿，活血解毒。用于肾虚血热型牙周病，牙齿酸软，咀嚼无力，松动移位，牙龈出血。 | G13: 口服。一次4克，一日2次。 | H13: 尚不明确。 | I13: 尚不明确。 | J13: 1.忌烟、酒及辛辣、油腻食物。 2.不宜在服药期间同时服用温补性中药。 3.儿童、哺乳期妇女、年老体弱者应在医师指导下服用。 4.有高血压、心脏病、肝病、肾病等慢性病严重者应在医师指导下服用。 5.服药时最好配合牙科治疗。 6.服药7天症状无缓解，应去医院就诊。 7.对本品过敏者禁用，过敏体质者慎用。 8.药品性状发生改变时禁止服用。 9.儿童必须在成人监护下使用。 10.请将此药品放在儿童不能接触的地方。 11.如正在服用其他药品，使用本品前请咨询医师或药师。 | K13: 妊娠与哺乳期注意事项： 孕妇禁用。 | L13: 如与其他药物同时使用可能会发生药物相互作用，详情请咨询医师或药师。 | N13: 密闭，置阴凉干燥处。 | O13: 每30丸重1克
A14: 通用名称：小儿热速清颗粒 商品名称：圣泰 英文名称：XiaoErReSuQingKeLi(ShengTai) 汉语拼音：Xiao Er Re Su Qing Ke Li | B14: 19.5 | C14: =IF(ISNUMBER(MATCH(#REF!,非处方药名称!A:A,0)),"非处方药","处方药") -> 处方药 | D14: 柴胡、黄芩、板蓝根、葛根、金银花、水牛角、连翘、大黄。辅料为蔗糖、糊精。 | E14: 本品为土黄色至棕褐色的颗粒;味微苦。 | F14: 清热，解毒，利咽。用于风热感冒，发热头痛，咽喉红肿，鼻塞流黄涕，咳嗽，便秘。 | G14: 口服。一岁以内，一次1/4-半袋，一岁至三岁，一次半袋-1袋，三岁至七岁，一次1袋-1.5袋，七岁至十二岁，一次1.5袋-2袋，一日3-4次。 | H14: 尚不明确。 | I14: 风寒感冒，大便次数多者忌用。 | J14: 1.感冒风寒，大便次数多者忌用。2.忌食生冷辛辣食物。3.按照用法用量服用，如病情较重或服药二天后疗效不明显者，应及时去医院就诊。4.药品性状发生改变时禁止服用。5.儿童必须在成人的监护下使用。6.请将此药品放在儿童不能接触的地方。7.如正在服用其他药品，使用本品前请咨询医师或药师。 | L14: 如正在服用其他药品，使用本品前请咨询医师或药师。 | M14: 清热，解毒，利咽。 | N14: 密封。 | O14: 每袋装2克 | P14: 2g*6袋/盒
A15: 通用名称：小儿肺热咳喘颗粒4克 商品名称：葫芦娃 汉语拼音：Xiaoer Feire Kechuan Keli | C15: =IF(ISNUMBER(MATCH(#REF!,非处方药名称!A:A,0)),"非处方药","处方药") -> 处方药 | D15: 麻黄、苦杏仁、生石膏、甘草、金银花、连翘、知母、黄芩、板蓝根、麦冬、鱼腥草。 | E15: 本品为棕黄色至深棕黄色颗粒；味甜 | F15: 清热解毒，宣肺止咳，化痰平喘。用于感冒，支气管炎，喘息性支气管炎，支气管肺炎属痰热壅肺证者。 | G15: 开水冲服，三周岁以下一次4克（一袋），一日3次；三周岁以上一次4克（一袋），一日4次；七周岁以上一次8克（2袋），一日3次。 | H15: 大剂量服用，可能有轻度胃肠不适反应。 | I15: 尚不明确 | J15: 1.忌辛辣、生冷、油腻食物。2.不宜在服药期间同时服用滋补性中药。3.婴儿及糖尿病患儿应在医师指导下服用。4.风寒闭肺、内伤久咳者不适用。5.运动员慎用。6.高血压、心脏病患儿慎用。脾虚易腹泻者在医师指导下服用。7.发热体温超过38.5℃的患者，应去医院就诊。8.服药3天症状无缓解，应去应用就诊。9.对本品过敏者禁用，过敏体质者慎用。10.本品性状发生改变时禁止使用。11.儿童必须在成人监护下使用。12.请将本品放在儿童不能接触的地方。13.如正在使用其他药品，使用本品前请咨询医师或药师。 | L15: 如与其他药物同时使用可能会发生药物相互作用，详情请咨询医师或药师。 | N15: 密封 | P15: 每袋装4克(相当于饮片10.6克) | Q15: 30个月
A16: 通用名称：熊胆川贝口服液 商品名称：一品红 英文名称：XiongDanChuanBeiKouFuYe(YiPinHong) 汉语拼音：Xiongdan Chuanbei Koufuye | B16: 22.5 | C16: =IF(ISNUMBER(MATCH(#REF!,非处方药名称!A:A,0)),"非处方药","处方药") -> 处方药 | D16: 熊胆、川贝母、杏仁 | E16: 本品为浅黄色至浅黄棕色的液体；气微香，味甜微苦、有凉喉感。 | F16: 清热化痰，止咳。用于痰热咳嗽，咳痰不止，咯痰不爽。 | G16: 口服。一次10毫升，一日2-3次。 | H16: 尚不明确。 | I16: 孕妇禁用；糖尿病患者禁服。 | J16: 1.忌食辛辣、油腻食物。 2.本品适用于肺热咳嗽，其表现为咳嗽，咯痰不爽，痰粘稠。 3.支气管扩张、肺脓疡、肺心病、肺结核患者应在医师指导下服用。 4.服用一周病证无改善，应停止服用，去医院就诊。 5.服药期间，若患者出现高热，体温超过38℃，或出现喘促气急者，或咳嗽加重，痰量明显增多者应到医院就诊。 6.孕妇、体质虚弱者慎用。 7.对本品过敏者禁用，过敏体质者慎用。 8.药品性状发生改变时禁止服用。 9.儿童必须在成人监护下使用。 10.请将此药品放在儿童不能接触的地方。 11.如正在服用其他药品，使用本品前请咨询医师或药师。 | L16: 如与其他药物同时使用可能会发生药物相互作用，详情请咨询医师或药师。 | N16: 密封 | O16: 每支装10毫升 | P16: 每盒6支，每盒6支，10支/盒，12支/盒 | Q16: 24个月
A17: 通用名称：盐酸卡替洛尔滴眼液 商品名称：美开朗 英文名称：Carteolol Hydrochloride Eye Drops 汉语拼音：Yansuan Katiluoer Diyanye | B17: 24.8 | C17: =IF(ISNUMBER(MATCH(#REF!,非处方药名称!A:A,0)),"非处方药","处方药") -> 处方药 | D17: 本品主要成份为：盐酸卡替洛尔。其化学名称为：5-[3-(1,1二甲基乙基)氨基]-2羟丙氧基-3,4-二氢-2（1H）-喹诺酮盐酸盐。分子式：C16H24N2O3HCl分子量：328.84 | E17: 本品为无色的澄明溶液。 | F17: 对原发性开角型青光眼具有良好的降低眼内压疗效。对于某些继发性青光眼，高眼压症，手术后未完全控制的闭角型青光眼以及其他药物及手术无效的青光眼，加用本品滴眼可进一步增强降眼压效果。 | G17: 滴眼，一日2次，一次1滴。滴于结膜囊内，滴后用手指压迫内毗角泪囊部3～5分钟。 | H17: 1.1/4的患者出现暂时性眼烧灼，眼刺痛及流泪，结膜充血水肿. 2.一些患者出现下列不良反应：视物模糊，畏光，上睑下垂，结膜炎，角膜着色及中度角膜麻醉。 3.长期连续用于无晶体眼或有眼底疾患者时，偶在眼底黄斑部出现浮肿，混浊，故需定期测定视力，进行眼底检查。 4.一些患者出现心率减慢及血压下降。 5.偶见下列不良反应：心率失常，心悸，呼吸困难，无力，头痛，头晕，失眠，鼻窦炎。 6.应用本品还有以下非常罕见不良反应： （1）全身症状：头痛。 （2）心血管系统：心率失常，晕厥，心传导阻滞，脑血管意外，脑缺血， | I17: 1 支气管哮喘者或有支气管哮喘史者，严重慢性阻塞性肺部疾病。 2 窦性心动过缓，Ⅱ或Ⅲ度房室传导阻滞，明显心衰，心源性休克。 3 对本品过敏者。 | J17: 1.本品慎用于已知是全身β-肾上腺能阻断剂禁忌症的患者，包括异常心动过缓，I度以上房室传导阻滞。 2.对有明显心脏疾病患者应用本品应监测脉搏。 3.本品慎用于对其他β-肾上腺能阻断剂过敏者。 4.已有肺功能低下的患者慎用。 5.本品慎用于自发性低血糖患者及接受胰岛素或降糖药治疗的患者，因β受体阻滞剂可掩盖低血糖症状。 6.本品不易单独用于治疗闭角型青光眼。 7.与其他滴眼液联合使用时，请间隔10分钟以上。 8.本品含氯化苯烷铵戴软性角膜接触镜者不宜使用。 9.定期复查眼压，根据眼压变化调整用药方案。 10 | K17: 儿童注意事项： 本品对于儿童的安全性和疗效尚未确立，请慎用。 妊娠与哺乳期注意事项： 本品对于孕妇的安全性尚未确立，孕妇应慎用。尚不清楚本品是否通过乳汁分泌，已知同类药物马来酸噻吗洛尔滴眼液滴眼后可在哺乳期妇女乳汁中测到，且对授乳婴儿具有多种潜在不良反应，所以哺乳期妇女应权衡利弊，在医生指导下使用。 老人注意事项： 尚不明确。 | L17: 1 与肾上腺素合用可引起瞳孔扩大。 2 正在服用儿茶酚胺耗竭药（如利血平）者，使用本品时应严密观察，因可引起低血压和明显的心动过缓。 3 不主张两种局部&beta;受体阻断剂同时应用，对正在应用&beta;受体阻断剂口服治疗的患者应慎用本品。 4 本品与钙通道拮抗剂合用应慎重，因可引起房室传导阻滞，左心室衰竭及低血压。对心功能受损的患者，应避免两种药合并使用。 5 本品与洋地黄类和钙通道拮抗剂合用可进一步延长房室传导时间。 6 酚噻嗪类药物可增加&beta;受体阻断剂的降血压作用，因可使相互的代谢途径受到抑制。 | M17: 药理作用： 1 盐酸卡替洛尔为非选择性&beta;-肾上腺受体阻断剂，对&beta;1和&beta;2受体均有阻断作用。盐酸卡替洛尔具有极小或不具有局麻作用。 2 卡替洛尔与其他&beta;受体阻断剂的主要区别在于它具有内在拟交感活性。 3 本品为盐酸卡替洛尔滴眼液，对高眼压和正常眼压患者均有降眼压作用，可使眼压下降22～25%。 4 卡替洛尔的主要代谢产物8-羟基-卡替洛尔是一种眼部&beta;受体阻断剂，也有降眼压作用，它可能与卡替洛尔降眼压作用持续时间较长有关。 5 本品的降眼压机制主要是减少房水生成，本品对房水经葡萄膜巩膜外流，房水流出易度及巩膜上静脉压无影响。非临床毒理研究： 致癌性：动物实验显示对大鼠和小鼠大量口服盐酸卡替洛尔连续2年不产生致癌毒性。致突变性：体内外动物实验未显示盐酸卡替洛尔有致突变活性。生殖毒性：动物实验显示大剂量口服盐酸卡替洛尔，对雄，雌性大鼠及小鼠的生殖功能均无影响。 | N17: 遮光，密闭保存。 | O17: 5毫升:100毫克 | Q17: 36月
A18: 通用名称：曲尼司特胶囊 商品名称：曲可伸 英文名称：Tranilast Capsules 汉语拼音：Qu Ni Si Te Jiao Nang | B18: 23.8 | C18: =IF(ISNUMBER(MATCH(#REF!,非处方药名称!A:A,0)),"非处方药","处方药") -> 处方药 | D18: 曲尼司特。 | E18: 胶囊。内含淡黄色粉末；无臭，无味。 | F18: 本品为抗变态反应药，可用于支气管哮喘及过敏性鼻炎的预防性治疗。 | G18: 口服。通常情况下，成人一日3次，一次1粒(0.1g);儿童一日5mg/kg，分3次服用。用于哮喘发作时与其他平喘药配伍用，或遵医嘱。 | H18: 1.肝脏：偶尔出现肝功能异常，需注意观察，可采取减量、停药等适当措施。 2.胃肠：有时发现食欲缺乏，恶心、呕吐、腹痛、腹胀、便秘、腹泻、胃部不适，偶有胃部不消化感。 3.血液：可有红细胞数和血色素量下降。 4.精神神经系统：头痛、嗜睡、偶尔头重、失眠、头昏、全身疲倦感等症状。 5.过敏反应：皮疹，偶见全身痒等过敏症状，此时应停药。 6.泌尿系统：偶见膀胱刺激症状，应停止用药。 7.其它：偶见心悸、浮肿、面部红晕、鼻出血、口腔炎等症状。 | I18: 1.孕妇忌用。 2.对本品成份过敏的患者禁用。 | J18: 1.本品能阻断过敏反应发生的环节，在哮喘好发季节前半月起服用，能起到预防作用。 2.本品不同于支气管舒张剂以及肾上腺皮质激素，对已经发作的哮喘症状，不能迅速起效。 3.本品可与其它平喘药并用，以本品作为基础处方药，有规则地服用。 4.激素依赖性患者使用本品时，激素用量应慢慢减少，不可突然停用。 5.肝、肾功能异常者慎用。 | K18: 儿童注意事项： 尚不明确。 妊娠与哺乳期注意事项： 1.妊娠（特别是3个月以内）和有可能妊娠的妇女，禁用。 2.哺乳妇女服用时应避免授乳。 老人注意事项： 尚不明确。 | L18: 与抗凝血药物华法令合用或终止合用时，可增强或减弱其作用并降低或增高血栓试验值，故在临床合用或终止合用时应注意观察凝血功能的变化。 | M18: 有稳定肥大细胞和嗜碱粒细胞的细胞膜作用，阻止其脱颗粒，从而抑制组胺、5-羟色胺过敏性反应物质的释放，对于1gE抗体引起的大白鼠皮肤过敏反应和实验性哮喘有显著抑制作用。 | N18: 密封，在干燥处保存。 | O18: 0.1克 | Q18: 36个月
A19: 通用名称：蓝芩口服液 商品名称：扬子江 英文名称：LanQinKouFuYe(YangZiJiang) 汉语拼音：Lanqin Koufuye | B19: 32.1 | C19: =IF(ISNUMBER(MATCH(#REF!,非处方药名称!A:A,0)),"非处方药","处方药") -> 处方药 | D19: 板蓝根、黄芩、栀子、黄柏、胖大海。 | E19: 本品为棕红色的澄清液体；味甜、微苦。 | F19: 清热解毒，利咽消肿。用于急性咽炎、肺胃实热证所致的咽痛、咽干、咽部灼热。 | G19: 口服。一次20毫升（2支），一日3次。 | H19: 个别患者服药后出现轻度腹泻，一般可自行缓解。 | I19: 尚不明确。 | J19: 1.忌烟酒。辛辣。鱼腥食物。 2.不宜在服药期间同时服用温补性中药。 3.孕妇慎用。糖尿病患者、儿童应在医师指导下服用。 4.脾虚大便溏者慎用。 5.属风寒感冒咽痛者，症见恶寒发热，无汗、鼻流清涕者慎用。 6.服药3天症状无缓解，应去医院就诊。 7.对本品过敏者禁用，过敏体质者慎用。 8.本品性状发生改变时禁止使用。 9.儿童必须在成人监护下使用。 10.请将本品放在儿童不能接触的地方。 11.如正在使用其他药品，使用本品前请咨询医师或药师。 | L19: 如与其他药物同时使用可能会发生药物相互作用，详情请咨询医师或药师。 | M19: 清热解毒，利咽消肿。 | N19: 密封，置阴凉处（不超过20℃），在贮藏期间允许有少量轻摇易散的沉淀。 | O19: 每支10毫升 | P19: 10ml*6支/盒
A20: 通用名称：四味珍层冰硼滴眼液 商品名称：珍视明 英文名称：siweizhencengbingpengdiyanye(zhenshimingdiyanye) 汉语拼音：Siweizhencenbinpeng Diyanye | B20: 21.2 | C20: =IF(ISNUMBER(MATCH(#REF!,非处方药名称!A:A,0)),"非处方药","处方药") -> 处方药 | D20: 珍珠层粉、天然冰片、硼砂、硼酸。辅料：氯化钠、乙醇、注射用水、苯氧乙醇。 | E20: 本品为近无色或微黄色的澄明液体。气香。 | F20: 清热解痉，去翳明目。用于肝阴不足，肝气偏盛所致的不能久视、青少年远视力下降；青少年假性近视、视力疲劳。 | G20: 滴于眼睑内。一次1-2滴，一日3-5次；必要时可酌情增加。 | H20: 尚不明确。 | I20: 尚不明确。 | J20: 1.本品为外用滴眼液，禁止内服。2.忌烟、酒、辛辣刺激性食物。3.眼部有炎症者应去医院就诊。4.用药后有沙涩磨痛、流泪频频、眼痒、眼睑皮肤潮红、眼胀者应停用，并到医院就诊。5.如视力下降明显应到医院就诊。6.滴眼时瓶口勿接触眼睛，使用后应将瓶盖拧紧，以免污染药液。7.用药7天症状无缓解，应去医院就诊。8.打开瓶盖后，15天内用完。9.对本品过敏者禁用，过敏体质者慎用。10.本品性状发生改变时禁止使用。11.儿童必须在成人监护下使用。12.请将本品放在儿童不能接触的地方。 | L20: 如与其他药物同时使用可能会发生药物相互作用，详情请咨询医师或药师。 | M20: 珍珠明目液由珍珠水解液与冰片配伍制成，珍珠水解液中主要成份为珍珠，珍珠具有镇心安神，养阴熄火，清热隧痰，去翳明目，解毒生肌的功能，现代药理学研究表明，珍珠具有延缓衰老，抗氧化作用，抗肿瘤作用，促进创面肉芽增生作用及降低心肌和脑组织脂褐素作用。 冰片具有通诸窍，散郁火，去翳明目，消肿止痛的功能。药理研究表明，龙脑具有明显的镇痛作用，抗炎作用及抗菌作用，局部应用对感觉神经有轻微刺激及上痛和防腐作用。冰片经粘膜，皮下组织均易吸收。 | N20: 密封，置凉暗处（避光并不超过20°C） | O20: 每瓶装8毫升;每瓶装13毫升;每瓶装15毫升 | P20: 塑料瓶，每小盒装一瓶。
A21: 通用名称：复方硫酸软骨素滴眼液 商品名称：润洁 英文名称：Compound Chondroitin Sulfate Eye Drops 汉语拼音：Fufang Liusuan Ruangaosu Diyanye | B21: 19.7 | C21: =IF(ISNUMBER(MATCH(#REF!,非处方药名称!A:A,0)),"非处方药","处方药") -> 处方药 | D21: 本品为复方制剂，其主要成分为每毫升含硫酸软骨素钠1毫克、维生素E0.1毫克、维生素B60.1毫克、尿囊素2毫克、牛磺酸2毫克。辅料为：玻璃酸钠、硼酸、硼砂、冰片、薄荷脑、无水乙醇、聚山梨酯80、三氯叔丁醇。 | E21: 本品为无色澄明或微带乳光的液体。 | F21: 用于视疲劳，干眼症。 | G21: 滴入眼内。一日4～6次，或有需要时滴眼;一次2～3滴。 | H21: 临床研究中报道偶有患者出现轻度眼分泌物增多及眼部不适感。 | I21: 尚不明确。 | J21: 1.本品仅供滴眼使用。 2.滴眼时请勿使管口接触手和眼睛，避免污染瓶内眼药水 3.若出现眼睛充血、发痒、红肿等较严重刺激症状时，应停止使用，并咨询医师或药师。 4.眼睛剧烈疼痛患者、青光眼患者使用前请咨询医生。 5.对本品过敏者禁用，过敏体质者慎用。 6.本品性状发生改变时禁止使用。 7.请将本品放在儿童不能接触的地方。 8.儿童必须在成人监护下使用。 9.如正在使用其他药品，使用本品前请咨询医师或药师。 | K21: 儿童注意事项： 尚不明确。 妊娠与哺乳期注意事项： 尚不明确。 老人注意事项： 尚不明确。 | L21: 如与其他药物同时使用可能会发生药物相互作用，详情请咨询医师或药师。 | M21: 硫酸软骨素为一种酸性粘多糖，是眼组织中的重要成份之一，具有促进角膜水分代谢、改善微循环、保护角膜并促进角膜组织损伤修复的功能，同时还可在角膜表面形成一层保护膜，防止水分散发，有效缓解视疲劳和干眼症状;牛磺酸除可抗菌消炎外，在眼组织内还参与多种生理活动，促进新陈代谢，改善视疲劳。 | N21: 密闭，在阴凉处。 | O21: 5ml;10ml | Q21: 24个月
A22: 通用名称：清热消炎宁胶囊 商品名称：敬修堂 英文名称：QingReXiaoYanNingJiaoNang(JingXiuTang) 汉语拼音：Qingrexiaoyanning Jiaonang | B22: 13.5 | C22: =IF(ISNUMBER(MATCH(#REF!,非处方药名称!A:A,0)),"非处方药","处方药") -> 处方药 | D22: 主要成分：丸节茶。 | E22: 本品为胶囊剂，内容物为黑褐色的粉末；味微苦、涩。 | F22: 清热解毒，消炎止痛，舒筋活络。适用于流行性感冒，咽喉炎，肺炎，细菌性痢疾，急性胃肠炎，阑尾炎，烧伤，疮疡脓肿，蜂窝组织炎。 | G22: 口服。一次2～4粒，一日3次。外用。将内容物加温开水溶化后，按患处大小搽敷，一日2～3次。 | H22: 尚不明确。 | I22: 尚不明确。 | J22: 1.忌烟、酒及辛辣、生冷、油腻食物。 2.不宜在服药期间同时服用滋补性中药。 3.发高烧体温超过38.5℃的患者，请上医院就诊。 4.高血压、心脏病、肝病、糖尿病、肾病等慢性病严重者应在医师指导下服用。 5.服药3天症状无缓解，应去医院就诊。 6.儿童、年老体弱者、孕妇应在医师指导下服用。 7.对本品过敏者禁用，过敏体质者慎用。 8.本品性状发生改变时禁止使用。 9.儿童必须在成人监护下使用。 10.请将本品放在儿童不能接触的地方。 11.如正在使用其他药品，使用本品前请咨询医师或药师。 | L22: 如与其他药物同时使用可能会发生药物相互作用，详情请咨询医师或药师。 | N22: 密封保存。 | O22: 每粒装0.32克 | Q22: 36个月。
A23: 通用名称：重感灵片 商品名称：嘉应 英文名称：ZhongGanLingPian(JiaYing) 汉语拼音：Zhongganmao Pian | B23: 6.5 | C23: =IF(ISNUMBER(MATCH(#REF!,非处方药名称!A:A,0)),"非处方药","处方药") -> 处方药 | D23: 毛冬青羌活葛根石膏马鞭草板蓝根青蒿马来酸氯苯那敏安乃近 | E23: 本品为黄色的糖衣片，除去糖衣后显棕褐色；味苦。 | F23: 解表清热，消炎止痛。用于治疗恶寒，高热，四肢酸痛，鼻塞，咽喉肿痛，咳嗽等重症感冒，流行性感冒，四时感冒的各种症状。 | G23: 口服。一次6～8片，一日3～4次。 | H23: 本品偶有粒细胞减少及过敏性皮疹反应 | I23: 尚不明确 | J23: 用药期间不宜驾驶车辆、管理机器及高空作业等。 | L23: 如与其他药物同时使用可能会发生药物相互作用，详情其咨询医师或药师。 | N23: 密封 | O23: 糖衣：每片含安乃近31.25毫克，马来酸氯苯那敏0.375毫克；薄膜衣：片重0.51克(含安乃近62.5毫克，马来酸氯苯那敏0.75毫克) | P23: 48片 | Q23: 36月
A24: 通用名称：氧氟沙星眼膏 商品名称：迪可罗 英文名称：Ofloxacin Eye Ointment 汉语拼音：Yangfu Shaxing Yangao | B24: 18.3 | C24: =IF(ISNUMBER(MATCH(#REF!,非处方药名称!A:A,0)),"非处方药","处方药") -> 处方药 | D24: 本品主要成分为：氧氟沙星。 | E24: 白色或类白色的软膏。 | F24: 适用于治疗细菌性结膜炎，角膜炎，角膜溃疡，泪囊炎，术后感染等外眼感染。 | G24: 局部用药:涂于眼睑内，一日3次，一次适量，或遵医嘱。 | H24: 偶尔有一过性刺激症状,不影响用药。 | I24: 对氧氟沙星或其它喹诺酮类药物过敏者禁用。 | J24: 1.品不宜长期使用。 2.用中出现过敏症状,应立即停止使用。 | K24: 儿童注意事项： 尚不明确。 妊娠与哺乳期注意事项： 尚不明确。 老人注意事项： 尚不明确。 | L24: 氧氟沙星与抗凝剂之间的相互作用不明显，本品与头孢噻肟、甲硝唑、克林霉素、环孢菌素等同用后，各药物的药动学过程均无明显改变。 | M24: 通过抑制细菌的DNA旋转酶和DNA复制而发挥作用。由于其独特的作用机理，具有抗菌谱广，抗菌活性强的特点，对革兰阳性菌，阴性菌群均有较强的抗菌作用。对葡萄球菌，化脓性链球菌，溶血性链球菌，肠球菌，肺炎球菌，大肠杆菌，柠檬酸细菌属，肺炎杆菌，肠菌属，沙雷氏菌属，变形杆菌属，铜绿假单胞菌，流感嗜血杆菌，不动杆菌属，弯曲杆菌属，衣原体属敏感性菌种等感染有效.本品与其他类抗菌药未见交叉耐药性。 | N24: 密封,在阴凉干燥处保存. | O24: 3.5克:10.5毫克 | Q24: 24个月
A25: 通用名称：咽炎片 商品名称：999 英文名称：YanYanPian(999) 汉语拼音：Yanyan Pian | B25: 15.8 | C25: =IF(ISNUMBER(MATCH(#REF!,非处方药名称!A:A,0)),"非处方药","处方药") -> 处方药 | D25: 玄参、板蓝根、天冬、麦冬、牡丹皮、百部(制)、青果、款冬花(制)、木蝴蝶、地黄、蝉蜕、薄荷油。 | E25: 本品为糖衣片;除去糖衣后显棕褐色，微苦、辛。 | F25: 养阴润肺，清热解毒，清利咽喉，镇咳止痒。用于慢性咽炎引起咽干，咽痒，刺激性咳嗽。 | G25: 口服。一次5片，一日3次。 | H25: 详见说明书。 | I25: 对本药品任何成分过敏者禁用。 | J25: 1 忌辛辣、鱼腥食物。 2 孕妇慎用。 3 服药七天后症状无改善，或出现其他症状，应去医院就诊。 4 按照用法用量服用，儿童应在医师指导下服用。 5 药品性状发生改变时禁止服用。 6 儿童必须在成人的监护下使用。 7 请将此药品放在儿童不能接触的地方。 8 如正在服用其他药物，使用本品前请咨询医师或药师。 | K25: 妊娠与哺乳期注意事项： 孕妇慎用。 | L25: 如与其他药物同时使用可能会发生药物相互作用，详情请咨询医师或药师。 | M25: 养阴润肺，清热解毒，清利咽喉，镇咳止痒。 | N25: 密封。 | O25: 每片重0.25克 | P25: 12粒*2板/盒 | Q25: 24个月
A26: 通用名称：喉疾灵胶囊 商品名称：陈李济 英文名称：HouJiLingJiaoNang(ChenLiJi) 汉语拼音：Houjiling Jiaonang | B26: 24.8 | C26: =IF(ISNUMBER(MATCH(#REF!,非处方药名称!A:A,0)),"非处方药","处方药") -> 处方药 | D26: 牛黄、板蓝根、山豆根、桔梗、诃子、了哥王、天花粉、连翘、冰片、珍珠层粉、广东土牛膝、猪牙皂。 | E26: 本品为胶囊剂，内容物为棕褐色的粉末；气芳香，味苦。 | F26: 清热，解毒，消肿止痛。用于扁桃体炎，急性咽炎，慢性咽炎急性发作。 | G26: 口服。一次3～4粒，一日3次。 | H26: 尚不明确。 | I26: 孕妇禁用。 | J26: 1 忌烟酒、辛辣、鱼腥食物。 2 不宜在用药期间同时服用温补性中药。 3 脾虚大便溏者慎用。 4 属风寒感冒咽痛者，症见恶寒发热、无汗、鼻流清涕者慎用。 5 严格按照用法用量服用，儿童、年老体弱者应在医师指导下服用。 6 扁桃体有化脓及全身高热者应去医院就诊。 7 服药3天症状无缓解，应去医院就诊。本品不宜长期服用。 8 对本品过敏者禁用，过敏体质者慎用。 9 本品性状发生改变时禁止使用。 10 儿童必须在成人监护下使用。 11 请将本品放在儿童不能接触的地方。 12 如正在使用其他药品，使用本品前请咨询医师或药师。 | L26: 如与其他药物同时使用可能会发生药物相互作用，详情请咨询医师或药师。 | M26: 尚不明确。 | N26: 密封。 | O26: 每粒装0.25克
A27: 通用名称：宣肺止嗽合剂 商品名称：普安康 英文名称：XuanFeiZhiSuHeJi(PuAnKang) 汉语拼音：Xuanfei Zhisu Heji | B27: 31 | C27: =IF(ISNUMBER(MATCH(#REF!,非处方药名称!A:A,0)),"非处方药","处方药") -> 处方药 | D27: 荆芥、前胡、桔梗、百部（蜜炙）、紫菀（蜜炙）、陈皮、鱼腥草、薄荷、罂粟壳（蜜炙）、甘草（蜜炙）。 | E27: 本品为红棕色至棕褐色的液体；气芳香，味微甜。 | F27: 疏风宣肺，止咳化痰。用于咳嗽属风邪犯肺证，症见咳嗽、咽痒、鼻塞流涕、恶寒发热、咯痰等。 | G27: 口服。每次20毫升，一日3次。 | H27: 尚不明确。 | I27: 尚不明确。 | J27: 1忌烟、酒及辛辣、生冷、油腻食物。 2不宜在服药期间同时服用滋补性中药。 3支气管扩张、肺脓疡、肺心病、肺结核患者出现咳嗽时应去医院就诊。 4糖尿病患者及有高血压、心脏病、肝病、肾病等慢性病严重者应在医师指导下服用。 5尚未有孕妇、儿童临床应用的研究资料。哺乳期妇女、年老体弱者应在医师指导下服用。 6服药期间，若患者发热体温超过38.5℃，或出现喘促气急者，或咳嗽加重、痰量明显增多者应去医院就诊。 7严格按用法用量服用，本品不宜长期服用。 8服药3天症状无缓解，应去医院就诊。 9对本品过敏者禁用，过敏体质 | L27: 如与其他药物同时使用可能会发生药物相互作用，详情请咨询医师或药师。 | N27: 密封。 | O27: 20ml/支;100ml/瓶 | Q27: 24月
A28: 通用名称：桑菊感冒片 商品名称：同仁堂 英文名称：SangJuGanMaoPian(TongRenTang) 汉语拼音：Sanju Ganmao Pian | B28: 11.4 | C28: =IF(ISNUMBER(MATCH(#REF!,非处方药名称!A:A,0)),"非处方药","处方药") -> 处方药 | D28: 桑叶、菊花、连翘、苦杏仁、桔梗、芦根、薄荷油、甘草。 | E28: 本品为淡棕色至棕褐色的片；气微香，味微苦。 | F28: 疏风清热，宣肺止咳。用于风热感冒初起，头痛，咳嗽，口干，咽痛。 | G28: 口服。一次4-8片，一日2-3次。 | H28: 尚不明确。 | I28: 尚不明确。 | J28: 1 忌烟、酒及辛辣、生冷、油腻食物。 2 不宜在服药期间同时服用滋补性中药。 3 风寒感冒者不适用。 4 有高血压、心脏病、肝病、糖尿病、肾病等慢性病严重者应在医师指导下服用。 5 儿童、孕妇、哺乳期妇女、年老体弱及脾虚便溏者应在医师指导下服用。 6 服药3天症状无缓解，应去医院就诊。 7 对本品过敏者禁用，过敏体质者慎用。 8 本品性状发生改变时禁止使用。 9 儿童必须在成人监护下使用。 10 请将本品放在儿童不能接触的地方。 11 如正在使用其他药品，使用本品前请咨询医师或药师。 | L28: 如与其他药物同时使用可能会发生药物相互作用，详情请咨询医师或药师。 | N28: 密封，置于阴凉处。 | O28: 素片：每片重0.6克；薄膜衣片：每片重0.62克 | P28: 塑料瓶装，每瓶装40片，0.6g*40s*2瓶/套，0.6g*40s*5瓶/套 | Q28: 36个月
A29: 通用名称：复方草珊瑚含片 商品名称：江中 英文名称：FuFangCaoShanHuHanPian(JiangZhong) 汉语拼音：Fu Fang Cao Shan Hu Han Pian | B29: 5.7 | C29: =IF(ISNUMBER(MATCH(#REF!,非处方药名称!A:A,0)),"非处方药","处方药") -> 处方药 | D29: 肿节风、薄荷脑、薄荷素油。 | E29: 本品为粉红色至棕红色的薄膜衣片，气香、味甜、清凉。 | F29: 疏风清热，消肿止痛，清利咽喉。用于外感风热所致的咽喉肿痛，声哑失音；急性咽喉炎属风热证者。 | G29: 含服。一次2片(小片)，每隔2小时一次，一日6次；或一次1片(大片)，每隔2小时1次，一日5～6次。 | H29: 尚不明确。 | I29: 对本药品过敏者禁用。 | J29: 1 忌烟酒、辛辣、鱼腥食物。 2 不宜在服药期间同时服用滋补性中药。 3 有高血压、心脏病、肝病、糖尿病、肾病等慢性病严重者应在医师指导下服用。 4 儿童、孕妇、哺乳期妇女、年老体弱、脾虚便溏者应在医师指导下服用。 5 声哑失音较重者，应及时去医院就诊。 6 服药3天症状无缓解，应去医院就诊。 7 对本品过敏者禁用，过敏体质者慎用。 8 本品性状发生改变时禁止使用。 9 儿童必须在成人监护下使用。 10 请将本品放在儿童不能接触的地方。 11 如正在使用其他药品，使用本品前请咨询医师或药师。 | L29: 如与其他药物同时使用可能会发生药物相互作用，详情请咨询医师或药师。 | M29: 疏风清热，消肿止痛，清利咽喉。 | N29: 密封。 | O29: 每片重0.44克(小片) | P29: PVC铝箔，每板装12片，每盒装4板，PVC铝箔，12s*10板/盒
A30: 通用名称：耳聋左慈丸 商品名称：同仁堂 英文名称：ErLongZuoCiWan 汉语拼音：Er long Zuo ci Wan | B30: 15.8 | C30: =IF(ISNUMBER(MATCH(#REF!,非处方药名称!A:A,0)),"非处方药","处方药") -> 处方药 | D30: 磁石(煅)、熟地黄、山茱萸(制)、山药、牡丹皮、泽泻、茯苓、竹叶柴胡。 | E30: 本品为棕黑色的浓缩丸；味甘、微酸。 | F30: 滋肾平肝。用于肝肾阴虚的耳鸣耳聋，头晕目眩。 | G30: 口服。一次8丸，一日3次。 | H30: 尚不明确。 | I30: 尚不明确。 | J30: 1.忌烟酒、辛辣刺激性食物。 2.感冒时不宜服用。 3.有高血压、心脏病、肝病、糖尿病、肾病等慢性病严重者应在医师指导下服用。 4.儿童、孕妇、哺乳期妇女、年老体弱者应在医师指导下服用。 5.本品只用于肝肾阴虚证之听力逐渐减退，耳鸣如蝉声者，凡属外耳、中耳病变而出现的耳鸣，如外耳道异物等，应去医院就诊。 6.突发耳鸣耳聋者应去医院就诊。 7.服药2周症状无缓解，应去医院就诊。 8.对本品过敏者禁用，过敏体质者慎用。 9.本品性状发生改变时禁止使用。 10.儿童必须在成人监护下使用。 11.请将本品放在儿童不能接触的地方。 12.如正在使用其他药品，使用本品前请咨询医师或药师。 | K30: 儿童注意事项： 应在医师指导下服用。 妊娠与哺乳期注意事项： 应在医师指导下服用。 老人注意事项： 应在医师指导下服用。 | L30: 如与其他药物同时使用可能会发生药物相互作用，详情请咨询医师或药师。 | N30: 密封，防潮 | O30: 每10丸重1g | P30: 每丸重0.19g，每瓶装60g。
A31: 通用名称：鼻渊通窍颗粒 商品名称：鲁南 英文名称：BiYuanTongQiaoKeLi(LuNan) 汉语拼音：Biyuan Tongqiao Keli | B31: 21.6 | C31: =IF(ISNUMBER(MATCH(#REF!,非处方药名称!A:A,0)),"非处方药","处方药") -> 处方药 | D31: 辛夷、苍耳子(炒)、麻黄、白芷、薄荷、藁本、黄芩、连翘、野菊花、天花粉、地黄、丹参、茯苓、甘草。 | E31: 本品为棕色至棕褐色的颗粒；气微香，味甜、微苦。 | F31: 疏风清热，宣肺通窍。用于急鼻渊（急性鼻窦炎）属外邪犯肺证，症见前额或颧骨部压痛，鼻塞时作，流涕黏白或黏黄，或头痛，或发热，苔薄黄或白，脉浮。 | G31: 开水冲服。一次1袋，一日3次。 | H31: 偶见腹泻。 | I31: 尚不明确。 | J31: 需在医生指导下用药；脾虚腹胀者慎用；服药期间勿食辛、辣等食物。 | L31: 如与其他药物同时使用可能发生药物相互作用，详情请咨询医师或药师。 | M31: 药理试验表明，本品对组胺和5-羟色胺所致的大鼠毛细血管通性增高、大鼠皮下棉球肉芽肿增生有一定的抑制作用；可增加小鼠碳粒廓清能力，促进环磷酰胺所致免疫功能低下小鼠的血清溶血素生成。 | N31: 密闭，防潮。 | O31: (1)每袋装10克(2)每袋装15克 | P31: 铝塑和服袋装，每盒装10袋，15g*15袋/盒，15g*21袋/盒，15g*10袋+1.2g*30s*1瓶/套，15g*10袋+1.2g*30s*1瓶/套，15g*10袋+1000mg*30s/套，，，
A32: 通用名称：冰珍去翳滴眼液 商品名称：白内停 英文名称：BingZhenQuYiDiYanYe(BaiNeiTing) 汉语拼音：Bingzhenquyi Diyanye | B32: 31.6 | C32: =IF(ISNUMBER(MATCH(#REF!,非处方药名称!A:A,0)),"非处方药","处方药") -> 处方药 | D32: 冰片、珍珠等 | E32: 本品为液状。 | F32: 去翳明目。用于老年性白内障初发期。 | G32: 滴于眼睑内，一次1～2滴，一日3～4次，滴眼后闭目2～3分钟。 | H32: 偶尔有轻度蛰样刺激感。 | I32: 眼部有创伤及溃疡者禁用。 | J32: 1.本品为外用滴眼药，禁止内服。 2.忌烟、酒、辛辣刺激性食物。 3.眼部有炎症者慎用。 4.用药后有眼痒，眼睑皮肤潮红，眼胀或过敏现象者停用，并到医院就诊。 5.如视力下降明显应到医院就诊。 6.治疗过程中局部出现炎症反应，立即停药并到医院就诊。 7.打开瓶盖后，15天内用完。 8.对本品过敏者禁用，过敏体质者慎用。 9.药品性状发生改变时禁止使用。 10.请将此药品放在儿童不能接触的地方。 11.如正在使用其他药品，使用本品前请咨询医师或药师。 | K32: 儿童注意事项： 尚不明确。 妊娠与哺乳期注意事项： 尚不明确。 老人注意事项： 尚不明确。 | L32: 如与其他药物同时使用可能会发生药物相互作用，详情请咨询医师或药师。 | M32: 尚不明确 | N32: 遮光，密闭保存。 | O32: 10ml | Q32: 24月
A33: 通用名称：雷公藤多苷片 商品名称：千金协力 英文名称：Tripterygium Glycosides 汉语拼音：Leigongtengduogan Pian | B33: 19.5 | C33: =IF(ISNUMBER(MATCH(#REF!,非处方药名称!A:A,0)),"非处方药","处方药") -> 处方药 | D33: 本品主要成分为雷公藤多甙。 | E33: 本品为浅黄色片；味微苦、涩 | F33: 祛风解毒、除湿消肿、舒筋通络。有抗炎及抑制细胞免疫和体液免疫等作用。用于风湿热瘀，毒邪阻滞所致的类风湿性关节炎，肾病综合症，白塞氏三联症，麻风反应，自身免疫性肝炎等。 | G33: 口服。每日每千克体重1～1．5毫克，分3次饭后服。一般首次应给足量，控制症状后减量。宜在医师指导下服用。 | H33: 1.消化系统：口干、恶心、 呕吐、乏力、食欲不振、腹胀、腹泻、黄疽、转氨酶升高；严重者可出现急性中毒性肝损伤、胃出血。2.血液系统：白细胞，血小板下降；严重者可出现粒细胞缺乏和全血细胞减少。3.泌尿系统：少尿或多尿、水肿、肾功能异常等肾脏损害；严重者可出现急性肾功能衰竭。4.心血管系统：心悸、胸闷、心律失常、血压升高或下降、心电图异常。5.生殖、内分泌系统：女子月经紊乱、月经量少或闭经；男子梢子数量减少、活力下降。6.神经系统：头昏、头辇、嗜睡，失眠、神经炎、复视。7.其他：皮疹、瘙痒、脱发、面部色素沉着。 | I33: 1.儿童、育龄期有孕育要求者、孕妇和哺乳期妇女禁用。 2.心、肝、肾功能不全者禁用;严重贫血、白细胞和血小板降低者禁用。 3.胃、十二指肠溃疡活动期患者禁用。 4.严重心律失常者禁用。 | J33: 1.服药期间可引起月经紊乱，精子活力及数目减少，白细胞及血小板减少，停药后可恢复。2.有严重心脑血管和老年患者慎用。3.孕妇忌用。4.本品在医生指导下严格按照说明书规定剂量用药，不可超量使用。5.用药期间应注意定期随诊并检査血、尿常规及心电图和肝肾功能，必要时停药并给予相应处理。6.连续用药一般不宜超过3个月。如继续用药，应由医生根据患者病情及治疗需要决定。 | K33: 儿童注意事项： 儿童禁用。 妊娠与哺乳期注意事项： 育龄期有孕育要求者、孕妇和哺乳期妇女禁用。 老人注意事项： 老年患者慎用。 | L33: 如与其他药物同时使用可能会发生药物相互作用，详情请咨询医师或药师。 | M33: 本品具有较强的抗炎及免疫抑制作用。在抗炎作用方面，它能拮抗和抑制炎症介质的释放、实验性炎症及关节炎的反应程度。在抑制免疫作用方面，它能抑制体液免疫和细胞免疫反应。 | N33: 避光、置阴凉(不超过20℃)干燥处密闭保存。 | O33: 10毫克 | P33: 口服固体药用高密度聚乙烯瓶包装。每瓶50片。 | Q33: 48个月。
A34: 通用名称：双氯芬酸钠滴眼液 商品名称：迪非 英文名称：Diclofenac Sodium Eye Drops 汉语拼音：Shuanglvfensuanna Diyanye | B34: 17.6 | C34: =IF(ISNUMBER(MATCH(#REF!,非处方药名称!A:A,0)),"非处方药","处方药") -> 处方药 | D34: 主要成分为双氯芬酸钠，化学名称为2-[(2,6-二氯苯基)氨基]苯乙酸钠。 | E34: 本品为无色或微黄色澄明水溶液。 | F34: 1.用于治疗葡萄膜炎、角膜炎、巩膜炎，抑制角膜新生血管的形成，治疗眼内手术后、激光滤帘成形术后或各种眼部损伤的炎症反应，抑制白内障手术中缩瞳反应；2.用于准分子激光角膜切削术后止痛及消炎；春季结膜炎、季节过敏性结膜炎等过敏性眼病，预防和治疗白内障及人工晶体术后炎症及黄斑囊样水肿，以及青光眼滤过术后促进滤过泡形成等。 | G34: 一日4～6次，一次1滴；眼科手术用药：术前3、2、1和0.5小时各滴眼一次，一次1滴。白内障术后24小时开始用药，一日4次，持续用药二周；角膜屈光术后15分钟即可用药，一日4次，持续用药三天。 | H34: 滴眼有短暂烧灼、刺痛、流泪等，极少数可有结膜充血、视物模糊。不足3%患者可出现乏力、困倦、恶心等全身反应。 | I34: 对本品过敏者禁用。 | J34: 1.本品仅限于滴眼用。 2.本品可妨碍血小板凝聚，有增加眼组织术中或术后出血的倾向。 3.戴接触镜者禁用本品，但角膜屈光术后暂时配戴治疗性亲水软镜者除外。 | K34: 儿童注意事项： 本品在儿童的安全性和作用尚未考察。 妊娠与哺乳期注意事项： 在动物致畸研究中，给小鼠用药量至人局部用量的5000倍(20mg/kg/day)，大鼠和兔用至2500倍（10mg/kg/day），均未发现致畸作用，尽管这些量已经达到对母体和胎儿产生毒性。大鼠母体对双氯芬酸钠的毒性表现为难产，妊娠延长，胎儿体重、生长和成活率下降。已经显示，双氯芬酸钠可透过大鼠和小鼠的胎盘屏障。但目前尚无在人体的研究报告，因此孕妇应慎用。 老人注意事项： 尚不明确。 | L34: 尚不明确。 | M34: 双氯芬酸钠是一种衍生于苯乙酸类的非甾体消炎镇痛药，其作用机理为抑制环氧化酶活性，从而阻断花生四烯酸向前列腺素的转化。同时，它也能促进花生四烯酸与甘油三脂结合，降低细胞内游离的花生四烯酸浓度，而间接抑制白三烯的合成。动物实验证实，前列腺素是引起眼内炎症的介质之一，能导致血-房水屏障崩溃、血管扩张、血管通透性增加、白细胞趋化、非胆碱能机制性瞳孔缩小等。双氯芬酸钠是非甾体消炎药中作用较强的一种，它对前列腺素合成的抑制作用强于阿司匹林和消炎痛等。双氯芬酸钠滴眼液对机械、化学、生物等刺激引起的血-房水屏障崩溃有较强的抑制作用。临床研究显示，0.1%双氯芬酸钠治疗白内障术后炎症，可降低前房的闪辉和细胞数；应用于角膜放射状切开术或激光屈光角膜切削术的病人，能缓解术后疼痛和畏光，优于安慰剂 | N34: 置凉暗处密闭保存。 | O34: 5毫升:5毫克 | Q34: 24个月
A35: 通用名称：马来酸噻吗洛尔滴眼液 商品名称：五景 英文名称：Timolol Maleate Eye Drops 汉语拼音：Malaisuansaimaluoer Diyanye | B35: 8.3 | C35: =IF(ISNUMBER(MATCH(#REF!,非处方药名称!A:A,0)),"非处方药","处方药") -> 处方药 | D35: 本品主要成份为：马来酸噻吗洛尔。其化学名称为：(-)-1-(叔丁氨基)-3-[(4-吗啉基-1,2,5-噻二唑-3-基)氧]-2-丙醇顺丁烯二酸盐。分子式：C13H24N4O3SC4H4O4分子量：432.49 | E35: 本品为无色的澄明液体。 | F35: 对原发性开角型青光眼具有良好的降低眼内压疗效。对于某些继发性青光眼，高眼压症，部分原发性闭角型青光眼以及其他药物及手术无效的青光眼，加用本品滴眼可进一步增强降眼压效果。 | G35: 滴眼，一次1滴，一日1～2次，如眼压已控制，可改为一日1次。如原用其他药物，在改用本品治疗时，原药物不易突然停用，应自滴用本品的第二天起逐渐停用。 | H35: 1 最常见的不良反应是眼烧灼感及刺痛。 2 心血管系统：心动过缓，心率失常。 3 神经系统：头晕，加重重症肌无力的症状，感觉异常，嗜睡，失眠，恶梦，抑郁，精神错乱，幻觉。 4 呼吸系统：支气管痉挛，呼吸衰竭，呼吸困难，鼻腔充血，咳嗽，上呼吸道感染。 5 内分泌系统：掩盖糖尿病患者应用胰岛素或降糖药后的低血糖症状。 | I35: 1 支气管哮喘者或有支气管哮喘史者，严重慢性阻塞性肺部疾病。 2 窦性心动过缓，Ⅱ或Ⅲ度房室传导阻滞，明显心衰，心源性休克。 3 对本品过敏者。 | J35: 1 当出现呼吸急促、脉搏明显减慢、过敏等症状时，请立即停止使用本品。 2 使用中若出现脑供血不足症状时应立即停药。 3 心功能损害者，使用本品时应避免服用钙离子拮抗剂。 4 对无心衰史的患者，如出现心衰症状应立即停药。 5 正在服用儿茶酚胺耗竭药（如利血平）者，使用本品时应严密观察。 6 冠状动脉疾患、糖尿病、甲状腺机能亢进和重症肌无力患者，用本品滴眼时需遵医嘱。 7 本品慎用于自发性低血糖患者及接受胰岛素或口服降糖药治疗的患者，因&beta;受体阻滞剂可掩盖低血糖症状。 8 本品不易单独用于治疗闭角型青光眼。 9 与其他滴眼液联合使用时，请间隔10分钟以上。 10 定期复查眼压，根据眼压变化调整用药方案。 11 用前应摇匀，避免容器尖端接触眼睛，防止滴眼液污染。 | K35: 儿童注意事项： 未进行该项实验且无可靠参考文献。 妊娠与哺乳期注意事项： 本品对于孕妇的安全性尚未确定。 滴眼后可在哺乳期妇女乳汁中测到本品，因对授乳婴儿具有多种潜在不良反应，需根据滴用本品对母亲的重要性决定终止哺乳或终止用药。 老人注意事项： 未进行该项实验且无可靠参考文献。 | L35: 1 与肾上腺素合用可引起瞳孔扩大。 2 不主张两种局部&beta;受体阻断剂同时应用。 3 本品与钙通道拮抗剂合用应慎重，因可引起房室传导阻滞，左心室衰竭及低血压。对心功能受损的患者，应避免两种药合并使用。 4 正在服用儿茶酚胺耗竭药（如利血平）者，使用本品时应严密观察，因可引起低血压和明显的心动过缓。 5 本品与洋地黄类和钙通道拮抗剂合用可进一步延长房室传导时间。 6 本品与奎宁丁合用能引起心率减慢等全身&beta;受体阻断的副作用。可能的原因是奎宁丁可抑制P450酶和CYPZD6对噻吗洛尔的代谢作用。 | M35: 马来酸噻吗洛尔是一种非选择性&beta;-肾上腺能受体阻滞剂，没有明显的内源性拟交感活性和局麻作用，对心肌无直接抑制作用。本品为马来酸噻吗洛尔滴眼剂，对高眼压患者和正常人均有降低眼内压作用。其降低眼内压的确切机理尚不清楚，眼压描记和房水荧光光度研究提示本品的降眼压作用与减少房水生成有关。非临床毒理研究：致癌性：动物实验显示长期大量口服马来酸噻吗洛尔可使雄性大鼠肾上腺嗜铬细胞瘤，雌性小鼠良性及恶性肺部肿瘤，良性子宫息肉及乳腺癌的发生率明显增高。生殖毒性：动物实验显示大剂量口服马来酸噻吗洛尔，对雄、雌性小鼠的生殖功能均无影响。 | N35: 室温下，避光贮存。 | O35: 5毫升:25毫克 | Q35: 24个月
A36: 通用名称：复方门冬维甘滴眼液 商品名称：新乐敦 英文名称：Compound Aspartate，Vitamin B6 and Dipotassium Glycyrrhetate Eye Drops 汉语拼音：WeiAnlin Diyanye | B36: 54 | C36: =IF(ISNUMBER(MATCH(#REF!,非处方药名称!A:A,0)),"非处方药","处方药") -> 处方药 | D36: 本品为复方制剂，每10毫升含门冬氨酸78毫克、维生素B65毫克、甘草酸二钾10毫克、盐酸萘甲唑林0.3毫克、甲硫酸新斯的明0.5毫克、马来酸氯苯那敏1毫克。辅料为：泛醇、薄荷脑、苯扎氯铵、吐温-80。 | E36: 本品为微黄色的澄明液体。 | F36: 用于抗眼疲劳，减轻结膜充血症状。 | G36: 滴眼，一次1-2滴，一日4-6次。 | H36: 偶见一过性刺激症状，不影响治疗。 | I36: 尚不明确。 | J36: 1.本品仅供眼用，切忌口服。 2.闭角型青光眼慎用。 3.滴眼时，瓶口勿接触手和眼睛，避免污染。 4.在使用过程中，如发现眼红、疼痛等情况，应停药就医。 5.使用后应将瓶盖拧紧以免污染药品。 6.对本品过敏者禁用，过敏体质者慎用。 7.本品性状发生改变时禁止使用。 8.请将本品放在儿童不能接触的地方。 9.儿童必须在成人监护下使用。 10.如正在使用其他药品，使用本品前请咨询医师或药师。 | K36: 儿童注意事项： 尚未明确。 妊娠与哺乳期注意事项： 尚未明确。 老人注意事项： 尚未明确。 | L36: 如与其他药物同时使用可能会发生药物相互作用，详情请咨询医师或药师。 | M36: 本品所含门冬氨酸、维生素B6在糖、蛋白质、脂肪代谢中起重要作用，可维持角膜与虹膜、睫状体的新陈代谢。甘草酸二钾具有抗炎、抗过敏作用。盐酸萘甲唑林为血管收缩剂，可减轻炎症和充血。马来酸氯苯那敏为抗组胺药，可缓解过敏反应症状。甲硫酸新斯的明为抗胆碱酯酶药，具有拟胆碱作用，可降低眼压，调节视力以及解除眼肌疲劳。 | N36: 密闭保存。 | O36: 13毫升 | Q36: 36个月
A37: 通用名称：盐酸左西替利嗪片 商品名称：迪皿 英文名称：Levocetirizine Hydrochloride Tablets 汉语拼音：Yansuan Zuoxitiliqin Pian | B37: 19 | C37: =IF(ISNUMBER(MATCH(#REF!,非处方药名称!A:A,0)),"非处方药","处方药") -> 处方药 | D37: 本品主要成分为盐酸左西替利嗪。 | E37: 本品为类白色片。 | F37: 荨麻疹、过敏性鼻炎、湿疹、皮炎、皮肤瘙痒症等。 | G37: 口服，成人及6岁以上儿童用量为每日一次，每次1片。2-6岁儿童，每日一次，每次半片。 | H37: 本品耐受性良好，不良反应轻微且多可自愈，常见不良反应有嗜睡、口干、头痛、乏力等。 | I37: 对本品及其它辅料过敏者禁用。 | J37: 1.有肝功能障碍或障碍史者慎用。 2.高空作业、驾驶或操纵机器期间慎用。 3.避免与镇静剂同服。 4.酒后避免使用本品。 5.肾功能减损患者使用本品适当减量。 | K37: 儿童注意事项： 2周岁以下儿童用药的安全性尚未确定。 妊娠与哺乳期注意事项： 孕期及哺乳期妇女禁用本品。 老人注意事项： 通常老年人生理机能衰退，需慎用本品。 | L37: 尚无使用本品进行药物相互作用的研究。消旋西替利嗪与伪麻黄碱、西咪替丁、酮康唑、红霉素、阿奇霉素、格列吡嗪和安定间无相互作用。 | M37: 本品为口服选择性组胺H1受体拮抗剂。无明显抗胆碱和抗5-羟色胺作用，中枢抑制作用较小。 | N37: 遮光，密封，干燥处保存。 | O37: 5毫克 | Q37: 24个月
A38: 通用名称：复方熊胆滴眼液 商品名称：三顺 英文名称：FuFangXiongDanDiYanYe(SanShun) 汉语拼音：Fufang Xiongdan Diyanye | B38: 12.2 | C38: =IF(ISNUMBER(MATCH(#REF!,非处方药名称!A:A,0)),"非处方药","处方药") -> 处方药 | D38: 熊胆粉、天然冰片。辅料：硼砂、硼酸、氯化钠、尼泊金乙酯、羧甲基纤维素钠。 | E38: 本品为淡黄色混悬液；气清香，味苦。 | F38: 清热降火、明目退翳。用于肝火上炎、热毒伤络型之急性细菌性结膜炎，流行性角结膜炎。 | G38: 滴眼，每次1～2次，一日6次，或遵医嘱。 | H38: 尚不明确。 | I38: 尚不明确。 | J38: 滴眼前轻摇药瓶，滴后拧紧瓶盖，忌食辛辣油腻食物。 | L38: 尚不明确。 | M38: 药理作用：本品能促进电热所致家兔角膜烧伤所致角膜翳处的角膜上皮修复，缩短愈合时间并减轻并发的结膜炎症状。体外试验结果表明，本品能抑制腺病毒Ⅲ型和单纯疱疹病毒Ⅰ型的增殖和金黄色葡萄球菌的生长。 | N38: 密闭，置凉处。 | O38: 每瓶装5ml;每瓶装8ml | P38: 5ml/盒；8ml/盒。
A39: 通用名称：玻璃酸钠滴眼液 商品名称：联邦亮晶晶 英文名称：Sodium Hyaluronate Eye Drops 汉语拼音：Bolisuanna Tiyanye | B39: 30.3 | C39: =IF(ISNUMBER(MATCH(#REF!,非处方药名称!A:A,0)),"非处方药","处方药") -> 处方药 | D39: 本品主要成分为透明质酸钠。 | E39: 本品为无色澄明的粘稠液体。 | F39: 眼睛疲劳、眼干燥症、眼干燥综合症、斯-约二氏综合症等内因性疾患。手术后药物性、外伤、光线对眼造成的刺激及戴隐形眼镜等引起的外因性疾病。 | G39: 一般一次1滴，1天滴眼5～6次，可根据症状适当增减。一般使用0.1％浓度的玻璃酸钠滴眼液，重症疾患以及效果不明显时使用0.3％的玻璃酸钠滴眼液。 | H39: 1.过敏症：有时可能会发生眼睑炎、眼睑皮肤炎等，出现上述症状应停药。2.有时可能会出现搔痒感、刺激感、充血、弥漫性表层角膜炎等角膜障碍，出现上述症状时应停药。 | I39: 尚未发现。 | J39: 1.过敏症：有时可能会发生眼睑炎、眼睑皮肤炎等，出现上述症状应停药。2.有时可能会出现搔痒感、刺激感、充血、弥漫性表层角膜炎等角膜障碍，出现上述症状时应停药。 | K39: 儿童注意事项： 尚不明确。 妊娠与哺乳期注意事项： 尚不明确。 老人注意事项： 尚不明确。 | L39: 尚不明确。 | M39: 玻璃酸钠是一种线性多糖，广泛存在于脊椎动物的结缔组织基质中。玻璃酸钠能与纤维连结蛋白结合，加速上皮细胞的粘附和延展；由于玻璃酸钠分子能存留大量水分子而具有较好的保水作用。家兔试验提示，局部应用玻璃酸钠可一定程度促进角膜上皮损伤的愈合。体外试验提示，玻璃酸钠能加速培养的家兔角膜片中结膜上皮细胞的延展，具有防止离体家兔结膜片干燥的作用。 | N39: 遮光、密闭2～8℃下保存。 | O39: (1)5毫升:5毫克;(2)7毫升:7毫克 | P39: 塑料瓶装，每小盒1瓶，(1)每瓶5ml （2）每瓶7ml。 | Q39: 24月
A40: 通用名称：重组人表皮生长因子滴眼液(酵母) 商品名称：易贝 英文名称：Recombinant Human Epidermal Growth Factor Eye Drops(Yeast) 汉语拼音：Chongzu renbiaopishengzhangyinzi diyanye | B40: 35.4 | C40: =IF(ISNUMBER(MATCH(#REF!,非处方药名称!A:A,0)),"非处方药","处方药") -> 处方药 | D40: 主酵母表达的重组人表皮生长因子(rhEGF)。 | E40: 本品为无色澄清液。 | F40: 各种原因引起的角膜上皮缺损，包括角膜机械性损伤、各种角膜手术后、轻度干眼症伴浅层点状角膜病变、轻度化学烧伤等。 | G40: 将本品直接滴入 眼 结膜囊内，每次 1―2滴，每日4次，或遵医嘱。 | H40: 未观察到局部刺激现象及全身性不良反应。 | I40: 对天然和重组 hEGF、甘油、甘露醇有过敏史者禁用。 | J40: 1.需根据病情，合并应用抗生素或抗病毒药物，针对病因进行治疗。 2.使用过程中应避免污染。 3.本品应在开启后一周内用完。 | K40: 儿童注意事项： 尚不清楚。 妊娠与哺乳期注意事项： 尚不清楚。 老人注意事项： 尚不清楚。 | L40: 未发现与其他药物有协同或拮抗作用。 | M40: 本品活性成份为重组人表皮生长因子（rhEGF）,可促进角膜上皮细胞的再生，从而缩短受损角膜的愈合时间。 | N40: 4-25℃保存。 | O40: 20000IU(40μg)/2ml/支;30000IU(60μg)/3ml/支;40000IU(80μg)/4ml/支 | Q40: 24个月
A41: 通用名称：蒲地蓝消炎口服液 商品名称：济川 英文名称：PuDiLanXiaoYanKouFuYe(JiChuan) 汉语拼音：Pudilan Xiaoyan Koufuye | B41: 42.7 | C41: =IF(ISNUMBER(MATCH(#REF!,非处方药名称!A:A,0)),"非处方药","处方药") -> 处方药 | D41: 蒲公英、地丁、板蓝根、黄芩 | E41: 本品为棕红色至深棕色的液体，气微香，味甜、微苦。 | F41: 清热解毒，抗炎消肿。用于疖肿、腮腺炎、咽炎、扁桃体炎等。 | G41: 口服。一次10毫升，一日3次，小儿酌减。如有沉淀，摇匀后服用。 | H41: 恶心、呕吐、腹胀、腹痛、腹泻、乏力、头晕等，头疹、瘙痒等过敏反应。 | I41: 对本品及所含成分过敏者禁用。 | J41: 请遵医嘱。1.孕妇慎用；2.过敏体质者慎用；3.症见腹痛喜暖泄泻等脾覆成寒者慎用。 | L41: 如与其他药物同时使用可能会发生药物相互作用，详情请咨询医师或药师。 | M41: 本品对大肠杆菌和脆弱类杆菌所致小鼠皮下混合感染的脓肿形成有一定的抑制作用，对金黄色葡萄球菌和脆弱类杆菌腹腔注射所致的小鼠感染有一定的保护作用，对二甲苯致小鼠耳廓肿胀和角叉菜胶所致大鼠足跖肿胀均有一定的抑制作用，对伤寒菌苗所致家兔体温升高也有一定的抑制作用。 . | N41: 密封，置阴凉处。 | O41: 每支装10毫升(相当于饮片10.01克) | P41: l0ml*6支/盒
A42: 通用名称：六神胶囊 商品名称：雷允上 英文名称：LiuShenJiaoNang(LeiYunShang) 汉语拼音：Liu Shen Jiao Nang | B42: 13.8 | C42: =IF(ISNUMBER(MATCH(#REF!,非处方药名称!A:A,0)),"非处方药","处方药") -> 处方药 | D42: 人工麝香、人工牛黄等味。 | E42: 本品为胶囊剂，内容物为浅棕色的颗粒;味辛辣。 | F42: 清热解毒，消炎止痛。主要用于烂喉丹痧、咽喉肿痛、喉风喉痈、单双乳蛾、小儿热疖、痈疡疔疮乳痈发背、无名肿毒等。 | G42: 口服。一次1粒，一日3次。 | H42: 尚不明确。 | I42: 孕妇忌服。 | J42: 本品仅供成人服用。 | L42: 如与其他药物同时使用可能会发生药物相互作用，详情请咨询医师或药师。 | N42: 密封。 | O42: 每粒装0.19克 | Q42: 36个月
A43: 通用名称：小儿金翘颗粒 商品名称：一欣和 英文名称：XiaoErJinQiaoKeLi(BiBiGao) 汉语拼音：Xiao Er Jin Qiao Ke Li | B43: 30.6 | C43: =IF(ISNUMBER(MATCH(#REF!,非处方药名称!A:A,0)),"非处方药","处方药") -> 处方药 | D43: 金银花、连翘、葛根、大青叶、山豆根、柴胡、甘草。辅料为蔗糖。 | E43: 本睥睨为棕黄色的颗粒;味甜、微苦。 | F43: 疏风清热，解毒利咽，消肿止痛。由于风热袭肺所致乳蛾，证见：恶寒发热，咽部红肿疼痛，吞咽时加剧，咽干灼热，喉核红肿；小儿急性扁桃体炎见上述证候者。 | G43: 开水冲服。1-3岁每次2.5克，一日4次；3-5岁每次5克，一日3次；5-7岁每次7.5克，一日3次；8-10岁，每次7.5克，一日4次；11-14岁，每次10克，一日3次。 | H43: 偶见腹痛，便稀。 | I43: 尚不明确。 | J43: 请遵医嘱。 | L43: 如与其他药物同时使用可能会发生药物相互作用，详情请咨询医师或药师。 | M43: 实验药理学试验结果显示，本品具有抗炎、镇痛、解热作用。（1）提高感染乙型溶血性链球菌和金黄色葡萄球菌小鼠的存活率；（2）减轻角叉菜胶致大鼠的急性炎症反应；（3）降低角叉菜胶致热大鼠和三联菌苗致热家兔的发热程度；（4）减轻热板和醋酸所致的小鼠疼痛。 | N43: 置阴凉干燥处。 | O43: 每袋装5克、每袋装7.5克
A44: 通用名称：开喉剑喷雾剂(儿童型) 商品名称：三力制药 英文名称：KaiHouJianPenWuJi(ErTongXing)(SanLiZhiYao) 汉语拼音：Kai Hou Jian Pen Wu Ji | B44: 24.6 | C44: =IF(ISNUMBER(MATCH(#REF!,非处方药名称!A:A,0)),"非处方药","处方药") -> 处方药 | D44: 八爪金龙、山豆根、蝉蜕、薄荷脑。 | E44: 本品为喷雾剂，内容物为浅棕色至棕色液体;味甜、微苦、微麻，有薄荷的清凉感。 | F44: 清热解毒，消肿止痛。用于急、慢性咽喉炎、扁桃体炎、咽喉肿痛、口腔炎、牙龈肿痛。 | G44: 喷患处，每次适量，一日数次。 | H44: 尚不明确。 | I44: 尚不明确。 | J44: 请遵医嘱。 | K44: 儿童注意事项： 尚不明确。 妊娠与哺乳期注意事项： 孕妇禁用。 老人注意事项： 尚不明确。 | L44: 如与其他药物同时使用可能会发生药物相互作用，详情请咨询医师或药师。 | M44: 尚不明确。 | N44: 密封，置阴凉干燥处(不超过20℃)。 | O44: 每瓶装10ml,15ml | Q44: 24个月
A45: 通用名称：小牛血去蛋白提取物眼用凝胶 商品名称：速高捷 英文名称：Deproteinized Calf Blood Extract Eye Gel 汉语拼音：Xiaoniuxuequdanbaitiquwu Yanyongningjiao | B45: 41.3 | C45: =IF(ISNUMBER(MATCH(#REF!,非处方药名称!A:A,0)),"非处方药","处方药") -> 处方药 | D45: 小牛血去蛋白提取物。 | E45: 本品为凝胶剂。 | F45: 用于各种起因的角膜溃疡，角膜损伤，由碱或酸引起的角膜灼伤，大泡性角膜炎，神经麻痹性角膜炎，角膜和结膜变性。 | H45: 尚不明确。 | I45: 尚不明确。 | J45: 尚不明确。 | K45: 儿童注意事项： 尚不明确。 妊娠与哺乳期注意事项： 慎用，以防对胎儿或婴儿的潜在副作用。 老人注意事项： 请遵医嘱。 | L45: 尚不明确。 | M45: 尚不明确。 | N45: 密封。 | O45: 5g(20%) | Q45: 24个月
A46: 通用名称：安儿宁颗粒 商品名称：金诃 英文名称：AnErNingKeLi(JinHe) 汉语拼音：An’erning Keli | B46: 22.7 | C46: =IF(ISNUMBER(MATCH(#REF!,非处方药名称!A:A,0)),"非处方药","处方药") -> 处方药 | D46: 天竺黄、红花、人工牛黄、岩白菜、甘草、高山辣根菜、短管兔耳草、白檀香、唐古特乌头、蔗糖。 | E46: 本品为黄色的颗粒；味甜、苦。 | F46: 清热祛风，化痰止咳。用于小儿风热感冒，咳嗽有痰，发热咽痛，上呼吸道感染见上述证候者。 | G46: 开水冲服。一岁以内一次1.5克，一至五岁一次3克，五岁以上一次6克，一日3次。 | H46: 尚不明确。 | I46: 尚不明确。 | J46: 请遵医嘱。 | L46: 如与其他药物同时使用可能会发生药物相互作用，详情请咨询医师或药师。 | N46: 密封。 | O46: 每袋装3g | P46: 包装材料为：聚乙烯药品包装用复合膜；包装规格为：3g×9袋/盒。 | Q46: 36个月。
A47: 通用名称：卵磷脂络合碘胶囊 商品名称：适丽顺 英文名称：Iodized Lecithin Capsules 汉语拼音：IodizedLecithinCapsules | B47: 67.3 | C47: =IF(ISNUMBER(MATCH(#REF!,非处方药名称!A:A,0)),"非处方药","处方药") -> 处方药 | D47: 本品为硬胶囊剂，内容物为白色至淡黄色粉末。 | F47: 治疗中心性浆液性脉络膜视网膜病变，中心性渗出性脉络膜视网膜病变，玻璃体出血，玻璃体混浊，视网膜中央静脉阻塞等。 | G47: 口服，成人一次1-3粒，一日2-3次。 | H47: 偶发皮疹、胃肠不适。 | I47: 1.患有慢性甲状腺疾病的患者慎用。 2.曾患突眼性甲状腺肿的患者慎用。 3.内源性甲状腺素合成不足的患者慎用。 4.对碘过敏者禁用。 | J47: 1.患有慢性甲状腺疾病的患者。2.曾患突眼性甲状腺肿的患者。3.内源性甲状腺素合成不足的患者。请仔细阅读说明书并遵医嘱使用。 | K47: 儿童注意事项： 尚不明确。 妊娠与哺乳期注意事项： 尚不明确。 老人注意事项： 尚不明确。 | L47: 如与其他药物同时使用可能会发生药物相互作用，详情请咨询医师或药师。 | M47: 尚不明确。 | N47: 密封。 | O47: 0.1mg(以碘计) | P47: 0.1mg（以碘计）
A48: 通用名称：盐酸左氧氟沙星眼用凝胶 商品名称：杰奇 英文名称：Levofloxacin Hydrochloride Eye Gel 汉语拼音：Yansuan Zuoyangfushaxing Yanyong Ningjiao | B48: 24.7 | C48: =IF(ISNUMBER(MATCH(#REF!,非处方药名称!A:A,0)),"非处方药","处方药") -> 处方药 | D48: 本品主要成份为盐酸左氧氟沙星，其化学名称为(S)(-)9-氟-2，3-二氢-3-甲基-10-(4-甲基-1-哌嗪基)-7-氧-7H-吡啶骈[1，2，3-de]-[1，4]苯骈恶嗪-6-羧酸盐酸盐水合物。 | E48: 本品为淡黄色或淡黄绿色透明的凝胶。 | F48: 本品适用于细菌性结膜炎、角膜炎、角膜溃疡、泪囊炎、术后感染等外眼感染。 | G48: 涂于眼下睑穹窿部，每日3次(早、中、晚各一次) | H48: 偶有一过性的刺激症状。 | I48: 对本品成份氧氟沙星或喹诺酮类药物过敏者禁用。 | J48: 1.不宜长期使用； 2.使用中出现过敏症状，应立即停止使用； 3.只限于眼用。 | K48: 儿童注意事项： 未进行该项实验且无可靠参考文献。 妊娠与哺乳期注意事项： 尚不明确。 老人注意事项： 未进行该项实验且无可靠参考文献。 | L48: 尚不明确。 | M48: 药理作用：本品属喹诺酮类抗菌药，为氧氟沙星的左旋体，其抗菌活性约为氧氟沙星的2倍，主要作用机制为抑制细菌DNA旋转酶的活性，抑制细菌DNA的复制。本品具有抗菌谱广、抗菌作用强的特点，对多数肠杆菌科细菌如肺炎克雷白菌、变形杆菌属、伤寒杆菌属、志贺菌属、部分大肠杆菌等有较强的抗菌活性，对部分葡萄球菌、肺炎链球苗、流感杆菌、绿脓杆菌、淋球菌、衣原体等也有良好的抗菌作用。毒理研究：未进行该项实验且无可靠参考文献。 | N48: 遮光、凉暗处密闭保存。 | O48: 5g:0.015g | Q48: 24个月
A49: 通用名称：醋酸地塞米松粘贴片 商品名称：意可贴 英文名称：Dexamethasone Acetate Adhesive Tablets 汉语拼音：Cusuandisaimisong Niantie Pian | B49: 18.6 | C49: =IF(ISNUMBER(MATCH(#REF!,非处方药名称!A:A,0)),"非处方药","处方药") -> 处方药 | D49: 醋酸地塞米松。辅料：卡波普，糊精，硬脂酸镁，丙烯酸树脂，二氧化钛，核黄素，邻苯二甲酸二辛酯。 | E49: 本品为双层片，类白色层为含药层，黄色层为保护层。 | F49: 用于非感染性口腔黏膜溃疡。 | G49: 贴于患处。一次1片，一日总量不超过3片，连用不得超过1周。洗净手指后粘少许唾液粘起黄色面，将白色层贴于患处，并轻压10-15秒，使其粘牢，不须取出，直至全部溶化。 | H49: 1.偶见皮疹等过敏反应。 2.长期、大面积使用可见糖皮质激素类全身性不良反应。 3.大面积长期使用亦能产生全身性不良反应。 | I49: 严重活动性结核病、高血压、糖尿病、胃或十二指肠溃疡、骨质疏松症、早期妊娠、角膜溃疡及有精神病史、癫痫病史、青光眼和严重心或肾功能不全者禁用。 | J49: 1.对本品过敏者禁用。 2.本品仅限口腔使用。 3.本品不宜长期使用，连用1周后症状未缓解，应停药就医。 4.孕妇、哺乳期妇女、儿童慎用。 5.本品在口腔内缓慢溶化后可咽下。 6.当本品性状发生改变时禁用。 7.如使用过量或发生严重不良反应时应立即就医。 8.请将此药品放在儿童不能接触的地方。 9.严重高血压、糖尿病、胃或十二指肠溃疡、骨质疏松症、有精神病史、或癫痫病史、青光眼等患者慎用，本品不宜大面积长期使用。 | K49: 儿童注意事项： 儿童慎用。 妊娠与哺乳期注意事项： 孕妇、哺乳期妇女慎用。 老人注意事项： 遵医嘱。 | L49: 1.使用本品时不能同时使用其他口腔用药。 2.如正在服用其他药品，使用本品前请咨询医师或药师。 | M49: 本品为糖皮质激素类药物。具有抗炎、抗过敏作用。 | N49: 遮光，在阴凉干燥处保存。 | O49: 0.3毫克 | Q49: 24个月。
A50: 通用名称：双氯芬酸钠喷雾剂 商品名称：思孚欣 英文名称：Diclofenac Sodium Spray 汉语拼音：Shuanglvfensuanna Penwuji | B50: 25.5 | C50: =IF(ISNUMBER(MATCH(#REF!,非处方药名称!A:A,0)),"非处方药","处方药") -> 处方药 | D50: 双氯芬酸钠 | E50: 本品为淡黄色的澄清液体，有薄荷清凉香气。 | F50: 本品为非甾体类抗炎药。用于复发性口腔溃疡局部及扁桃体切除术后局部止痛。 | G50: 局部喷雾，2～3小时一次，每次3～4揿（每揿含双氯芬酸钠0.5mg）。 | H50: 少数患者口腔溃疡局部有一过性刺激痛，很快即可消失。偶见头晕。 | I50: 已知对本品过敏的患者。服用阿司匹林或其他非甾体类抗炎药后诱发哮喘、荨麻疹或过敏反应的患者。禁用于冠状动脉搭桥手术（CABG）围手术期疼痛的治疗。有应用非甾体类抗炎药后发生肠胃道出血或穿孔病史的患者。有活动性消化道溃疡/出血，或者既往曾复发溃疡/出血的患者。重度心力衰竭患者。 | J50: 1.避免与其它非甾体类抗炎药，包括选择性COX-2抑制剂合并用药。2.根据控制症状的需要，在最短治疗时间内使用最低有效剂量，可以是不良反应降到最低。3.在使用所有非甾体类抗炎药治疗过程中的任何时候，都可能出现胃肠道出血、溃疡和穿孔的不良反应，其风险可能是致命的。这些不良反应可能伴有或不伴有警示症状，也无论患者是否有肠胃道不良反应史或严重的肠胃事件病史。既往有肠胃道病史（溃疡性大肠炎，克隆氏病）的患者应谨慎使用非甾体类抗炎药，以免使病情恶化。当患者服用该药发生肠胃道出血或溃疡时，应停药。老年患者使用非甾体类抗炎药出现不良反应的频率增加，尤其是肠胃道出血和穿孔，其风险可能是致命的。4.针对多种COX-2选择性或非选择性NSAIDs药物迟勋时间达3年的临床试验显示，本品可能引起严重心血管血栓性不良事件、心肌梗塞和中风的风险增加，其风险可能是致命的。所有的NSAIDs，包括COX-2选择性或非选择性药物，可能有相似的风险。有心血管疾病或心血管疾病危险因素的患者，其风险更大。及时既往没有心血管症状，医生和患者也应对此类事件的发生保持警惕。应告知患者严重心血管安全性的症状和/或体征以及如果发生应采取的步骤。 患者应该警惕诸如胸痛、气短、无力、言语含糊等症状和体征，而且当有任何上述症状或者体征发生后应该马上寻求医生帮助。5.和所有非甾体类抗炎药（NSAIDs）一样，本品可导致新发高血压或使已有的高血压症状加重，其中的仍和一种都可以导致心血管事件的发生率增加。服用噻嗪类或髓袢利尿剂的患者服用非甾体类抗炎药（NSAIDs）时，可能会影响这些药物的疗效。高血压病患者应慎用非甾体类抗炎药（NSAIDs），包括本品。在开始本品治疗和整个治疗过程中应密切监测血压。6.有高血压和/或心力衰竭（如液体潴留和水肿）病史的患者应慎用。7.NSAIDs，包括本品可能引起致命的、严重的皮肤不良反应，例如剥脱性皮炎、Stevens Johnson综合征（SJS）和中毒性表皮坏死溶解症（TEN）。这些严重事件可在没有征兆的情况下出现。应告知患者严重皮肤反应的症状和体征，在第一次出现皮肤皮疹或过敏反应的其他征象时，应停用本品。 | K50: 儿童注意事项： 请在医师指导下用药。 妊娠与哺乳期注意事项： 请在医师指导下用药。 老人注意事项： 请在医师指导下用药。 | L50: 如正在使用其他药品，使用本品前请咨询医师或药师。 | M50: 本品为非甾体抗炎药。可选择性切断花生四烯酸代谢系列中环氧合酶的作用环节，阻断前列腺素的合成途径，具有消炎、镇痛作用。毒理研究：未进行该项实验且无可靠参考文献。 | N50: 密封。 | O50: 8ml:80mg(每揿含双氯芬酸钠0.5mg) | Q50: 24个月
A51: 通用名称：耳聋左慈丸(浓缩丸) 商品名称：耳聋左慈丸(佛慈)(浓缩丸 英文名称：ErLongZuoCiWan 汉语拼音：Er Long Zuo Ci Wan | B51: 14 | C51: =IF(ISNUMBER(MATCH(#REF!,非处方药名称!A:A,0)),"非处方药","处方药") -> 处方药 | D51: 磁石(煅)、熟地黄、山药、山茱萸(制)、茯苓、牡丹皮、竹叶柴胡、泽泻。 | E51: 本品为黑褐色的小蜜丸；味甜，微酸。 | F51: 滋肾平肝。用于肝肾阴虚的耳鸣耳聋，头晕目眩。 | G51: 口服。一次9克，一日2次。 | H51: 尚不明确。 | I51: 对本品过敏者禁用，过敏体质者慎用。 | J51: 1突发耳鸣耳聋者禁用。 2本药只用于肝肾阴虚证之听力逐渐减退，耳鸣如蝉声者，凡属外耳、中耳病变而出现的耳鸣，如外耳道异物等，应去医院就诊。 3按照用法用量服用，长期服用应向医师咨询。 4药品性状发生改变时禁止服用。 5儿童必须在成人的监护下使用。 6请将此药品放在儿童不能接触的地方。 7如正在服用其他药品，使用本品前请咨询医师或药师。 | L51: 如与其他药物同时使用可能会发生药物相互作用，详情请咨询医师或药师。 | N51: 密封。 | O51: 每8丸相当于原生药3g | P51: 200s/瓶，240s*2瓶/盒，240s/瓶，180s/瓶，168s/瓶 | Q51: 36个月
A52: 通用名称：金莲花分散片 商品名称：烟霞 英文名称：JinLianHuaFenSanPian(YanXia) 汉语拼音：Jinlianhua Fensan Pian | B52: 22 | C52: =IF(ISNUMBER(MATCH(#REF!,非处方药名称!A:A,0)),"非处方药","处方药") -> 处方药 | D52: 金莲花。辅料为微晶纤维素、交联聚乙烯吡咯烷酮、香精、阿司帕坦、硬脂酸镁、可壳色素。 | E52: 本品为灰黄色至棕黄色片；气芳香，味甜。 | F52: 清热解毒。用于上呼吸道感染、咽炎、扁桃体炎。 | G52: 加水分散后口服或直接嚼服，一次3片，一日2-3次。 | H52: 尚不明确。 | I52: 尚不明确。 | J52: 1.忌食烟酒,辛辣,油腻食物。 2.如疑咽部有肿物所致疼痛应去医院就诊。 3.按照用法用量服用,糖尿病患者,儿童应在医院指导下服用。 4.对本品过敏者禁用,过敏体质者慎用。 5.药品性状发生改变时禁止服用。 6.儿童必须在成人的监护下使用。 7.请将此药品放在儿童不能接触的地方。 8.如正在服用其他药品,使用本品前请咨询医师或药师。 | L52: 如与其他药物同时使用可能会发生药物相互作用，详情请咨询医师或药师。 | N52: 密封。 | O52: 每片重0.7克 | P52: 铝塑包装，0.7g×9片×3板/盒;0.7g×9片×2板/盒。 | Q52: 暂定24个月
A53: 通用名称：复明片 商品名称：碑林 英文名称：FuMingPian(BeiLin) 汉语拼音：Fuming Pian | B53: 27.4 | C53: =IF(ISNUMBER(MATCH(#REF!,非处方药名称!A:A,0)),"非处方药","处方药") -> 处方药 | D53: 羚羊角，蒺藜，木贼，菊花，车前子，夏枯草，决明子，人参，山茱萸，石斛，枸杞子，菟丝子，女贞子，石决明，黄连，谷精草，关木通，熟地黄，山药，泽泻，茯苓，牡丹皮，地黄，槟榔。 | E53: 本品为糖衣片，除去糖衣，显棕褐色；气微香，味微苦。 | F53: 滋补肝肾，养阴生津，清肝明目。用于青光眼，初、中期白内障及肝肾阴虚引起的羞明畏光、视物模糊等病。 | G53: 口服。一次5片，一日3次，每疗程30天。 | H53: 尚不明确。 | I53: 禁忌辛辣刺激。 | J53: 请遵医嘱。 | L53: 如正在服用其他药品，使用本品前请咨询医师或药师。 | N53: 密封，防潮。 | O53: 片芯重0.3g | P53: 塑料瓶，0.3g*90s/瓶，塑料瓶，50s/瓶/盒，0.3g*90s+1.2g*30s/套，0.3g*90s+1.2g*30s/套，0.3g*90s+1000mg*30s/套 | Q53: 24个月
A54: 通用名称：氯雷他定糖浆 商品名称：百为哈 英文名称：Loratadine Syrup 汉语拼音：Lvleitading Tangjiang | B54: 9.5 | C54: =IF(ISNUMBER(MATCH(#REF!,非处方药名称!A:A,0)),"非处方药","处方药") -> 处方药 | D54: 本品每瓶含氯雷他定60毫克。辅料为：蔗糖、甘油、丙二醇、香精、苯甲酸钠、盐酸。 | E54: 本品为无色至淡黄色澄清的粘稠液体，带调味剂的芳香气味。 | F54: 用于缓解过敏性鼻炎有关的症状，如喷嚏、流涕、鼻痒、鼻塞以及眼部痒及烧灼感。口服药物后，鼻和眼部症状及体征得以迅速缓解。亦适用于缓解慢性荨麻疹、瘙痒性皮肤病及其他过敏性皮肤病的症状及体征。 | G54: 口服。成人及12岁以上儿童：一日1次，一次两茶匙（10毫升）。2～12岁儿童：体重>30公斤：每天一次，每次两茶匙（10毫升）。体重≤30公斤：每天一次，每次一茶匙（5毫升）。 | H54: 在每天10毫升的推荐剂量下，本品未见明显的镇静作用。常见不良反应有乏力、头痛、嗜睡、口干、胃肠道不适包括恶心、胃炎以及皮疹等。罕见不良反应有脱发、过敏反应、肝功能异常、心动过速及心悸等。 | I54: 对本品及其所含成份过敏者禁用。 | J54: 1.2岁以下儿童用药请咨询医师。2.严重肝功能不全的患者请在医生指导下使用。3.妊娠期及哺乳期妇女慎用。4.在做皮试前约48小时左右应中止使用本品，因抗组胺药能阻止或降低皮试的阳性反应发生。5.对本品过敏者禁用，过敏体质者慎用。6.本品性状发生改变时禁止使用。7.请将本品放在儿童不能接触的地方。8.儿童必须在成人监护下使用。9.如正在使用其他药品，使用本品前请咨询医师或药师。 | K54: 儿童注意事项： 2岁以下儿童用药请咨询医师。 妊娠与哺乳期注意事项： 妊娠期及哺乳期妇女慎用。 老人注意事项： 肝肾功能轻中度受损时，对本药的代谢和排泄无明显的影响，所以老年患者用药量 与成人相同。 | L54: 1 同时服用酮康唑、大环内酯类抗生素、西咪替盯茶碱等药物，会提高氯雷他定在血浆中的浓度，应慎用。其他已知能抑制肝脏代谢的药物，在未明确与氯雷他定相互作用前应谨慎合用；2 如与其他药物同时使用可能发生药物相互作用，详情请咨询医师或药师。 | M54: 药理学本品属长效三环类抗组胺药，竞争性地抑制组胺H1受体，抑制组胺所引起的过敏症状。本品无明显的抗胆碱和中枢抑制作用。毒理学动物试验未见明显致畸作用。 | N54: 密封保存。 | O54: 60毫升:60毫克 | Q54: 36个月
A55: 通用名称：盐酸氯环利嗪片 商品名称：康夫丽尔 英文名称：Chlorcyclizine Hydrochloride Tablets 汉语拼音：Yansuan lühuanliqin Pian | B55: 49.8 | C55: =IF(ISNUMBER(MATCH(#REF!,非处方药名称!A:A,0)),"非处方药","处方药") -> 处方药 | D55: 分子量：C18H21CLN2·HCL | E55: 本品为糖衣片，除去糖衣后显白色。 | F55: 适用于各种过敏性疾病，特别是荨麻疹、枯草热和过敏性鼻炎等。 | G55: 口服，一次一片，一日两次，儿童减半或在医生指导下使用。 | H55: 同一般抗组胺药。嗜睡，服用大剂量可出现口干、眩晕等症状。 | I55: 孕妇、青光眼、前列腺肥大者忌服。 | J55: 对本品过敏者禁用。请仔细阅读说明书并遵医嘱使用。 | K55: 儿童注意事项： 未进行该项试验且无参考文献。 妊娠与哺乳期注意事项： 未进行该项试验且无参考文献。 老人注意事项： 未进行该项试验且无参考文献。 | L55: 未进行该项试验且无参考文献。 | M55: 本品为长效抗组胺药，其作用持续时间一般为12～18小时。能拮抗组胺所致动物的毛细血管扩张作用和支气管平滑肌的痉挛作用。实验证明本品具有抗胆碱作用。 | N55: 密封。 | O55: 25mg | Q55: 24月
A56: 通用名称：匹多莫德颗粒 商品名称：金世力德 英文名称：Pidotimod Granules 汉语拼音：Piduomode Keli | B56: 20.2 | C56: =IF(ISNUMBER(MATCH(#REF!,非处方药名称!A:A,0)),"非处方药","处方药") -> 处方药 | D56: （R）-3-[（S）-（5-氧-2-吡咯烷基）-羰基]-噻唑烷基-4-羧酸 | E56: 本品为白色或类白色可溶颗粒。 | F56: 本品为免役刺激剂（immunostimulant），适用于细胞免疫功能低下患者：1.呼吸道反复感染（气管炎、支气管炎）；2.耳鼻喉科反复感染（鼻炎、鼻窦炎、耳炎、咽炎、扁桃体炎）；3.泌尿系统反复感染；4.妇科反复感染；可用于预防感染性期病症，缩短病程，减轻疾病的严重度，减少反复发作次数，也可作为急性感染时抗菌药物治疗的辅助药物。 | G56: 成人：急性期用药：开始两周，每次0.8g，一日二次，随后减为每次0.8g，一日一次，或遵医嘱。预防期用药：每次0.8g，一日一次，连续用药60天或遵医嘱。儿童：急性期用药：开始两周，每次0.4g，一日二次，随后减为每次0.4g，一日一次，连续用药60天或遵医嘱。预防期用药：每次0.4g，连续用药60天或遵医嘱。 | H56: 尚未有用本品出现严重副作用的报导。少见的不良反应有头痛、眩晕、恶心、呕吐、腹泻、皮疹等，一般无须停药治疗。 | I56: 对本品过敏者禁用。妊娠三个月内妇女禁用。 | J56: 高敏体质者慎用；因食物会影响药物吸收，所以，本品应在餐前或餐后2小时左右服用。 | K56: 儿童注意事项： 严格遵守儿童用药的用法与用量，详见[用法用量]项。 妊娠与哺乳期注意事项： 妊娠3个月内妇女禁用。 老人注意事项： 尚不明确。 | L56: 尚未有本药与其它药物相互作用、相互影响的资料及报导。 | M56: 本品是一种人工合成的口服免疫增强剂，通过刺激和调节细胞介导的免疫反应而起作用。毒理研究重复给药毒性：大鼠连续52周灌服本品200、400、800mg/kg/日，中、高剂量组雌性动物体重明显增加，800mg/kg/日（按体表面积折算，相当于临床推荐最大剂量的4.9倍）组动物尿pH值和尿蛋白增高，组织学检查可见高剂量组雄性动物颈淋巴结外皮层细胞增加，少数雌性动物胃、十二指肠膨大部分粘膜增生，可能与给药有关。 | N56: 密封，在干燥处保存。 | O56: 2g:0.4g | Q56: 24个月
A57: 通用名称：眼氨肽滴眼液 商品名称：乐润 英文名称：Ocular Extractives Eye Drops 汉语拼音：Antaidian Diyanye | B57: 11.2 | C57: =IF(ISNUMBER(MATCH(#REF!,非处方药名称!A:A,0)),"非处方药","处方药") -> 处方药 | D57: 本品系采用动物全眼球和甲状腺水解提取精制而成的纯生化制剂，含有机碘和谷、胱、甘、天冬、赖等十八种氨基酸、多肽、核苷酸和多种微量元素等有效成份。本品为牛或猪眼球经消毒后以乙醇提取除去蛋白质的灭菌水溶液 | E57: 本品为淡黄色或黄色的澄明液体。 | F57: 本品适用于初期老年性白内障，玻璃体混浊等眼疾的治疗。适用于角膜炎、视力疲劳、青少年假性近视。 | G57: 滴眼，一次1滴，一日3次。 | H57: 少数病例滴眼后有局部刺激感和/或结膜囊分泌物增多，极少数病例滴眼后有结膜、眼睑充血和不适感，一般在继续用药过程中症状会减退或消失。 | I57: 对本品过敏者禁用 | J57: ①本品开启使用后要避免污染，如发现药液混浊，切勿再用。用毕后密闭存放于阴凉避光处。在10天内用完，不宜久藏 ②用药期间如有持续性结膜充血或刺痛不适感，应停药就诊。 ③为维持疗效，本品宜长期使用。 | K57: 儿童注意事项： 目前尚不明确。 妊娠与哺乳期注意事项： 目前尚不明确。 老人注意事项： 目前尚不明确。 | L57: 尚不明确。 | M57: 本品能改善眼部血液循环和新陈代谢，促进玻璃体混浊吸收，促进组织修复再生，阻止白内障发展，提高视觉功能。 | N57: 遮光、密闭，在凉处保存 | O57: 5ml:12.5g | Q57: 24个月
A58: 通用名称：铁笛片 商品名称：希臣 英文名称：TieDiPian(XiChen) 汉语拼音：Tiedi Pian | B58: 22.4 | C58: =IF(ISNUMBER(MATCH(#REF!,非处方药名称!A:A,0)),"非处方药","处方药") -> 处方药 | D58: 麦冬、玄参、瓜蒌皮、诃子(肉)、青果、凤凰衣、桔梗、浙贝母、茯苓、甘草。 | E58: 本品为灰色片；气微、味甜、微苦。 | F58: 清肺利咽，生津止渴。用于肺热津伤的咽干口燥，声音嘶哑，咽喉肿痛。 | G58: 含化。一次2片，一日4次。 | H58: 尚不明确。 | I58: 尚不明确。 | J58: 1.忌食辛辣、煎炸、鱼虾等食物。 2.凡声嘶、咽痛初起，兼见恶寒发热，鼻流清涕等外感风寒者慎用。 3.发热重，咽喉痛甚者不宜使用。 4.若声嘶日久，逐渐加重，或伴痰中带血者，应考虑咽喉严重疾病的可能，需及时去医院就诊。 5.按照用法用量服用，糖尿病患者及儿童应在医师指导下服用。 6.一般症状在服药3天内无改善或出现发热渐高等其他症状应去医院就诊。 7.对本品过敏者禁用，过敏体质者慎用。 8.本品性状发生改变时禁止服用。 9.儿童必须在成人的监护下使用。 10.请将此药品放在儿童不能接触的地方。 11.如正 | L58: 如与其他药物同时使用可能会发生药物相互作用，详情请咨询医师或药师。 | N58: 密闭、防潮。 | O58: 每片重1克 | P58: 1g*24s/盒，1g*8s/盒，1g*16s/盒，1g*12s/盒，1g*36s/盒，1g*2s/盒 | Q58: 24个月
A59: 通用名称：复方血栓通软胶囊 商品名称：广发制药 英文名称：FuFangXueShuanTongRuanJiaoNang(GuangFaZhiYao) 汉语拼音：Fufang xueshuantong Ruanjiaonang | B59: 28.9 | C59: =IF(ISNUMBER(MATCH(#REF!,非处方药名称!A:A,0)),"非处方药","处方药") -> 处方药 | D59: 三七、黄芪、丹参、玄参。 | E59: 本品为软胶囊剂，内容物为深棕褐色油状物；味苦，微甘。 | F59: 活血化瘀，益气养阴。用于治疗血瘀兼气阴两虚证的视网膜静脉阻塞。症见视力下降或视觉异常，眼底瘀血征象，神疲乏力，咽干、口干等症。 | G59: 口服。一次1粒，一日3次。 | H59: 尚不明确。 | I59: 孕妇慎用。 | J59: 孕妇慎用。 | L59: 如与其他药物同时使用可能会发生药物相互作用，详情请咨询医师或药师。 | N59: 密封，阴凉处保存（不超过20℃）。 | O59: 每粒装0.74g | P59: 铝塑泡罩包装9s/板/盒，铝塑泡罩包装每板9粒，每盒2板，12s/盒 | Q59: 暂定为18个月
A60: 通用名称：醋甲唑胺片 商品名称：尼目克司 英文名称：Methazolamide Tablets 汉语拼音：CuJiaZuo’An Pian | B60: 356 | C60: =IF(ISNUMBER(MATCH(#REF!,非处方药名称!A:A,0)),"非处方药","处方药") -> 处方药 | D60: 本品主要成分及其化学名称：主要成分：醋甲唑胺，化学名称：5-乙酰胺基-4-甲基-1-硫-3，4-二氮茂磺酰胺。其分子式与分子量：C5H8N4O3S2，236.26 | E60: 本品为白色片。 | F60: 用于原发性开角型青光眼、闭角型青光眼及某些继发性青光眼，局部用抗青光眼药眼压控制不理想患者的辅助治疗。因本品降眼压的同时对酸碱平衡影响较少，故对于患有严重阻塞性肺部疾患的患者本品优于乙酰唑胺。醋甲唑胺对尿枸橼酸分泌的影响较乙酰唑胺小，故对于需口服碳酸酐酶抑制剂治疗但又易引起肾结石形成的患者，推荐应用醋甲唑胺。 | G60: 成人口服初始用药时，用25mg，一日2次，这一剂量常可使眼压下降4～5mmHg，且副作用最小。如用药后降眼压效果不理想，剂量可加大为50mg，一日2次。 | H60: 1.有报道醋甲唑胺可引起严重的血液学不良反应，包括再生障碍性贫血和粒细胞缺乏症。 2.有报道服醋甲唑胺可引起肾结石，但非常罕见。 3.其他有恶心、厌食、感觉异常、不适、疲劳及皮肤糜烂等不良反应。 | I60: 1 肝、肾功能不全致低钠血症、低钾血症、高氯性酸中毒，肾上腺衰竭及肾上腺皮质机能减退(阿狄森病)和有肝昏迷倾向患者禁用。 2 有磺胺过敏史的患者禁用。 | J60: 1.慎用于有代谢性酸中毒及低血钾危险的患者。 2.闭角型青光眼不应用醋甲唑胺代替手术治疗，否则可引起永久性粘连性房角关闭。 3.本品不能长期用于控制眼压。 | K60: 儿童注意事项： 本品对儿童的安全性和疗效尚不清楚。 妊娠与哺乳期注意事项： 1.本品可引起啮齿类动物畸形，孕妇应避免服用。 2.尚不清楚本品是否分泌至乳液中，哺乳期妇女使用本品治疗，应停止哺乳。 老人注意事项： 老年人和成年人对本品有很好的耐受性，故本品适用于老年患者。 | L60: 1 碳酸酐酶抑制剂与高剂量阿斯匹林合用可引起严重的代谢紊乱。因此，本品与水杨酸制剂合用要慎重。2 低剂量醋甲唑胺本身不引起低血钾，但碳酸酐酶抑制剂可增加其他药物的排钾作用。3 与促肾上腺皮质激素、糖皮质激素联合使用，可以导致严重的低血钾，在联合用药时应注意监护血清钾的浓度及心脏功能。亦应估计到长期同时使用有增加低血钙的危险，可以造成骨质疏松，因为这些药增加钙的排泄。 | M60: 本品化学结构类似乙酰唑胺（在氮原子上多一个甲基）。因此,药理作用及作用机理与乙酰唑胺相同。又因醋甲唑胺的结构设计减少了电离作用，故眼内透性较乙酰唑胺增强。本品穿透血-房水和血-脑屏障的功能亦较乙酰唑胺强（人脑脊髓液的浓度比乙酰唑胺高50倍）。抑制碳酸酐酶作用比乙酰唑胺强60％，在体内仅55％的醋甲唑胺与血浆蛋白结合（而90％～95％的乙酰唑胺与血浆蛋白结合）。因为只有药物剂量的未结合部分发挥药理作用，故较低剂量即有明显降眼压反应。醋甲唑胺可抑制房水生成，大部分患者用药后房水生成可减少40％。口服1～2小时后产生降眼压作用，维持16～18小时。本品的降眼压作用呈剂量依赖性。应用25、50及100mg口服，每8h1次，可使眼压分别下降3.3、4.3及5.6mmHg。 | N60: 避光，密闭保存。 | O60: 50毫克x10片 | Q60: 暂定24个月
A61: 通用名称：博士伦博视康牌叶黄素片 英文名称：Ocuvite Lutein Film-coated Tablets 汉语拼音：BoShiLunBoShiKangPaiXieHuangSuPian | B61: 257 | C61: =IF(ISNUMBER(MATCH(#REF!,非处方药名称!A:A,0)),"非处方药","处方药") -> 处方药 | D61: 万寿菊提取物、95%维生素C颗粒(维生素C、羟丙甲纤维素)、50%维生素E微囊(维生素E、明胶、蔗糖、淀粉、硅酸铝钠)、硒酵母、氧化锌、微晶纤维素、乳糖、氢化植物油、羟丙甲纤维素、羟丙纤维素、硬脂酸、甘油、滑石粉、氧化铁、日落黄铝色淀、胭脂红铝色淀、二氧化钛、纯化水 | F61: 缓解视疲劳、抗氧化 | G61: 每日2次，每次1片，吞服 | J61: 本品不能代替药物；本品添加了营养素，与同类营养素同时食用不宜超过推荐量；勿将本品置于儿童可及之处；高硒地区人群不宜食用 | N61: 置于阴凉干燥处，贮存温度不宜超过25℃ | O61: 530毫克/片 | P61: 530mg*60s | Q61: 36个月
A62: 通用名称：聚甲酚磺醛溶液 商品名称：爱宝疗 英文名称：Policresulen Solution 汉语拼音：JuJiaFenHuangQuanRongYe(AiBaoLiao) | B62: 65 | C62: =IF(ISNUMBER(MATCH(#REF!,非处方药名称!A:A,0)),"非处方药","处方药") -> 处方药 | D62: 聚甲酚磺醛化学名：亚甲基二(羟基甲基苯磺酸)聚合物分子量：[C8H8O4S]n | E62: 本品为红棕色的液体。 | F62: 妇科：用于局部治疗宫颈及阴道的局部炎症(如细菌、滴虫和霉菌感染引起的白带增多)，尖锐湿疣、使用子宫托造成的压迫性溃疡等。用于宫颈息肉切除或活检后的止血。外科和皮肤科：加速烧伤后坏死组织脱落，促进愈合过程(如小面积烧伤、肢体溃疡、褥疮、慢性炎症、尖锐湿疣等)。耳鼻喉科：用于局部治疗口腔黏膜和齿龈的炎症：口腔溃疡、扁桃体切除后及鼻出血的止血。 | G62: 1.妇科：局部贴敷可借助阴道镜，镊子和棉签。未经稀释的聚甲酚磺醛溶液可用于表皮和深部组织损伤。用于局部涂抹或贴敷时本品无需稀释，治疗前先彻底清洁宫颈及宫颈管，去除分泌物，为此可将浸有本品的棉签插入宫颈管，转动数次取出，然后再将浸有药液的纱布块轻轻贴敷于病变组织，持续1-3分钟，上述过程通常每周进行1-2次。用于止血时，本品亦无需稀释，一般贴敷1-2分钟即可达到目的。用于阴道冲洗时，本品应按1:5的比例以水稀释。2.外科、皮肤科：为了终止伤口出血，可将浸有本品的纱布块压在出血部位1-2分钟，止血后最好擦干残 | H62: 用药初期，极个别病例会产生局部刺激症状，但通常会很快自行消失，少有肛门下坠感。当治疗口腔病变时，请注意其高酸性可能损伤牙釉质。 | I62: 禁用于对本品中任何成分过敏的患者。怀孕期间，聚甲酚磺醛仅在绝对需要的情况下方可使用，此时应充分考虑药物对母婴的潜在危害。 | K62: 儿童注意事项： 尚不明确。 妊娠与哺乳期注意事项： 怀孕期间，特别是妊娠晚期，任何宫颈内治疗均应避免，宫颈外和阴道烧灼只有在极特殊的情况下方可进行。聚甲酚磺醛亦不例外，此时应充分考虑药物对母婴的潜在危害，尽管动物试验表明此药无任何致畸作用，但人体试验的结果尚未获得，人们还不清楚哺乳期妇女的乳汁内是否会含有此药的活性成份。 老人注意事项： 尚不明确。 | L62: 聚甲酚磺醛只能局部应用，由于不能排除与其它药物的相互影响，故同一部位避免同时使用两种以上的药物。 | M62: 聚甲酚磺醛具有广谱的抗菌作用，包括革兰氏阳性菌、革兰氏阴性菌和某些真菌，尤其值得一提的是对那氏菌、厌氧菌和滴虫有效。(详见内包装说明书) | N62: 避光保存。 | O62: 36%,每克溶液含聚甲酚磺醛360毫克。 | P62: 棕色玻璃瓶，25ml/瓶。 | Q62: 60个月
A63: 通用名称：蒲地蓝消炎胶囊 商品名称：星辰 英文名称：PuDiLanXiaoYanJiaoNang 汉语拼音：Pudilan Xiaoyan Jiaonang | B63: 27.4 | C63: =IF(ISNUMBER(MATCH(#REF!,非处方药名称!A:A,0)),"非处方药","处方药") -> 处方药 | D63: 黄芩，蒲公英，苦地丁，板蓝根。 | E63: 本品为胶囊剂，内容物为棕褐色的颗粒及粉末；气微，味苦。 | F63: 清热解毒，抗炎消肿。用于疖肿、腮腺炎，咽炎、淋巴腺炎、扁桃腺炎等。 | G63: 口服。一次3～5粒，一日4次。小儿酌减。 | H63: 尚不明确。 | I63: 1.孕妇慎用; 2.脾胃虚寒症见：腹痛、喜暖、泄泻者慎用。 | J63: 1.忌食辛辣刺激性食物; 2.用药期间不宜同时服用温热性药物; 3.孕妇及脾胃虚寒症见：腹痛、喜暖、泄泻者慎用; 4.儿童、哺乳期妇女、年老体弱及糖尿病患者应在医师指导下服用; 5.疮疖较重或局部变软化脓，或扁桃体有化脓及全身高热者应到医院就诊; 6.服药3天症状无缓解，应去医院就诊; 7.对本品过敏者禁用，过敏体质者慎用; 8.本品性状发生改变时禁止使用; 9.儿童必须在成人监护下使用; 10.请将本品放在儿童不能接触的地方; 11.如正在使用其他药品，使用本品前请咨询医师或药师。 | K63: 妊娠与哺乳期注意事项： | L63: 如与其他药物同时使用可能会发生药物相互作用，详情请咨询医师或药师。 | N63: 密封，置阴凉干燥处（不超过20℃）。 | O63: 每粒装0.4g | P63: 每粒装0.4g | Q63: 暂定24个月
A64: 通用名称：【白内停】吡诺克辛钠滴眼液（15毫升） 商品名称：吡诺克辛钠滴眼液(白内停 英文名称：OxytetracyclineHydrochlorideTablets 汉语拼音：Binuokexinna Diyanye | B64: 9.4 | C64: =IF(ISNUMBER(MATCH(#REF!,非处方药名称!A:A,0)),"非处方药","处方药") -> 处方药 | D64: 主要成分：吡诺克辛钠.化学名：1-羟-5-氧-5H-吡啶并-[3,2-a]-吩恶嗪-3-羧酸；化学结构:分子式：C16H18N2O5分子量：308.25 | E64: 本品为淡黄色或橙黄色液体。 | F64: 主要治疗初期老年性白内障、轻度糖尿病性白内障或并发性白内障等。 | G64: 滴眼，每日3～4次，每次1～2滴。 | H64: 极少数患者可有轻微眼部刺痛。 | I64: 眼外伤及严重感染时，暂不使用，或遵医嘱。 | J64: 1 使用前须将1片药片投入1瓶溶剂中，待药物完全溶解后，方可使用。片剂溶解入溶剂后，应连续使用，在20天内用完。2 糖尿病引起的白内障患者，应在使用本品的同时，在医师指导下结合其他方法治疗。3 滴眼时请勿使管口接触手和眼睛，避免污染瓶内眼药水。4 本品宜避光保存；使用后请拧紧瓶盖，以防污染。5 对本品过敏者禁用，过敏体质者慎用。6 本品性状发生改变时禁止使用。7 请将本品放在儿童不能接触的地方。8 如正在使用其他药品，使用本品前请咨询医师或药师。 | K64: 儿童注意事项： 尚不明确。 妊娠与哺乳期注意事项： 尚不明确。 老人注意事项： 尚不明确。 | L64: 如与其他药物同时使用可能会发生药物相互作用，详情请咨询医师或药师。 | M64: 本品通过保持和改善晶状体膜的功能、阻止多元糖醇的积累而防止或减少晶状体混浊。 | N64: 密封保存。 | O64: 15毫升:0.8毫克 | P64: 0.8mg*15ml/瓶。 | Q64: 24个月
A65: 通用名称：布洛芬混悬液 商品名称：翔宇赛可 英文名称：Ibuprofen Suspension 汉语拼音：Buluofen Koufu Hunxuanye | B65: 9.4 | C65: =IF(ISNUMBER(MATCH(#REF!,非处方药名称!A:A,0)),"非处方药","处方药") -> 处方药 | D65: 本品主要成分为布洛芬，其化学名称为2-(4-异丁基苯基)丙酸。 | E65: 橙色粘稠液体；味香甜。 | F65: 本品为非甾体类抗炎药，有解热、镇痛及抗炎作用。主要用于：1.由感冒、急性上呼吸道感染，急性咽喉炎等疾病引起的发热。2.轻、中度疼痛。3.类风湿性关节炎及骨关节炎等风湿性疾病。 | G65: 口服：1 成人及12岁以上儿童：推荐剂量为一次0.3～0.4g，一日3～4次，或遵医嘱。2 1～12岁儿童患者：(1)用于发热，推荐剂量为按体重一次20mg/kg，一日3次服用或遵医嘱。(2)用于镇痛，推荐剂量为按体重一次30mg/kg，一日3次服用或遵医嘱。 | H65: 偶见轻度消化不良，皮疹、头痛及转氨酶升高等，也有引起胃肠道出血而加重溃疡的报道。 | I65: 1 活动性消化道溃疡者禁用； 2 对本药过敏者、因服用阿斯匹林和其它非类固醇类抗炎药诱发哮喘、鼻炎或荨麻疹的患者禁用。 | J65: 1 肠胃病患者慎用；2 有支气管哮喘病史患者，可能会引起支气管痉挛；3 并用抗凝血药的患者，服药的最初几日应随时监测其凝血酶原时间；4 对其它抗风湿药物耐受性差者可能对本品有良好耐受性；5 心功能不全及原发性高血压病患者慎用；6 连续服用3天发热不退时，应请医生诊治。 | K65: 儿童注意事项： 尚不明确。 妊娠与哺乳期注意事项： 尚不明确。 老人注意事项： 尚不明确。 | L65: 尚不明确。 | M65: 非甾体类解热镇痛消炎药，作用机制是抑制前列腺素的合成，从而发挥解热、镇痛、消炎作用。 | N65: 密封，在阴凉处保存。 | O65: 5毫升:0.1克 | Q65: 暂定36个月。
A66: 通用名称：金嗓散结丸 商品名称：碑林 英文名称：JinSangSanJieWan(BeiLin) 汉语拼音：Jin Sang San Jie Wan | B66: 18.3 | C66: =IF(ISNUMBER(MATCH(#REF!,非处方药名称!A:A,0)),"非处方药","处方药") -> 处方药 | D66: 马勃、莪术（醋炒）、金银花、桃仁（燀）、玄参、三棱（醋炒）、红花、丹参、板蓝根、麦冬、浙贝母、泽泻、鸡内金（炒）、蝉蜕、木蝴蝶、蒲公英。 | E66: 本品为棕黑色的水蜜丸;气微，味甘，微苦。 | F66: 清热解毒，活血化瘀，利湿化痰。用于热毒蕴结、气滞血瘀所致的声音嘶哑、声带充血、肿胀；慢性喉炎、声带小结、声带息肉见上述证候者。 | G66: 口服。一日2次，一次60-120粒。 | H66: 尚不明确。 | I66: 忌辛辣食物。 | J66: 请遵医嘱。 | L66: 如与其他药物同时使用可能会发生药物相互作用，详情请咨询医师或药师。 | N66: 密封。 | O66: 每10粒重1克 | P66: 塑料瓶，每瓶装360丸。 | Q66: 24个月。
A67: 通用名称：余麦口咽合剂 商品名称：好医生 英文名称：YuMaiKouYanHeJi(DianHong) 汉语拼音：Yumaikouyan Heji | B67: 36 | C67: =IF(ISNUMBER(MATCH(#REF!,非处方药名称!A:A,0)),"非处方药","处方药") -> 处方药 | D67: 余甘子、地黄、赤芍、麦冬、甘草，辅料为山梨酸钾。 | E67: 本品为棕褐色液体；味甜、微苦。 | F67: 彝医：麦枯息火。中医：滋阴降火。用于阴虚火旺、虚火上炎所致的口疮灼热、疼痛，局部红肿、心烦、口干，小便黄赤，以及复发性口腔溃疡见以上症状者。 | G67: 口服。一次15～20毫升(口含几分钟吞下，疗效更好)，一日3~4次。4~6日为一疗程。 | H67: 尚不明确。 | I67: 尚不明确。 | J67: 1.忌烟、酒及辛辣、油腻食物。2.不宜在服药期间同时服用温补性中药。3.孕妇慎用。儿童及年老体弱者应在医师指导下服用。4.脾虚大便溏者慎用。5.本品久置后有少量可摇散的沉淀，摇匀后使用。6.服药3天症状无缓解，应去医院就诊。7.对本品过敏者禁用，过敏体质者慎用。8.本品性状发生改变时禁止使用。9.儿童必须在成人监护下使用。10.请将本品放在儿童不能接触的地方。11.如正在使用其他药品，使用本品前请咨询医师或药师。 | L67: 如与其他药物同时使用可能会发生药物相互作用，详情请咨询医师或药师。 | N67: 密封。 | O67: 每1毫升相当于饮片1克 | P67: 口服液体药用塑料瓶装，每瓶100毫升，每盒1瓶。 | Q67: 24个月。
A68: 通用名称：障眼明片 商品名称：白云山中一 英文名称：ZhangYanMingPian(BaiYunShanZhongYi) 汉语拼音：Zhangyanming Pian | B68: 40.8 | C68: =IF(ISNUMBER(MATCH(#REF!,非处方药名称!A:A,0)),"非处方药","处方药") -> 处方药 | D68: 肉苁蓉、枸杞子、熟地黄、山茱萸、蕤仁(去内果皮)、密蒙花、菊花、决明子、青葙子、川芎、黄芪、黄精等味。 | E68: 本品为糖衣片，除去糖衣后显棕褐色；味苦、微酸。 | F68: 补益肝肾，退翳明目。用于初期及中期老年性白内障。 | G68: 口服。一次4片，一日3次。 | H68: 尚不明确。 | I68: 忌辛辣油腻食物，忌烟酒等。 | J68: 1.忌辛辣油腻食物，忌烟酒等。 2.脾胃虚寒、消化不良及老人用量酌减。 3.如遇外感发热等应停用本药。 4.对本品过敏者禁用，过敏体质者慎用。 5.本品性状发生改变时禁止使用。 6.请将本品放在儿童不能接触的地方。 7.如正在使用其他药品，使用本品前请咨询医师或药师。 | L68: 如与其他药物同时使用可能会发生药物相互作用，详情请咨询医师或药师。 | M68: 老年性白内障是常见的瞳神疾患，瞳神属肾，目者，五脏六腑之精，肾为藏精之所，肝血赖肾精以滋养，肾精亦赖肝血以滋生，肝肾亏损，也为白内障致病因之一。此症多脾气虚弱，肝肾不足，阴精亏损，无以上济于目，以致视力模糊，辨物不清。治法宜健脾调中，补益肝肾，升阳利窍，退翳明目。方中肉苁蓉、山茱萸、枸杞子、蕤仁补肝肾而益精气，党参、黄芪、甘草，健脾益胃，补气调中，辅以升麻能升举脾胃清阳之气，川芎为血中气药，辛散、温通，菊花、密蒙花清肝明目，除障退翳，蔓荆子、石菖蒲清利头目，开窍解浊，因此服后不仅视力提高，且能使视力疲劳，视物模糊得以改善而致消失，精神困倦，头晕眼花，胃纳欠佳，夜多小便，腰酸健忘等全身症状也获明显改善。此药对早期疗效更佳，可能通过补益肝肾，健脾调中，调节全身各器官功能，而达到提高睫状肌舒缩能力，增强晶状体弹性，抑制晶状体混浊发展，以及促进视网膜感光细胞的新陈代谢，而达到提高视力的作用。此外对陈旧性眼底病也有疗效，长期服用无副作用，动物实验无毒性，如口干可用淡盐水或菊花水送服。 | N68: 密封。 | O68: 糖衣片:片芯重0.21g;薄膜衣:每片重0.21g,每片重0.42g
A69: 通用名称：十五味萝蒂明目丸 商品名称：卓玛丹 英文名称：ShiWuWeiLuoDiMingMuWan(ZhuoMaDan) 汉语拼音：Shiwuwei Luodi Mingmu Wan | B69: 33 | C69: =IF(ISNUMBER(MATCH(#REF!,非处方药名称!A:A,0)),"非处方药","处方药") -> 处方药 | D69: 萝蒂、寒水石(奶制)、藏茴香、石灰华、甘草、红花、渣驯膏、丁香、金钱白花蛇、绿绒蒿、铁屑(诃子制)、诃子、余甘子(去核)、代赭石、毛诃子。 | E69: 本品为黑色水丸；有铁锈气，味苦。 | F69: 清肝、明目。用于早期白内障、结膜炎等。 | G69: 早晨服。一次2～3丸，一日1次。 | H69: 尚不明确。 | I69: 尚不明确。 | J69: 请遵医嘱。 | L69: 如与其他药物同时使用可能会发生药物相互作用详情请咨询医师或药师。 | M69: 1.消除晶状体混浊功效 (1)抗氧化，减少晶体不溶性蛋白产生：制剂中阿如拉 (诃子) 含酚氧化酶、过氧化酶、抗坏血酸氧化酶，实验证实，上述酶类可清除活性氧，防止与延缓晶状体混浊发生。 (2)所含藏药材含有丰富维生素 C ，为体内抗氧化剂，防止自由基对晶体蛋白损害。 2.促进晶状体混浊吸收 (1)药化学证实：萝蒂甙类化合物萝蒂羟基甙素，可使晶状体混浊物质吸收，晶体透明度明显改善，晶状体混浊逐渐消退。 (2)萝蒂提取物能激活晶状体内蛋白水解酶活性，可使晶体混浊物质变性蛋白水解消散。 3.消除结膜炎症功效 (1)杀菌、抑菌、消除致病微生物：制剂中阿如拉 (诃子) 、觉如拉 (余甘子) 有效成分诃子酸、诃黎勒酸、没食子酸、余甘子酸，对金黄色葡萄球菌、肺炎球菌、溶血性链球菌、绿脓杆菌有明显杀灭作用;对流感病毒亦有灭活作用。勒协 (丁香) 、郭牛 (茴香) 、木穷典元 (绿绒蒿) 亦有明显抑菌作用。 (2)调节免疫，抑制迟发性超敏发应，抗炎症：制剂中卡奇鸽尔更 (红花) 有效成分红花甙素调节免疫，抑制迟发性超敏反应;并能抑制毛细血管渗透性，减少炎性渗出，促进炎症吸收。 4.促进代谢，解除睫状肌痉挛，改善眼屈光状态 (1)补充营养物质：方中三果 (诃子、余甘子、毛诃子) 富含大量氨基酸、维生素，补充营养及生理性消耗，并是构成酶类 (辅酶Ⅰ、Ⅱ) 重要成分，起着促进生物氧化、维护视神经、眼肌、视力、上皮功能的作用。 (2)补充必需的微量元素：方中君西 (寒水石) 、吉合协 (铁屑) ，目宝巴加 (代赭石) 含有人体必需的微量元素，如锌、钴、锰、铬、铁、镁等，它们是核酸、 DNA 蛋白质合成，酶代谢，维持夜间视力，促进代谢重要物质。 (3)促进眼部血循环，改善眼部代谢： 方中卡奇鸽尔更 (藏红花) 甙类化合物红花甙、红花素、红花多糖扩张眼部血管、改善眼部营养，促进眼部代谢。从而消除眼肌痉挛，净化屈光系统，对眼肌疲劳有明显疗效。 | N69: 密闭，置阴凉干燥处。 | O69: 每丸重1g;0.25g | P69: 药用PVC硬片/药用包装用铝箔。15丸/板×6
A70: 通用名称：牛黄解毒片 商品名称：薄膜衣片 英文名称：NiuHuangJieDuPian(BaoMoYiPian) 汉语拼音：Niu Huang Jie Du Pian | B70: 6 | C70: =IF(ISNUMBER(MATCH(#REF!,非处方药名称!A:A,0)),"非处方药","处方药") -> 处方药 | D70: 人工牛黄、雄黄、石膏、大黄、黄芩、桔梗、冰片、甘草。 | E70: 本品为薄膜衣片，除去包衣后显棕黄色；有冰片香气，味微苦、辛。 | F70: 清热解毒。用于火热内盛，咽喉肿痛，牙龈肿痛，口舌生疮，目赤肿痛。 | G70: 口服。一次3片，一日2-3次。 | H70: 尚不明确。 | I70: 孕妇禁用。 | J70: 请遵医嘱。 | L70: 如与其他药物同时使用可能会发生药物相互作用，详情请咨询医师或药师。 | M70: 牛黄解毒片具有明显的解热、抗炎以及镇痛、镇静、抗惊厥等作用，对引发各种炎症的多种致病微生物有较强的抑制作用。 | N70: 药品阴凉贮存区(20℃以下) | O70: 片芯重0.27克 | P70: 铝塑板装，每板装10片。
A71: 通用名称：曲安奈德鼻喷雾剂 商品名称：珍德 英文名称：Triamcinolone Acetonide Nasal Spray 汉语拼音：Qu'annaide Bi Penwu Ji | B71: 21.9 | C71: =IF(ISNUMBER(MATCH(#REF!,非处方药名称!A:A,0)),"非处方药","处方药") -> 处方药 | D71: 曲安奈德。化学名称：9-氟-11β，21-二羟基-16α，17【(1-甲基亚乙基)双(氧)】-孕甾-1，4-二烯-3，20-二酮。 | E71: 水混悬溶液 | F71: 本品适于预防和治疗成人和6岁以下儿童的常年性及季节性过敏性鼻炎，其症状主要有鼻痒、鼻阻、流鼻涕、打喷嚏等。 | G71: 鼻腔内喷雾治疗。用前应充分振摇，使均匀。当使用次数超过120次后，每揿的实际给药量会低于55μ克，因此应抛弃药瓶，并不得将残留的药液倒入其他瓶使用。 (具体使用步骤参见附图)。 1.成人和12岁以上的儿童：每天一次，每次各鼻孔两揿(220μ克／天)。每日总剂量不超过八揿。 2.6～12岁的儿童：每天一次，每次每鼻孔一揿(110μ克／天)。每日最大推荐剂量为：每天一次，每次每鼻孔两揿(220μ克／天)。 3.或遵医嘱。 4.为达到最佳疗效，应有规律用药。对部分患者而言，在治疗第一天症状会有所改善，但通常来说，需1周的治疗方可达到最大疗效。 | H71: 在临床研究中观察，与其它鼻部吸入剂一样，本品有关的局部不良反应包括偶见鼻、咽部干燥或灼感，喷嚏或轻微鼻出血、头痛等，但一般不需停药，随着身体对本品的适应，上述症状随之消失。与其它鼻喷雾剂一样，可能发生鼻分泌物呈黄色或绿色，感觉有异味，鼻部或咽部有较严重的刺痛或流鼻血，请向医生咨询。经鼻应用皮质激素后曾有病人可能发生鼻中隔穿孔、眼压升高的报道，但极为罕见，通常见于曾做过鼻手术的病人。 | I71: 对醋酸曲安奈德过敏者禁用。 | J71: 1.鼻腔和鼻旁窦伴有细菌感染者，应同时进行抗菌治疗。 2.已经全身应用糖皮质激素类药物并造成肾上腺功能损伤者，改用本药局部治疗时，也应注意检查垂体一肾上腺系统的功能。 3.对严重过敏性鼻炎病人，尤其是伴有过敏性眼部症状者应同时接受其它药物治疗。 4.早有病例发生鼻、咽部白色念球菌感染，一旦发生应给予适当的治疗并间断本品使用。 5.下例情况慎用本品：呼吸道活动性结核病，未治疗的真菌病，全身性或病毒性感染，或眼部单纯疱疹病毒感染。 6.鼻中隔溃疡、鼻部手术或创伤后慎用本品。 | K71: 儿童注意事项： 6～12岁的儿童：每天一次，每次每鼻孔一揿(110μ克／天)，每日最大推荐剂量为：每天一次，每次每鼻孔两揿(220μ克／天)。 妊娠与哺乳期注意事项： 孕妇及哺乳期妇女慎用。或遵医嘱。 老人注意事项： 用量同成年人。 | L71: 尚不明确。 | M71: 药理作用 曲安奈德属曲安西龙的衍生物，为一种强效的糖皮质激素。具有明显的抗过敏作用，可明显减轻过敏性鼻炎的鼻腔症状。糖皮质激素抗过敏的确切机制尚不清楚。 毒理研究 生殖毒性：雌、雄大鼠口服曲安奈德剂量达15μ克／千克(按体表面积计算，相当于成人鼻腔给药每日最大推荐量的1／2)时，对怀孕率无影响；给药剂量等于和大于5μ克／千克(同上计算，相当于成人鼻腔给药每曰最大推荐量的1／5)时，出现吸收胎和死胎数增加，仔鼠体重和存活率降低；剂量为升μ克／千克(同上计算，相当于成人鼻腔给药每日最大推荐量的1／30)时未见上述反应。曲安奈德喷雾剂吸入给药对大鼠、兔、猴均表现出致畸作用。对上述各种动物的致畸剂量分别为大鼠20μ克／k9.家兔20μ克／k9.猴500μ克／千克(同上计算，分别相当于成人鼻腔给药每日最大推荐量的7／10.2.37倍)，大鼠和家兔表现出的剂量相关性致畸表现为腭裂、脑积水和中轴骨骼缺陷，而猴表现出的致畸作用为颅骨畸形。尚无怀孕妇女的充分和严格对照的临床研究。只有在本品对胎儿的潜在利益大于潜在危害时，才能在怀孕期使用本品。 致癌性：大鼠连续2年口服曲安奈德剂量达1μ克／千克(同上计算，分别相当于成人和儿童鼻腔给药每日最大推荐量的1／30和1／50)、大鼠连续2年口服曲安奈德剂量达3μ克／千克(同上计算，分别相当于成人、儿童鼻腔给药每曰最大推荐量的1／12和1／30)时，均未表现出致癌性。 | N71: 密封、在凉暗处保存。 | O71: 6毫升：6.6毫克，每瓶120揿，每揿含曲安奈德55微克
A72: 通用名称：富马酸酮替芬片 商品名称：鹏鹞 英文名称：Ketotifen Fumarate Tablets 汉语拼音：Fumasuan Tongtifen Pian | B72: 3 | C72: =IF(ISNUMBER(MATCH(#REF!,非处方药名称!A:A,0)),"非处方药","处方药") -> 处方药 | D72: 富马酸酮替芬 | E72: 本品为白色或类白色片。 | F72: 用于过敏性鼻炎,过敏性支气管哮喘。 | G72: 口服,每次半片或1片,一日2次,早晚服.儿童剂量请咨询医师或药师。 | H72: 1 常见有嗜睡、倦怠、口干、恶心等胃肠道反应。 2 偶见头痛、头晕、迟钝以及体重增加。 | I72: 对本品过敏者,车辆驾驶员,机械操作者以及高空作业者工作时禁用。 | J72: 1 服药期间不得驾驶机、车、船、从事高空作业、机械作业及操作精密仪器。 2 儿童用量请咨询医师或药师。 3 孕妇慎用。 4 对本品过敏者禁用，过敏体质者慎用。 5 本品性状发生改变时禁止使用。 6 请将本品放在儿童不能接触的地方。 7 儿童必须在成人监护下使用。 8 如正在使用其他药品，使用本品前请咨询医师或药师。 | K72: 儿童注意事项： 遵医嘱。 妊娠与哺乳期注意事项： 孕妇慎用。 老人注意事项： 遵医嘱。 | L72: 1 与多种中枢神经抑制剂或酒精并用，可增强本品的镇静作用，应予避免。 2 不得与口服降血糖药并用。 3 如与其他药物同时使用可能会发生药物相互作用，详情请咨询医师或药师。 | M72: 本品兼有组胺H1受体拮抗作用和抑制过敏反应介质释放作用,不仅抗过敏作用较强,且药效持续时间较长,故对预防各种支气管哮喘发作及外源性哮喘的疗效比对内源性哮喘更佳。 | N72: 遮光、密封保存。 | O72: 1mg(按C19H19NOS计) | P72: 1mg*60s | Q72: 36个月
A73: 通用名称：清开灵滴丸 商品名称：瑞亿 英文名称：QingKaiLingDiWan(RuiYi) 汉语拼音：Qingkailing Diwan | B73: 19.8 | C73: =IF(ISNUMBER(MATCH(#REF!,非处方药名称!A:A,0)),"非处方药","处方药") -> 处方药 | D73: 胆酸、珍珠母、猪去胆氧酸、栀子、水牛角、板蓝根、黄芩苷、金银花。 | E73: 本品为棕褐色的滴丸；气香，味微苦。 | F73: 清热解毒，镇静安神。用于外感风热所致发热，烦躁不安，咽喉肿痛；及上呼吸道感染、病毒性感冒、急性咽炎见上述证候者。 | G73: 口服或舌下含服。一次10～20丸，一日2～3次；儿童酌减或遵医嘱。 | H73: 尚不明确 | I73: 孕妇禁用。 | J73: 1 忌烟、酒及辛辣、生冷、油腻食物。 2 不宜在服药期间同时服滋补性中药。 3 风寒感冒者不适用，其表现为恶寒重，发热轻，无汗，头痛，鼻塞，流清涕，喉痒咳嗽。 4 高血压、心脏病患者慎服；平素脾胃虚寒及久病体虚患者如出现腹泻时慎服。 5 患有肝病、肾病、糖尿病等慢性病严重者应在医生指导下服用。 6 服药3天症状无缓解，应去医院就诊。 7 儿童、年老体弱者应在医师指导下服用。 8 对本品过敏者禁用，过敏体质者慎用。 9 本品性状发生改变时禁止使用。 10 儿童必须在成人监护下使用。 11 请将本品放在儿童不能接触的地方。 12 如正在使用其他药品，使用本品前请咨询医师或药师。 | L73: 如与其他药物同时使用可能会发生药物相互作用，详情请咨询医师或药师。 | M73: 本品能抑制小鼠电惊厥反应，提高小鼠耐缺氧能力，降低伤寒副伤寒三联菌苗引起家兔的发热反应。说明本品具有抗惊厥，解热，提高机体耐力等作用。 | N73: 密封。 | O73: 每10丸重0.35g
A74: 通用名称：复方黄芩片 商品名称：康乐 英文名称：FuFangHuangQinPian(KangLe) 汉语拼音：Fufang Huangqin Pian | B74: 10.9 | C74: =IF(ISNUMBER(MATCH(#REF!,非处方药名称!A:A,0)),"非处方药","处方药") -> 处方药 | D74: 黄芩、虎杖、穿心莲、十大功劳。 | E74: 本品为糖衣片，除去糖衣后显棕褐色；味苦。 | F74: 清热解毒，凉血消肿。用于咽喉肿痛，口舌生疮，感冒发热，痈肿疮疡。 | G74: 口服。一次4片，一日3～4次。 | H74: 尚不明确。 | I74: 尚不明确。 | J74: 1忌辛辣、鱼腥食物。 2不宜在服药期间同时服用温补性中成药。 3服药三天后症状无改善，或出现其他症状，应去医院就诊。 4按照用法用量服用，儿童应在医师指导下服用。 5对本品过敏者禁用，过敏体质者慎用。 6本品性状发生改变时禁止使用。 7儿童必须在成人的监护下使用。 8请将本品放在儿童不能接触的地方。 9如正在使用其他药品，使用本品前请咨询医师或药师。 | L74: 如与其他药物同时使用可能会发生药物相互作用，详情请咨询医师或药师。 | N74: 密封。 | O74: (薄膜衣)每片重0.33克 | Q74: 24月
A75: 通用名称：山蜡梅叶颗粒 商品名称：佑美 英文名称：shanlameiyekeli(youmei) 汉语拼音：shanlameiyekeli(youmei) | B75: 15.8 | C75: =IF(ISNUMBER(MATCH(#REF!,非处方药名称!A:A,0)),"非处方药","处方药") -> 处方药 | D75: 本品为棕黄色至棕褐色的颗粒；气香，味甜、微苦。 | E75: 本品为棕黄色至棕褐色颗粒，气香，味甜，微苦。 | F75: 辛凉解表，清热解毒。用于风热感冒，发热，恶寒，咽痛。 | G75: 开水冲服，一次10克，一日3次。 | H75: 尚不明确。 | I75: 尚不明确。 | J75: 请遵医嘱。 | L75: 如与其他药物同时使用可能会发生药物相互作用，详情请咨询医师或药师。 | N75: 密封。 | O75: 每袋装10g | Q75: 36月
A76: 通用名称：金嗓开音丸 商品名称：碑林 英文名称：JinSangKaiYinWan(BeiLin) 汉语拼音：Jinsang Kaiyin Wan | B76: 20.2 | C76: =IF(ISNUMBER(MATCH(#REF!,非处方药名称!A:A,0)),"非处方药","处方药") -> 处方药 | D76: 金银花、连翘、玄参、板蓝根、赤芍、黄芩、桑叶、菊花、前胡、苦杏仁（去皮）、牛蒡子、泽泻、胖大海、僵蚕（麸炒）、蝉蜕、木蝴蝶。辅料为：蜂蜜。 | E76: 本品为黑褐色的水蜜丸；气微，味甘。 | F76: 疏风，清热，利咽开音。用于风热邪毒引起的咽喉肿痛，声音嘶哑，急性咽炎、急性喉炎具有上述症候者 。 | G76: 口服。水蜜丸60～120丸（6克～12克），一日2次。 | H76: 尚不明确。 | I76: 尚不明确。 | J76: 1.忌辛辣、鱼腥食物。 2.不宜在服药期间同时服用温补性中成药。 3.不适用于外感风邪所致的咽喉痛、声音嘶哑者。 4.服药七天后症状无改善，或咽喉痛、声音嘶哑加重、或出现其他症状，应去医院就诊。 5.凡脾气虚大便溏者慎用。 6.按照用法用量服用，儿童应在医师指导下服用。 7.对本品过敏者禁用，过敏体质者慎用。 8.本品性状发生改变时禁止服用。 9.儿童必须在成人的监护下使用。 10.请将此药品放在儿童不能接触的地方。 11.如正在服用其他药物，使用本品前请咨询医师或药师。 | L76: 如与其他药物同时使用可能会发生药物相互作用，详情请咨询医师或药师。 | N76: 密闭，防潮。 | O76: 水蜜丸每10丸重1g | Q76: 24个月
A77: 通用名称：盐酸非索非那定片 商品名称：莱多菲 英文名称：Fexofenadine Hydrochloride Tablets 汉语拼音：Yansuan Feisuofeinading Pian | B77: 25 | C77: =IF(ISNUMBER(MATCH(#REF!,非处方药名称!A:A,0)),"非处方药","处方药") -> 处方药 | D77: 本品主要成份为盐酸非索非那定，其化学名为&plusmn;4-[4-[4-(羟基二苯基甲基)-1-哌啶基]-1-羟基丁基]-&alpha;,&alpha;-二甲基苯乙酸盐酸盐。 | E77: 本品为薄膜衣片，除去包衣后显白色或类白色。 | F77: 适用于缓解成人和12岁及12岁以上的儿童的季节过敏性鼻炎相关的症状。如打喷嚏，流鼻涕，鼻、上腭、喉咙发痒，眼睛发痒、潮湿、发红。 | G77: 成人、12岁及12岁以上的儿童:口服，一日一次，一次120mg。肾功能不全的患者推荐起始剂量为60mg，一日一次。 | H77: 季节性过敏性鼻炎 安慰剂对照的季节性过敏性鼻炎临床试验中，2461名12岁及12岁以上患者接受了盐酸非索非那定20mg至240mg一日2次的治疗，盐酸非索非那定与安慰剂不良反应相似。安慰剂对照的季节性过敏性鼻炎临床试验中，570名12岁及12岁以上患者接受了盐酸非索非那定120mg或180mg一日一次治疗，盐酸非索非那定与安慰剂不良反应相似。以上研究表明，不良反应的发生率，包括思睡，都不是剂量相关性的，并且在各种年龄、性别和种族组之间是相似的。 | I77: 对本品成份过敏者禁用。 | J77: 尚不明确。 | K77: 儿童注意事项： 盐酸非索非那定对6岁以下儿童患者的安全性和疗效尚未建立。 妊娠与哺乳期注意事项： 由于缺乏妊娠妇女用药资料，因此，除非所获利益大于对胎儿的潜在危险，否则妊娠妇女不应服用本品。对哺乳的影响：虽未进行足够的和较好的哺乳期妇女对照研究，但因为很多药物都会在人乳中分泌，因此哺乳期妇女慎用。 老人注意事项： 尚不能确定老年患者与年轻患者的反应是否有差异。但是由于该药物经肾脏排泄，肾功能损伤的患者药物毒性反应发生的危险性有可能增加。而老年患者很可能有肾功能的下降，因此剂量的选择需谨慎，必要时需要进行肾功能监测。 | L77: 与红霉素和酮康唑的药物相互作用： 同时给予酮康唑和红霉素增加了非索非那定的胃肠吸收。在体内动物研究中也表明除增加吸收之外，酮康唑降低了盐酸非索非那定的胃肠分泌，而红霉素也可能降低胆汁排泄。盐酸非索非那定对红霉素和酮康唑的药动学无明显影响。药物与抗酸剂的相互作用： 在15分钟内给予120mg盐酸非索非那定（2times;60mg胶囊）和含有铝和镁抗酸剂（Maalox）降低了非索非那定AUC的41%和Cmax的43%。盐酸非索非那定不应该与含有铝和镁的抗酸剂差不多时间给予。 | M77: 药理作用:盐酸非索非那定是具有选择性外周H1受体拮抗作用的抗组胺药物。非索非那定在大鼠中抑制组胺从腹膜肥大细胞释放。在实验动物中，没有观察到抗胆碱、α1-肾上腺素或β-肾上腺素受体阻断作用，也未观察到镇静或其他中枢神经系统作用。本品不能通过血脑屏障。 | N77: 密封保存。有效期：暂定18个月。 | O77: 30毫克 | Q77: 24月
A78: 通用名称：耳聋通窍丸 商品名称：花溪 英文名称：HuaXiErLongTongQiaoWan 汉语拼音：ErLongTongQiaoWan | B78: 41.4 | C78: =IF(ISNUMBER(MATCH(#REF!,非处方药名称!A:A,0)),"非处方药","处方药") -> 处方药 | D78: 龙胆、黄柏、大黄、栀子(姜制)、石菖蒲、当归、芦荟、黄芩、黄连、磁石(煅)、木香、路路通。辅料为青黛、滑石粉、明胶。 | E78: 本品为灰黑色的水丸；除去外衣呈灰褐色，味苦。 | F78: 清热泻火，利湿通便。用于肝胆火盛，头眩目胀，耳聋耳鸣，耳内流脓，大便干燥，小便赤黄。 | G78: 口服。一次5克，一日1次。 | H78: 尚不明确。 | I78: 尚不明确。 | J78: 孕妇忌服。 | L78: 如与其他药物同时使用可能会发生药物相互作用，详情请咨询医师或药师。 | N78: 密闭，防潮。 | O78: 每袋装5g | P78: 5克*9袋/盒，5袋/盒，10袋/盒，3袋/盒 | Q78: 24月
A79: 通用名称：氧氟沙星滴眼液 商品名称：泰利必妥 英文名称：Ofloxacin Eye Drops 汉语拼音：YangFuShaXingDiYanYe | B79: 22.7 | C79: =IF(ISNUMBER(MATCH(#REF!,非处方药名称!A:A,0)),"非处方药","处方药") -> 处方药 | D79: 氧氟沙星 | E79: 本品为淡黄色或淡黄绿色的澄明液体。 | F79: 适用于治疗细菌性结膜炎、角膜炎、角膜溃疡、泪囊炎、术后感染等外眼感染。 | G79: 滴于眼睑内，每日3-5次，每次1-2滴，或遵医嘱。 | H79: 偶尔有辛辣似蜇样的刺激症状。 | I79: 对氧氟沙星或喹诺酮类过敏者禁用。 | J79: 1.不宜长期使用，使用中出现过敏症状，应立即停止使用。 2.只限于滴眼用。 3.滴眼时瓶口勿接触眼睛;使用后应将瓶盖拧紧，以免污染药品。 4.当药品性状发生改变时，禁止使用。 5.儿童必须在成人监护下使用。 6.请将此药品放在儿童不能接触的地方。 | K79: 儿童注意事项： 尚不明确。 妊娠与哺乳期注意事项： 尚不明确。 老人注意事项： 尚不明确。 | L79: 氧氟沙星与抗凝剂之间的相互作用不明显，本品与头孢噻肟、甲硝唑、克林霉素、环孢菌素等同用后，各药物的药动学过程均无明显改变。 | M79: 广谱抗菌药，对沙眼衣原体亦有效。主要用于治疗细菌性外眼感染、沙眼及细菌性眼内感染。 | N79: 遮光、密闭保存。 | O79: 5ml:15mg | Q79: 12个月
A80: 通用名称：酚麻美敏片 商品名称：泰诺 英文名称：Paracetamol,Pseudoepherine Hydrochloride,Dextromethorphan Hydrobromide and Chlorphenamine Maleate Tablets 汉语拼音：fenmameiminpian | B80: 11 | C80: =IF(ISNUMBER(MATCH(#REF!,非处方药名称!A:A,0)),"非处方药","处方药") -> 处方药 | D80: 本品为复方制剂，每片含主要成份对乙酰氨基酚325毫克、盐酸伪麻黄碱30毫克、氢溴酸右美沙芬15毫克、马来酸氯苯那敏2毫克。辅料为：粉状纤维素、预胶化淀粉、淀粉甘醇酸钠、微晶纤维素、淀粉、硬脂酸镁、欧巴代和棕榈蜡。 | E80: 本品为薄膜衣片，除去包衣后，显白色或类白色。 | F80: 用于普通感冒或流行性感冒引起的发热、头痛、四肢酸痛、打喷嚏、流鼻涕、鼻塞、咳嗽、咽痛等症状。 | G80: 口服，成人每6小时1～2片，24小时不超过8片；6～12岁儿童每6小时1片， 24小时不超过4片。 | H80: 有时有轻度头晕、乏力、恶心、上腹不适、口干、食欲缺乏和皮疹，可自行恢复。 | I80: 严重肝肾功能不全者禁用。 | J80: 1.用药3-7天，症状未缓解，请咨询医师或药师。 2.12岁以下儿童用量请咨诲医师或药师。 3.服用本品期间不得饮酒或含有酒精的饮料。 4.不能同时服用与本品成份相似的其他抗感冒药。 5.心脏病、高血压、甲状腺疾病、糖尿病、前列腺肥大、青光眼、抑郁症、哮喘等患者以及老年人应在医师指导下使用。 6.孕妇及哺乳期妇女慎用。 7.肝、肾功能不全者慎用。 8.运动员慎用。 9.服药期间不得驾驶机、车、船、从事高空作业、机械作业及操作精密仪器。 10.对本品过敏者禁用，过敏体质者慎用。 11.本品性状发生改变时禁止 | K80: 儿童注意事项： 6岁以下儿童不宜使用本药。 妊娠与哺乳期注意事项： 妊娠期及哺乳期妇女慎用。 老人注意事项： 尚未明确。 | L80: 1.与其他解热镇痛药同用，可增加肾毒性的文献。2.本品不宜与氯霉素、巴比妥类(如苯巴比妥)、解痉药(如颠茄)、酚妥拉明、洋地黄苷类并用。3.如与其他药物药物同时使用可能会发生药物相互作用，详情请咨询医师或药师。 | M80: 本品中对乙酰氨基酚能抑制前列腺素合成，具有解热镇痛作用;口服后胃肠道吸收，0.5-2小时血药浓度达到峰值，作用3-4小时。盐酸伪麻黄碱能选择性收缩上呼吸道血管，胡鼻部粘膜出血，减轻鼻塞、流涕、打喷嚏等症状。氢溴酸右美沙芬能抑制咳嗽中枢产生镇咳作用，口服后30分钟起效，作用持续6小时。马来酸氯苯那敏为抗组胺药，可消除或减轻感冒所致的流泪、流涕、喷嚏等过敏症状，口服后15-60分钟起效，作用可维持4-6小时。 | N80: 密封，干燥处保存。 | O80: 对乙酰氨基酚325毫克,盐酸伪麻黄碱30毫克,氢溴酸右美沙芬15毫克,马来酸氯苯那敏2毫克 | P80: PVC/PVDC泡罩硬片、铝箔包装，10片/盒。 | Q80: 60个月。
A81: 通用名称：盐酸西替利嗪片 商品名称：西可韦 英文名称：Cetirizine Hydrochloride Tablets 汉语拼音：Yansuanxitiliqin Pian | B81: 9.2 | C81: =IF(ISNUMBER(MATCH(#REF!,非处方药名称!A:A,0)),"非处方药","处方药") -> 处方药 | D81: 本品主要成份为：盐酸西替利嗪。其化学名称为：()-2-[2-[4-[(4-氯苯基)苯甲基]-1-哌嗪基]乙氧基]乙酸二盐酸盐。 | E81: 本品为白色或类白色片。 | F81: 用于季节性或常年性过敏性鼻炎、由过敏原引起的荨麻疹及皮肤瘙痒。 | G81: 口服：成人或12岁以上儿童，一次10mg，一日1次或遵医嘱。如出现不良反应，可改为早晚各5mg。6～11岁儿童，根据症状的严重程度不同，推荐起始剂量为5mg或10mg，一日1次。2～5岁儿童，推荐起始剂量为2.5mg，一日1次；最大剂量可增至5mg，一日1次，或2.5mg每12小时1次。 | H81: 不良反应轻微且为一过性，有困倦、嗜睡、头痛、眩晕、激动、口干及胃肠道不适等。偶有天门冬氨酸氨基转移酶轻度升高。 | I81: 对本品过敏者禁用。 | J81: 1 肾功能损害者用量应减半。 2 酒后避免使用。 3 司机、操作机器或高空作业人员慎用。 | K81: 儿童注意事项： 在医生指导下服用。 妊娠与哺乳期注意事项： 孕妇及哺乳期妇女禁用。 老人注意事项： 老年人慎用。 | L81: 未发现有与其他药物相互作用的报道，但同时服用镇静药时应慎重。 | M81: 本品为选择性组胺H1受体拮抗剂。动物实验表明本品无明显抗胆碱和抗5-羟色胺作用，不易通过血-脑脊液屏障而作用于中枢H1受体，临床使用时中枢抑制作用较轻。 | N81: 遮光、密封保存。 | O81: 10毫克 | P81: l0mg*12T | Q81: 36个月
A82: 通用名称：双黄连口服液 商品名称：太龙 英文名称：ShuangHuangLianKouFuYe(TaiLong) 汉语拼音：Shuang Huang Lian Kou Fu Ye | B82: 15.2 | C82: =IF(ISNUMBER(MATCH(#REF!,非处方药名称!A:A,0)),"非处方药","处方药") -> 处方药 | D82: 金银花、黄芩、连翘。 | E82: 本品为棕红色的澄清液体;味甜，微苦。 | F82: 疏风解表，清热解毒。用于外感风热所致的感冒，症见发热、咳嗽、咽痛。 | G82: 口服。一次2支，一日3次。 | H82: 尚不明确。 | I82: 尚不明确。 | J82: 1.忌烟、酒及辛辣、生冷、油腻食物。 2.不宜在服药期间同时服用滋补性中成药。 3.风寒感冒者不适用，其表现为恶寒重，发热轻，无汗，鼻塞流清涕，口不渴，咳吐稀白痰。 4.有高血压、心脏病、肝病、糖尿病、肾病等慢性病严重者、孕妇或正在接受其它治疗的患者，均应在医师指导下服用。 5.服药三天后，症状无改善，或出现发热咳嗽加重，并有其他症状如胸闷、心悸等时应去医院就诊。 6.按照用法用量服用，小儿、年老体虚者应在医师指导下服用。 7.连续服用应向医师咨询。 8.药品性状发生改变时禁止服用。 9.儿童必须在成人的监护下使用。 10.请将此药品放在儿童不能接触的地方。 11.如正在服用其他药品，使用本品前请咨询医师或药师。 | L82: 如与其他药物同时使用可能会发生药物相互作用，详情请咨询医师或药师。 | M82: 清热解毒。 | N82: 密封，避光，置阴凉处。 | O82: 每支装10毫升；每支装10毫升(浓缩型) | P82: 10ml*10支/盒。
A83: 通用名称：清开灵软胶囊 商品名称：神威 英文名称：QingKaiLingRuanJiaoNang(ShenWei) 汉语拼音：Qingkailing Ruanjiaonang | B83: 19.8 | C83: =IF(ISNUMBER(MATCH(#REF!,非处方药名称!A:A,0)),"非处方药","处方药") -> 处方药 | D83: 胆酸、珍珠母、猪去氧胆酸、栀子、水牛角、板蓝根、黄芩甙、金银花。辅料为明胶，甘油，葡萄紫，精制玉米油，大豆磷脂，蜂蜡。 | E83: 本品为软胶囊，内容物为棕褐色至棕黑色的膏状物；气特异，味苦。 | F83: 清热解毒，镇静安神。用于外感风热所致发热，烦躁不安，咽喉肿痛；上呼吸道感染，病毒性感冒，急性咽炎等病症属上述证候者。 | G83: 口服。一次1～2粒，一日3次；儿童酌减或遵医嘱。 | H83: 尚不明确。 | I83: 尚不明确。 | J83: 1.忌烟、酒及辛辣、生冷、油腻食物。 2.不宜在服药期间同时服滋补性中药。 3.风寒感冒者不适用，其表现为恶寒重，发热轻，无汗，头痛，鼻塞，流清涕，喉痒咳嗽。 4.平素脾胃虚寒及久病体虚患者如出现腹泻时慎用。 5.患有肝病、肾病、糖尿病等慢性病严重者应在医生指导下服用。 6.孕妇及高血压、心脏病患者慎用。 7.服药3天后或服药期间症状无改善，或症状加重，或出现新的严重症状如胸闷、心悸等应立即停药，并去医院就诊。 8.小儿、年老体弱者应在医师指导下服用。 9.对本品过敏者禁用，过敏体质者慎用。 10.本品性 | L83: 如与其他药物同时使用可能会发生药物相互作用，详情请咨询医师或药师。 | N83: 密封，置阴凉(不超过20℃)干燥处。 | O83: 每粒装0.4克(含黄芩苷20毫克)；每粒装0.2克(含黄芩苷10毫克) | P83: 铝塑泡罩包装，每盒1板，每板12粒。 | Q83: 30个月。
A84: 通用名称：知柏地黄丸 商品名称：同仁堂 英文名称：zhibaidihuangwan(tongrentang)(shuimiwan) 汉语拼音：Zhibai Dihuang Wan | B84: 12.7 | C84: =IF(ISNUMBER(MATCH(#REF!,非处方药名称!A:A,0)),"非处方药","处方药") -> 处方药 | D84: 知母、黄柏、熟地黄、山药、山茱萸(制)、牡丹皮、茯苓、泽泻。辅料为蜂蜜。 | E84: 本品为黑褐色的大蜜丸；味甜而带酸苦。 | F84: 滋阴清热。用于潮热盗汗，口干咽痛，耳鸣遗精。 | G84: 口服。一次6克(30粒)，一日2次。 | H84: 尚不明确。 | I84: 尚不明确。 | J84: 1.孕妇慎用。 2.虚寒性病患者不适用，其表现为怕冷，手足凉，喜热饮。 3.不宜和感冒类药同时服用。 4.本品宜空腹或饭前服用开水或淡盐水送服。 5.服药一周症状无改善，应去医院就诊。 6.药品性状发生改变时禁止服用。 7.按照用法用量服用，小儿应在医师指导下服用。 8.儿童必须在成人的监护下使用。 9.请将此药品放在儿童不能接触的地方。 10.如在服用其他药品，使用本品前请咨询医师或药师。 | L84: 如与其他药物同时使用可能会发生药物相互作用，详情请咨询医师或药师。 | N84: 密封。 | O84: 每100粒重20克 | P84: 塑料瓶装，每瓶装360粒。 | Q84: 60个月。
A85: 通用名称：天麻首乌片 商品名称：国华 英文名称：TianMaShouWuPian(GuoHua) 汉语拼音：Tianma Shouwu Pian | B85: 22.5 | C85: =IF(ISNUMBER(MATCH(#REF!,非处方药名称!A:A,0)),"非处方药","处方药") -> 处方药 | D85: 天麻、白芷、何首乌、熟地黄、丹参、川芎、当归、蒺藜（炒）、桑叶、墨旱莲、女贞子、白芍、黄精、甘草。辅料为：蔗糖、滑石粉、硬脂酸镁、明胶、柠檬黄。 | E85: 本品为糖衣片，除去包衣后显棕褐色；气香，味微苦。 | F85: 滋阴补肾，养血息风。用于肝肾阴虚所致的头晕目眩、头痛耳鸣、口苦咽干、腰膝痠软、脱发、白发；血管神经性头痛、脂溢性脱发见上述证候者。 | G85: 口服。一次6片，一日3次。 | H85: 尚不明确。 | I85: 尚不明确。 | J85: 1.忌不易消化食物。 2.感冒发热病人不宜服用。 3.有高血压、心脏病、肝病、糖尿病、肾病等慢性病严重者应在医师指导下服用。 4.儿童、孕妇、哺乳期妇女应在医师指导下服用。 5.服药4周症状无缓解，应去医院就诊。 6.对本品过敏者禁用，过敏体质者慎用。 7.本品性状发生改变时禁止使用。 8.儿童必须在成人监护下使用。 9.请将本品放在儿童不能接触的地方。 10.如正在使用其他药品，使用本品前请咨询医师或药师。 | L85: 如与其他药物同时使用可能会发生药物相互作用，详情请咨询医师或药师。 | M85: 滋阴补肾，养血息风。 | N85: 密封，置干燥处。 | O85: 0.25克/片
A86: 通用名称：金嗓子喉片 商品名称：新包装 英文名称：JinSangZiHouPian(XinBaoZhuang) 汉语拼音：Jingsangzi Houpian | B86: 26.4 | C86: =IF(ISNUMBER(MATCH(#REF!,非处方药名称!A:A,0)),"非处方药","处方药") -> 处方药 | D86: 薄荷脑、金银花、西青果、桉油、石斛、罗汉果、橘红、八角茴香油等。 | E86: 本品为黄棕色至棕褐色的半透明扁圆片；气特异，味甜，有凉喉感。 | F86: 疏风清热，解毒利咽，芳香辟秽。适用于改善急性咽炎，急性喉炎所致的咽喉肿痛，干燥灼热，声音嘶哑等症。 | G86: 含服，一次1片，一日6次。 | H86: 尚不明确。 | I86: 尚不明确。 | J86: 1.忌烟酒、辛辣、鱼腥食物。 2.不宜在服药期间同时服用温补性中药。 3.孕妇慎用。糖尿病患者、儿童应在医师指导下服用。 4.脾虚大便溏者慎用。 5.属风寒感冒咽痛者，症见恶寒发热、无汗、鼻流清涕者慎用。 6.服药3天症状无缓解，应去医院就诊。 7.对该药品过敏者禁用，过敏体质者慎用。 8.该药品性状发生改变时禁止使用。 9.儿童必须在成人监护下使用。 10.请将该药品放在儿童不能接触的地方。 11.如正在使用其他药品，使用该药品前请咨询医师或药师。 | L86: 如与其他药物同时使用可能会发生药物相互作用，详情请咨询医师或药师。 | N86: 密封，置阴凉干燥处。 | O86: 每片重2克 | P86: 铝塑袋装；每袋装5片，4袋/盒。
A87: 通用名称：金喉健喷雾剂 商品名称：宏宇 英文名称：JinHouJianPenWuJi(HongYu) 汉语拼音：Jinhoujian Penwuji | B87: 21.3 | C87: =IF(ISNUMBER(MATCH(#REF!,非处方药名称!A:A,0)),"非处方药","处方药") -> 处方药 | D87: 艾纳香油，大果木姜子油，薄荷脑。 | E87: 本品为喷雾剂，容器中的药液为淡黄色的澄清液体，气芳香。 | F87: 苗医：宋宫证。蒙嘎宫昂，来罗拉米。中医：祛风解毒，消肿止痛，清咽利喉。用于风热所致咽痛、咽干、咽喉红肿、牙龈肿痛、口腔溃疡等症。 | G87: 喷患处，每次适量，一日数次。 | H87: 尚不明确。 | I87: 药品性状发生改变时禁止使用。 | J87: 1.忌辛辣、鱼腥食物。 2.使用时应避免接触眼睛。 3.不宜在服药期间同时服用温补性中药。 4.孕妇慎用。儿童应在医师指导下使用。 5.属风寒感冒咽痛者，症见恶寒发热、无汗、鼻流清涕者慎用。 6.切勿置本品于近火及高温处并严禁剧烈碰撞，使用时勿近明火。 7.用药3天症状无缓解，应去医院就诊。 8.对本品及酒精过敏者禁用，过敏体质者慎用。 9.本品性状发生改变时禁止使用。 10.儿童必须在成人监护下使用。 11.请将本品放在儿童不能接触的地方。 12.如正在使用其他药品，使用本品前请咨询医师或药师。 | L87: 如与其他药物同时使用可能发生药物相互作用，详情请咨询医师或药师。 | M87: 祛风解毒，消肿止痛，清咽利喉。 | N87: 密闭，在阴凉处保存。 | O87: 每瓶装10毫升，20毫升
A88: 通用名称：清音丸 商品名称：同仁堂 英文名称：QingYinWan(TongRenTang) 汉语拼音：Qingyin Wan | B88: 16 | C88: =IF(ISNUMBER(MATCH(#REF!,非处方药名称!A:A,0)),"非处方药","处方药") -> 处方药 | D88: 诃子肉、川贝母、百药煎、乌梅肉、葛根、茯苓、甘草、天花粉。辅料为赋形剂蜂蜜。 | E88: 本品为褐色的水蜜丸;味甘、微酸涩。 | F88: 清热利咽，生津润燥。用于肺热津亏，咽喉不利，口舌干燥，声哑失音。 | G88: 口服。温开水送服或噙化。一次2克，一日2次。 | H88: 尚不明确。 | I88: 尚不明确。 | J88: 1.忌辛辣食物。 2.有高血压、心脏病、肝病、糖尿病、肾病等慢性病严重者应在医师指导下服用。 3.声哑失音较重者，应及时去医院就诊。 4.儿童、孕妇、哺乳期妇女、年老体弱、脾虚便溏者应在医师指导下服用。 5.服药3天症状无缓解，应去医院就诊。 6.对本品过敏者禁用，过敏体质者慎用。 7.本品性状发生改变时禁止使用。 8.儿童必须在成人监护下使用。 9.请将本品放在儿童不能接触的地方。 10.如正在使用其他药品，使用本品前请咨询医师或药师。 | L88: 如与其他药物同时使用可能会发生药物相互作用，详情请咨询医师或药师。 | N88: 密封。 | O88: 每丸重3克 | P88: 塑料瓶装，每瓶装32克。 | Q88: 48个月
A89: 通用名称：鼻炎康片 商品名称：德众 英文名称：BiYanKangPian(DeZhong) 汉语拼音：Biyankang Pian | B89: 25.9 | C89: =IF(ISNUMBER(MATCH(#REF!,非处方药名称!A:A,0)),"非处方药","处方药") -> 处方药 | D89: 广藿香、苍耳子、鹅不食草、野菊花、黄芩、麻黄、当归、猪胆粉、薄荷油、马来酸氯苯那敏。辅料为硬脂酸镁、二氧化硅、氢氧化铝、淀粉、滑石粉、麦芽糊精、薄膜包衣预混剂。 | E89: 本品为糖衣片，除去糖衣后显褐棕色;味微甘而苦涩、有凉感。 | F89: 清热解毒，宣肺通窍，消肿止痛。用于急慢性鼻炎，过敏性鼻炎等。 | G89: 口服。一次4片，一日3次。 | H89: 可见困倦、嗜睡、口渴、虚弱感；个别患者服药后偶有胃部不适，停药后可消失。 | I89: 孕妇慎用。 | J89: 1.忌辛辣、鱼腥食物。 2.孕妇慎用。 3.凡过敏鼻炎属虚寒症者慎用。 4.高血压、心脏病等慢性病者，应在医师指导下服用。 5.个别患者服药后偶有胃部不适，停药后可消失；建议饭后服用。 6.急性鼻炎服药三天后症状无改善，或出现其他症状，应去医院就诊。 7.用药期间不宜驾驶车辆、管理机器及高空作业等。 8.按照用法用量服用，儿童应在医师指导下服用。 9.药品性状发生改变时禁止服用。 10.儿童必须在成人的监护下使用。 11.清将此药品放在儿童不能接触的地方。 12.如正在服用其他药物，使用本品前请咨询医师或 | K89: 妊娠与哺乳期注意事项： 孕妇慎用。 | L89: 如与其他药物同时使用可能发生药物相互作用，详情请咨询医师或药师。 | N89: 密封。 | O89: 每片重0.37克(含马来酸氯苯那敏1毫克) | P89: 高密度聚乙烯瓶，每瓶50片
A90: 通用名称：桂林西瓜霜 商品名称：三金 英文名称：GuiLinXiGuaShuang(SanJin) 汉语拼音：Guilin Xigua Shuang | B90: 14.6 | C90: =IF(ISNUMBER(MATCH(#REF!,非处方药名称!A:A,0)),"非处方药","处方药") -> 处方药 | D90: 西瓜霜、硼砂(煅)、黄柏、黄连、山豆根、射干、浙贝母、青黛、冰片、无患子果(炭)、大黄、黄芩、甘草、薄荷脑。辅料为二氧化硅、甜菊素、枸橼酸。 | E90: 本品为灰黄绿色的粉末；气香，味咸、微苦而辛凉。 | F90: 清热解毒，消肿止痛。用于风热上攻、肺胃热盛所致的乳蛾、喉痹、口糜，症见咽喉肿痛、喉核肿大、口舌生疮、牙龈肿痛或出血；急、慢性咽炎，扁桃体炎，口腔炎，口腔溃疡，牙龈炎见上述证候者及轻度烫伤(表皮未破)者。 | G90: 外用。喷、吹或敷于患处，一次适量，一日数次；重症者兼服，一次1-2克，一日3次。 | H90: 尚不明确。 | I90: 尚不明确。 | J90: 1.忌烟酒、辛辣、鱼腥食物。 2.不宜在服药期间同时服用滋补性中药。 3.有高血压、心脏病、肝病、糖尿病、肾病等慢性病严重者应在医师指导下服用。 4.儿童、孕妇、哺乳期妇女、年老体弱、脾虚便溏者应在医师指导下应用。 5.扁桃体有化脓或口糜严重患者应去医院就诊。 6.发热体温超过38.5℃的患者应去医院就诊。 7.口腔内喷或敷药时请不要呼吸，以防药粉进入呼吸道而引起呛咳。用药后半小时内不得进食、饮水。 8.严格按用法用量应用，本品不宜长期应用。 9.用药3天症状无缓解，应去医院就诊。 10.对本品过敏者禁用 | L90: 如与其他药物同时使用可能会发生药物相互作用，详情请咨询医师或药师。 | M90: 清热解毒，消肿止痛。 | N90: 密闭。 | O90: 每瓶装1.0g、2.0g、2.5g、3.0g、3.5g | P90: 聚乙烯塑料瓶装，每小盒装2.5克。
A91: 通用名称：复方鱼腥草合剂 商品名称：金笛 英文名称：FuFangYuXingCaoHeJi(jindi) 汉语拼音：Fufang Yuxingcao Heji | B91: 20.4 | C91: =IF(ISNUMBER(MATCH(#REF!,非处方药名称!A:A,0)),"非处方药","处方药") -> 处方药 | D91: 鱼腥草、黄芩、板蓝根、连翘、金银花.辅料为蔗糖、蜂蜜、防腐剂(苯甲酸钠、羟苯乙酯)。 | E91: 本品为黄棕色至棕色的液体，味甜、微苦涩。 | F91: 清热解毒。用于外感风热引起的咽喉疼痛；急性咽炎、扁桃腺炎有风热证候者。 | G91: 口服，一次20～30毫升，一日3次。 | H91: 尚不明确。 | I91: 糖尿病患者禁服。 | J91: 1.忌烟酒、辛辣、鱼腥食物。 2.不宜在服药期间同时服用温补性中药。 3.孕妇慎用。儿童应在医师指导下服用。 4.脾虚大便溏者慎用。 5.属风寒感冒咽痛者，症见恶寒发热、无汗、鼻流清涕者慎用。 6.扁桃体有化脓及全身高热者应去医院就诊。 7.服药3天症状无缓解，应去医院就诊。 8.对本品过敏者禁用，过敏体质者慎用。 9.本品性状发生改变时禁止使用。 10.儿童必须在成人监护下使用。 11.请将本品放在儿童不能接触的地方。 12.如正在使用其他药品，使用本品前请咨询医师或药师。 | L91: 如与其他药物同时使用可能会发生药物相互作用，详情请咨询医师或药师。 | M91: 清热解毒。 | N91: 密封，置阴凉处(不超过20C)。 | O91: 钠钙玻璃管制口液体瓶装,每瓶装10毫升,每盒装18瓶。 | P91: 钠钙玻璃管制口液体瓶装，每瓶装10毫升，每盒装18瓶。
A92: 通用名称：双羊喉痹通颗粒 商品名称：百灵鸟 英文名称：ShuangYangHouBiTongKeLi(BaiLingNiao) 汉语拼音：Shuangyang Houbitong Keli | B92: 24.8 | C92: =IF(ISNUMBER(MATCH(#REF!,非处方药名称!A:A,0)),"非处方药","处方药") -> 处方药 | D92: 野烟叶、羊耳菊、矮地茶、羊奶奶叶、僵蚕、荆芥、薄荷。辅料为蔗糖。 | E92: 本品为棕褐色颗粒;具薄荷香气，味甜。 | F92: 1.苗医：旭嘎凯沓痂，洼嘎挡孟。陡：纳蒙宁宫，纳蒙嘎宫昂。阶：蒙给宁宫。2.中医：清热解毒，利咽止痛。用于急喉痹(急性咽炎)、急乳蛾(急性扁桃体炎)所致的咽喉肿痛。 | G92: 口服。一次1袋，一日3次。 | H92: 尚不明确。 | I92: 孕妇禁用。 糖尿病患者禁服。 | J92: 1.忌烟酒、辛辣、鱼腥食物。 2.不宜在服药期间同时服用温补性中药。 3.儿童应在医师指导下服用。 4.脾虚大便溏者慎用。 5.属风寒感冒咽痛者，症见恶寒发热、无汗、鼻流清涕者慎用。 6.扁桃体有化脓及全身高热者应去医院就诊。 7.服药3天症状无缓解，应去医院就诊。 8.对本品过敏者禁用，过敏体质者慎用。 9.药品性状发生改变时禁止服用。 10.儿童必须在成人监护下使用。 11.请将此药品放在儿童不能接触的地方。 12.如正在服用其他药品，使用本品前请咨询医师或药师。 | L92: 如与其他药物同时使用可能会发生药物相互作用，详情请咨询医师或药师。 | N92: 密封。 | O92: 每袋装10g | P92: 复合膜包装，每盒6袋。 | Q92: 24个月
A93: 通用名称：复方小儿退热栓 商品名称：敬修堂 英文名称：FuFangXiaoErTuiReShuan(JingXiuTang) 汉语拼音：Fufang Xiao’er Tuire | B93: 11.3 | C93: =IF(ISNUMBER(MATCH(#REF!,非处方药名称!A:A,0)),"非处方药","处方药") -> 处方药 | D93: 对乙酰氨基酚、人工牛黄、南板蓝根浸膏粉。辅料为吐温、尼泊金乙酯、半合成酯肪酸甘油酯。 | E93: 本品为棕色的栓剂。 | F93: 解热镇痛，利咽解毒，袪痰定惊。用于小儿发热，惊悸不安，咽喉肿痛及肺热痰多咳嗽。 | G93: 直肠给药。将药栓单个撕开，再从塑料片分离处撕开取出药栓，患者取侧卧位，将药栓塞入肛门深约2厘米处。一至三岁小儿一次1粒，一日1次，三至六岁一次1粒，一日2次。 | H93: 偶见皮疹、荨麻疹、药热及粒细胞减少；长期大量用药会导致肝肾功能异常。 | I93: 严重肝肾功能不全者禁用。 | J93: 1.本品以清热为主，连续使用不得超过3天，发热持续未缓解，应及时就诊。2.本品含对乙酰氨基酚。服用本品期间不得饮酒或含有酒精的饮料；不能同时服用与本品成份相似的其他抗感冒药；肝、肾功能不全者慎用。3.出现皮疹、荨麻疹等过敏反应时，应立即停止使用。4.对本品过敏者禁用，过敏体质者慎用。5.本品性状发生改变时禁止使用。6.儿童必须在成人监护下使用。7.请将本品放在儿童不能接触的地方。8.如正在使用其他药品，使用本品前请咨询医师或药师。 | K93: 1.与其他解热镇痛药并用，有增加肾毒性的危险。 2.如与其他药物同时使用可能会发生药物相互作用，详情请咨询医师或药师。 | N93: 密闭，置阴凉处（不超过20℃）。 | O93: 每粒含对乙酰氨基酚150mg,人工牛黄5mg | P93: 药用聚乙烯聚氯乙烯复合片材包装，每盒装5粒。 | Q93: 30个月。
A94: 通用名称：萘敏维滴眼液 商品名称：润洁 英文名称：Naphazoline Hydrochloride,Chlorphenamine Maleate and Vitamin B12 Eye Drops 汉语拼音：Naiminwei Diyanye | B94: 17.3 | C94: =IF(ISNUMBER(MATCH(#REF!,非处方药名称!A:A,0)),"非处方药","处方药") -> 处方药 | D94: 维生素B12、马来酸氯苯那敏、盐酸萘唑林。 | E94: 本品为粉红色澄明液体，具有特殊气味。 | F94: 适用于眼疲劳、结膜充血、眼痒等不适症状。 | G94: 滴眼。一日3～4次，一次1～2滴。可根据年龄、症状，适当增加滴眼液次数。 | H94: 局部反应：瞳孔散大，加重充血、刺激、眼部不适、视物模糊，点状角膜炎，流泪，眼内压升高。全身症状：晕眩，头痛，恶心，发汗，焦躁，瞌睡，虚弱，血压升高，心律不齐，高血糖。 | I94: 1.闭角型青光眼。 2.对本品任何成分过敏者禁用。 | J94: 1.高血压，心血管异常，糖尿病，甲状腺机能亢进，感染或外伤病人应慎用本品。2.保存于小儿手拿不到的位置。3.尚不清楚是否对胎儿造成伤害，因此只有在明确必须使用时，孕妇才可小心使用本品。建议哺乳期妇女在使用本品时暂停哺乳。4.小儿需在保护者的监督指导下使用;儿童，尤其婴儿使用可能会发生中枢神经抑制，导致昏迷和体温显著下降。 | K94: 儿童注意事项： 尚不明确。 妊娠与哺乳期注意事项： 尚不清楚是否对胎儿造成伤害，因此只有在明确必须使用时，孕妇才可小心使用本品。建议哺乳期妇女在使用本品时暂停哺乳。 老人注意事项： 尚不明确。 | L94: 当马普替林或三环类抗抑郁药与本品合用时可加强萘唑林的升高血压作用。使用MAO抑制剂治疗的病人如果再用拟肾上腺素药物可能会发生严重的高血压危象。 | M94: 萘唑林：对结膜血管具有收缩作用，主要是由于药物对结膜小动脉上的?-肾上腺素受体的直接刺激作用，结果降低了结膜充血。萘唑林为拟肾上腺素药。马来酸氯苯那敏：具有较强的抗组胺作用，用于缓解眼部的的过敏症状。维生素B12：具有重要的亲神经性作用，它与中枢及周围的有髓鞘神经纤维代谢有密切关系，可保持上述纤维功能的完整性。 | N94: 密闭，室温保存。 | O94: 10ml;15ml | Q94: 24个月。
A95: 通用名称：盐酸羟甲唑啉喷雾剂 商品名称：达芬霖 英文名称：Oxymetazoline Hydrochloride Spray 汉语拼音：Yan Suan Qiang Jia Zuo Lin Pen Wu Ji | B95: 21.2 | C95: =IF(ISNUMBER(MATCH(#REF!,非处方药名称!A:A,0)),"非处方药","处方药") -> 处方药 | D95: 本品每毫升含主要成份盐酸羟甲唑啉0.5毫克，辅料为三氯叔丁醇及氯化钠。 | E95: 本品为无色澄明液体。 | F95: 适用于患有急慢性鼻炎、鼻窦炎、过敏性鼻炎、肥厚性鼻炎的两到六岁儿童。 | G95: 喷鼻。成人和6岁以上儿童，一次一侧1-3喷，早晨和睡前各1次。 | H95: 1 用药过频易致反跳性鼻充血，久用可致药物性鼻炎。 2 少数人有轻微烧灼感，针刺感、鼻黏膜干燥以及头痛、头晕、心率加快等反应。 3 罕见过敏反应。 | I95: 1 萎缩性鼻炎及鼻腔干燥者禁用。 2 孕妇及2周岁以下儿童禁用。 3 正在接受单氨氧化酶抑制剂(如帕吉林、苯乙肼、多塞平等)治疗的患者禁用。 | J95: 1 严格按推荐用量使用，连续使用不得超过7天，如需继续使用，应咨询医师。 2 高血压、冠心并甲状腺功能亢进、糖尿病等患者慎用。 3 2～6岁儿童应在医师指导下使用。 4 如使用过量或出现严重不良反应，应立即就医。 5 对本品过敏者禁用，过敏体质者慎用。 6 本品性状发生改变时禁止使用。 7 请将本品放在儿童不能接触的地方。 8 儿童必须在成人监护下使用。 9 如正在使用其他药品，使用本品前请咨询医师或药师。 | K95: 儿童注意事项： 3岁以下小儿禁用。 妊娠与哺乳期注意事项： 孕妇、哺乳期妇女禁用。 老人注意事项： 慎用或遵医嘱。 | L95: 1 使用本品时不能同时使用其他收缩血管类滴鼻剂。2 如与其他药物同时使用可能会发生药物相互作用，详情请咨询医师或药师。 | M95: 盐酸羟甲唑林为咪唑林类衍生物，具有直接激动血管α-肾上腺素能受体而引起血管收缩的作用，从而减轻炎症所致的充血和水肿。 | N95: 遮光、密闭深存。 | O95: 10毫升:5毫克 | Q95: 36个月。
A96: 通用名称：复方氨酚烷胺胶囊 商品名称：快克 英文名称：Compound Paracetamol and Amantadine Hydrochloride Capsules 汉语拼音：Fufang AnFen Wan'an Jiaonang | B96: 8.5 | C96: =IF(ISNUMBER(MATCH(#REF!,非处方药名称!A:A,0)),"非处方药","处方药") -> 处方药 | D96: 本品为复方制剂，每粒含对乙酰氨基酚250毫克、盐酸金刚烷胺100毫克、马来酸氯苯那敏2毫克、人工牛黄10毫克、咖啡因15毫克。 | E96: 本品为胶囊剂，内容物为淡黄色小丸。 | F96: 适用于缓解普通感冒及流行性感冒引起的发热、头痛、四肢酸痛、打喷嚏、流鼻涕、鼻塞、咽痛等症状，也可用于流行性感冒的预防和治疗。 | G96: 口服。成人，一次1粒，一日2次。 | H96: 有时有轻度头晕、乏力、恶心、上腹不适、口干、食欲缺乏和皮疹等，可自行恢复。 | I96: 严重肝肾功能不全者禁用。 | J96: 1 用药3-7天，症状未缓解，请咨询医师或药师。 2 服用本品期间不得饮酒或含有酒精的饮料。 3 不能同时服用与本品成份相似的其他抗感冒药。 4 前列腺肥大、青光眼等患者以及老年人应在医师指导下使用。 5 肝功能不全、肾功能不全、脑血管病史、精神病史或癫痫病史患者慎用。 6 孕妇及哺乳期妇女慎用。 7 服药期间不得驾驶机、车、船、从事高空作业、机械作业及操作精密仪器。 8 如服用过量或出现严重不良反应，应立即就医。 9 对本品过敏者禁用，过敏体质者慎用。 10 本品性状发生改变时禁止使用。 11 请将本品放在儿童不能接触的地方。 12 如正在使用其他药品，使用本品前请咨询医师或药师。 | K96: 儿童注意事项： 不推荐使用。 妊娠与哺乳期注意事项： 孕妇及哺乳期妇女慎用。 老人注意事项： 因肝、肾功能减退，应慎用。 | L96: 1 与其他解热镇痛药同用，可增加肾毒性的危险。 2 本品不宜与氯霉素、巴比妥类（如苯巴比妥）等并用。 3 如与其他药物同时使用可能会发生药物相互作用，详情请咨询医师或药师。 | M96: 1 对乙酰氨基酚能抑制前列腺素合成，有解热镇痛的作用； 2 金刚烷胺可抗亚一甲型流感病毒，抑制病毒繁殖； 3 咖啡因为中枢兴奋药，能增强对乙酰氨基酚的解热镇痛效果，并能减轻其他药物所致的嗜睡、头晕等中枢抑制作用； 4 马来酸氯苯那敏为抗过敏药，能减轻流涕、鼻塞、打喷嚏等症状； 5 人工牛黄具有解热、镇惊作用。 6 述诸药配伍制成复方，可增强解热、镇痛效果，解除或改善感冒所引起的各种症状。 | N96: 密封，在阴凉干燥处保存 | O96: 复方
A97: 通用名称：红霉素眼膏 商品名称：双吉 英文名称：Erythromycin Eye Ointment 汉语拼音：Hongmeisu Yangao | B97: 3.2 | C97: =IF(ISNUMBER(MATCH(#REF!,非处方药名称!A:A,0)),"非处方药","处方药") -> 处方药 | D97: 本品每克含红霉素12.5毫克，辅料为:黄凡士林、液状石蜡。 | E97: 本品为白色至黄色的软膏。 | F97: 用于沙眼、结膜炎、角膜炎、眼睑缘炎及眼外部感染。 | G97: 涂于眼睑内，一日2～3次，最后一次宜在睡前使用。 | H97: 偶见眼睛疼痛，视力改变，持续性发红或刺激感等过敏反应。 | I97: 尚不明确。 | J97: 1.避免接触其他黏膜（如口、鼻等）。 2.用药部位如有烧灼感、搔痒、红肿等情况应停药，并将局部药物洗净，必要时向医师咨询。 3.用前应洗净双手。 4.孕妇及哺乳期妇女应在医师指导下使用。 5.使用后应拧紧瓶盖，以免污染药品。 6.对本品过敏者禁用，过敏体质者慎用。 7.本品性状发生改变时禁止使用。 8.请将本品放在儿童不能接触的地方。 9.儿童必须在成人监护下使用。 10.如正在使用其他药品，使用本品前请咨询医师或药师。 | K97: 儿童注意事项： 尚不明确。 妊娠与哺乳期注意事项： 尚不明确。 老人注意事项： 尚不明确。 | L97: 如与其他药物同时使用可能会发生药物相互作用，详情请咨询医师或药师。 | M97: 红霉素为大环内酯类抗生素，作用机制是抑制细菌蛋白质合成，对革兰氏阳性细菌和沙眼衣原体有抗菌作用。 | N97: 密闭，在阴凉（不超过20℃）干燥处保存。 | O97: 0.5% | Q97: 60个月。
A98: 通用名称：清喉利咽颗粒 商品名称：慢严舒柠 英文名称：QingHouLiYanKeLi(ManYanShuNingRuTangXing) 汉语拼音：Qing Hou Li Yan Ke Li | B98: 26.8 | C98: =IF(ISNUMBER(MATCH(#REF!,非处方药名称!A:A,0)),"非处方药","处方药") -> 处方药 | D98: 黄芩、西青果、桔梗、竹茹、胖大海、橘红、枳壳、桑叶、香附(醋制)、紫苏子、紫苏梗、沉香、薄荷脑，辅料为乳糖、蛋白糖。 | E98: 本品为黄棕色的颗粒，气香，味甜、微苦。 | F98: 清热利咽，宽胸润喉。用于外感风热所致的咽喉发干、声音嘶哑；急慢性咽炎，扁桃体炎见上述证候者，常用有保护声带作用。 | G98: 开水冲服。一次1袋，一日2～3次。 | H98: 尚不明确。 | I98: 尚不明确。 | J98: 1.忌烟酒、辛辣、鱼腥食物。2.不宜在服药期间同时服用滋补性中药。3.有高血压、心脏病、肝病、糖尿病、肾病等慢性病严重者应在医师指导下 服用。4.儿童、孕妇、哺乳期妇女、年老体弱、脾虚便溏者应在医师指导下服用。5.扁桃体有化脓或发热体温超过38.5℃的患者应去医院就诊。6.声音嘶哑较重者，应及时去医院就诊。7.若需长期服用，请咨询医师。8.服药3天症状无缓解，应去医院就诊。9.对本品过敏者禁用，过敏体质者慎用。10.本品性状发生改变时禁止使用。11.儿童必须在成人监护下使用。12.请将本品放在儿童不能接触的地方。13.如正在使用其他药品，使用本品前请咨询医师或药师。 | L98: 如与其他药物同时使用可能会发生药物相互作用，详情请咨询医师或药师。 | M98: 13味中药组成 直接作用于咽喉部 缓解症状，滋润嗓子，缓解声带疲劳，保护声带 调理人体阴阳平衡，治嗓+护嗓双管齐下 | N98: 密封。 | O98: 每袋装5克(含乳糖) | P98: 药品包装用复合膜包装，5克 x 6袋/盒丨5克 x 8袋/盒丨5克 x 10袋/盒丨5克 x 12袋/盒|5克 x 18袋/盒丨5克 x 24袋/盒丨5克 x 30袋/盒
A99: 通用名称：咽立爽口含滴丸 商品名称：艾纳香 英文名称：YanLiShuangKouHanDiWan(AiNaXiang) 汉语拼音：Yanlishuang Kouhandiwan | B99: 34.5 | C99: =IF(ISNUMBER(MATCH(#REF!,非处方药名称!A:A,0)),"非处方药","处方药") -> 处方药 | D99: 天然冰片、艾纳香油、薄荷素油、薄荷脑、辅料为甘草酸单胺盐、聚乙二醇。 | E99: 本品为白色至浅黄色滴丸；有特异香气、味甜、微苦。 | F99: 苗医：迫喔劫漳凯，泱安挡孟，旭嘎洼嘎宏。陡：纳、拉蒙宁宫。阶：蒙给宁宫，干宫检，罗项。中医：疏风散热，消肿止痛，清利咽喉。用于急性咽炎，慢性咽炎急性发作，咽痛，咽粘膜红肿，咽干，口臭等症。 | G99: 含服。一次2-4丸，一日4次。 | H99: 尚不明确。 | I99: 尚不明确。 | J99: 1.忌辛辣、鱼腥食物。 2.不宜在服药期间同时服用温补性中药。 3.孕妇慎用。哺乳期妇女、儿童、老人应在医师指导下服用。 4.勿空腹服用或一次大剂量服用，勿直接吞入胃肠道，避免引起胃肠刺激。 5.服药3天症状无缓解，应去医院就诊。 6.对该药品过敏者禁用，过敏体质者慎用。 7.该药品性状发生改变时禁止使用。但如表面出现龟裂纹，或颜色稍变浅，属正常范围，不影响药效。 8.儿童必须在成人监护下使用。 9.请将该药品放在儿童不能接触的地方。 10.如正在使用其他药品，使用该药品前请咨询医师或药师。 | L99: 如与其他药物同时使用可能会发生药物相互作用，详情请咨询医师或药师。 | N99: 密封。 | O99: 每丸重0.025克 | P99: 聚丙烯塑料瓶装，每瓶36丸，每盒2瓶。 | Q99: 24个月。
A100: 通用名称：西瓜霜清咽含片 商品名称：三金 英文名称：XiGuaShuangQingYanHanPian(SanJin) 汉语拼音：Xiguashuangqingyan Hanpian | B100: 7 | C100: =IF(ISNUMBER(MATCH(#REF!,非处方药名称!A:A,0)),"非处方药","处方药") -> 处方药 | D100: 西瓜霜、西青果、罗汉果、麦冬、南沙参、乌梅、陈皮、甘草、桉油、薄荷素油、薄荷脑、冰片。辅料为蔗糖、葡萄糖浆 | E100: 本品为薄膜衣片状物，除去薄膜衣后，显棕黄色至黄棕色；气芳香、味甜、辛凉微酸、苦涩。 | F100: 清热解毒，消肿利咽。用于缓解咽痛，咽干，灼热，声音不扬或西医诊断为急性咽炎，有上述表现者。 | G100: 含服，一次1片，一日6次。 | H100: 尚不明确。 | I100: 对本药品所含任何成分过敏者禁用。 | J100: 1.忌烟酒、辛辣、鱼腥食物。 2.不宜在服药期间同时服用温补性中药。 3.孕妇慎用。 4.糖尿病患者、儿童应在医师指导下服用。 5.属风寒感冒咽痛者，症见恶寒发热、无汗、鼻流清涕者慎用。 6.服药3天症状无缓解，应去医院就诊。 7.对本品过敏者禁用，过敏体质者慎用。 8.药品性状发生改变时禁止服用。 9.儿童必须在成份的监护下使用。 10.请将此药品放在儿童不能接触的地方。 11.如正在服用其他药品，使用本品前请咨询医师或药师。 | L100: 如与其他药物同时使用可能会发生药物相互作用，详情请咨询医师或药师。 | M100: 尚不明确。 | N100: 密封，置阴凉干燥处。 | O100: 每片重1.8克
...

Sheet 非处方药名称
A1: 枸橼酸铋钾颗粒（非处方）
A2: 乳果糖口服溶液
A3: 铝碳酸镁片
A4: 麻仁软胶囊
A5: 通天口服液
A6: 藿香正气滴丸
A7: 麻仁润肠丸
A8: 固本益肠片
A9: 达立通颗粒
A10: 胃乃安胶囊
A11: 枸橼酸铋钾胶囊
A12: 丁桂儿脐贴（2贴装）
... A3117: 西瓜霜喉口宝含片

Sheet Sheet1
A1: 用法用量 | B1: 用法用量
A2: 温开水冲服 | B2: 温开水冲服。12岁以下儿童用量见下表：2～3岁， 12～14公斤， 0.5～1片/次， 一日3次4～6岁， 16～20公斤， 1～1.5片/次， 一日3次7～9岁， 22～26公斤， 1.5～2片/次， 一日3次10～12岁， 28～32公斤，2～2.5片/次， 一日3次
A3: 口服 | B3: 口服。成人，一次1片，一日2次。
A4: 滴眼 | B4: 滴眼，一日3次，一次1～2滴或遵医嘱。
A5: 开水冲服 | B5: 开水冲服。一岁以内一次6克，一岁至三岁一次612克，四岁至七岁一次12-18克，八岁至十二岁一次24克，一日2次。
A6: 含服 | B6: 含服。一次4～6粒，日3次。
A7: 口服 | B7: 口服。一次3～4片，一日3次。
A8: 口服 | B8: 口服。一次2袋，一日1～2次。
A9: 口服 | B9: 口服。一次1～2袋，一日2～3次。
A10: 口服 | B10: 口服。一次4粒，一日3次。
A11: 口服 | B11: 口服。一次2片，一日3次；或遵医嘱。该药品连服七日为一疗程，可以连续服用三至五个疗程。
A12: 口服 | B12: 口服。一次2粒，一日3次。
... A1152: 口服 | B1152: 口服。吞服或用少量水溶解后服用，成人一次20~40mg，一日3次，或遵医嘱。
A1153: 糖皮质激素在应用生理剂量替代治疗时无明显不良反应 | B1153: 糖皮质激素在应用生理剂量替代治疗时无明显不良反应，不良反应多发生在应用药理剂量时，而且与疗程、剂量、用药种类、用法及给药途径等有密切关系。常见不良反应有以下几类。 1.静脉迅速给予大剂量可能发生全身性的过敏反应，包括面部、鼻粘膜、眼睑肿胀，荨麻疹，气短，胸闷，喘鸣。长程用药可引起以下副作用：医源性柯兴综合征面容和体态、体重增加、下肢浮肿、紫纹、易出血倾向、创口愈合不良、痤疮、月经紊乱、肱或股骨头缺血性坏死、骨质疏松或骨折(包括脊椎压缩性骨折、长骨病理性骨折)、肌无力、肌萎缩、低血钾综合征、胃肠道刺激(恶心、呕吐)、胰腺炎、消化性溃疡或肠穿孔，儿童生长受到抑制、青光眼、白内障、良性颅内压升高综合征、糖耐量减退和糖尿病加重。 2.患者可出现精神症状：欣快感、激动、不安、谵妄、定向力障碍，也可表现为抑制。精神症状尤易发生于患慢性消耗性疾病的人及以往有过精神不正常者。在用量达每日强的松40mg或更多，用药数日至二周即可出现。并发感染为糖皮质激素的主要不良反应。以真菌、结核菌、葡萄球菌、变形杆菌、绿脓杆菌和各种疱疹病毒感染为主。多发生在中程或长程疗法时，但亦可在短期用大剂量后出现。 3.下丘脑-垂体-肾上腺轴受到抑制，为激素治疗的重要并发症，其发生与制剂、剂量、疗程等因素有关。每日用强的松20mg以上，历时3周以上，以及出现医源性柯兴综合征时，应考虑肾上腺功能已受到抑制。 4.糖皮质激素停药后综合征可有以下各种不同的情况。①下丘脑-垂体-肾上腺功能减退，可表现为乏力、软弱、食欲减退、恶心、呕吐、血压偏低、长程治疗后此轴心功能的恢复一般需要9～12个月，功能恢复的先后依次为：i.下丘脑促肾上腺皮质激素释放素(CRF)分泌恢复并增多;ii.ACTH分泌恢复并高于正常，此时肾上腺皮质激素的分泌仍偏低;iii.氢皮质素的基础分泌恢复正常、垂体ACTH的分泌由原来偏多而恢复正常;iV.下丘脑-垂体-肾上腺皮质轴对应激的反应恢复正常。②停药后原来疾病已被控制的症状重新出现。为了避免肾上腺皮质功能减退的发生及原来疾病症状的复燃，在长程激素治疗后应缓慢地逐渐减量，并由原来的一日服用数次，改为每日上午服药一次，或隔日上午服药一次。③糖皮质激素停药综合征。有时患者在停药后出现头晕、昏厥倾向、腹痛或背痛、低热、食欲减退、恶心、呕吐、肌肉或关节疼痛、头疼、乏力、软弱，经仔细检查如能排除肾上腺皮质功能减退和原来疾病的复燃，则可考虑为对糖皮质激素的依赖综合征。 5.大剂量长期使用可有肥胖，多毛症，痤疮，血糖，血压及眼压升高，水钠潴留，水肿。可引起低血钾，肌肉麻痹，兴奋，胃肠溃疡，甚至出现胃肠出血，穿孔，骨质疏松，病理性骨折，伤口不易愈合，白内障，失明。突然停药可引起停药综合征。 | H1153: 突然停药可引起停药综合征
A1154: 口服 | B1154: 口服。一次12克，一日3次，或遵医嘱。
A1155: 口服 | B1155: 口服。一次1格半至2格(15～20毫升)，一日3次；服时摇匀。
A1156: 口服 | B1156: 口服，每一次20克，一日3～5次。
A1157: 口服 | B1157: 口服。一次10～20毫升，一日3次。
A1158: 口服 | B1158: 口服。一次6～8片，一日3次。
A1159: 口服 | B1159: 口服。一次15克，一日3次。
A1160: 口服 | B1160: 口服。一次20毫升，一日3次。
A1161: 口服 | B1161: 口服。一次2粒，一日3次。
A1162: 含服 | B1162: 含服。一次1片，每隔1～2小时1次。
A1163: 口服 | B1163: 口服。一次10毫升，一日4次。
A1164: 口服 | B1164: 口服。一次5片，一日3次。
A1165: 口服 | B1165: 口服，一次1丸，一日2次，小儿酌减。
... A1340: 口服 | B1340: 口服。每次10毫升，每天2-3次。儿童酌减
A1341: 本品可用静脉滴注或深部肌肉注射给药 | B1341: 本品可用静脉滴注或深部肌肉注射给药。 成人和16岁以上儿童或体重为40公斤或40公斤以上儿童患者，可根据病情，每次1～2克，每12小时一次，静脉滴注，疗程7～10天；轻中度尿路感染，每次0.5～1克，静脉滴注或深部肌肉注射，疗程7～10天；重度尿路感染，每次2克，每12小时一次，静脉滴注，疗程10天；对于严重感染并危及生命时，可以每8小时2克静脉滴注；用于中性粒细胞减少伴发热的经验治疗，每次2克，每8小时一次静脉滴注，疗程7～10天或至中性粒细胞减少缓解。如发热缓解但中性粒细胞仍处于异常低水平，应重新评价有无继续使用抗生素治疗的必要。 2月龄至12岁儿童，最大剂量不可超过成人剂量（即每次2克剂量）。体重超过40公斤的儿童的剂量，可使用成人剂量。一般可每公斤体重40毫克，每12小时静脉滴注，疗程7～14天；对细菌性脑脊髓膜炎儿童患者，可为每公斤体重50毫克，每8小时一次，静脉滴注。对儿童中性粒细胞减少伴发热经验治疗的常用剂量为每公斤体重50毫克，每12小时一次（中性粒细胞减少伴发热的治疗为每8小时一次），疗程与成人相同。 2月龄以下儿童经验有限。可使用每公斤体重50毫克剂量。然而2月龄以上儿童患者的资料表明，每公斤30毫克，每8或12小时一次对于1至2月龄儿童患者已经足够。对2月龄以下儿童使用本品应谨慎。 儿童深部肌肉注射的经验有限。 对肝功能不全患者，无调节本品剂量的必要。 对肾功能不全病人，如肌酐清除率低于（含）60ml/min，则应调节本品用量，弥补这些病人减慢的肾清除速率。这些病人使用头孢吡肟的初始剂量与肾功能正常的患者相同，维持剂量和给药间隙时间如下： 与正常给药方案比较，肾功能不全成人患者的推荐维持给药方案 肌酐清除率（ml/min） 推荐维持给药方案 ＞60， 每次0.5克， 每次1克， 每次2克， 每次2克， 正常给药方案 每12小时一次 每12小时一次 每12小时一次 每8小时一次 30-60 每次0.5克， 每次1克， 每次2克， 每次2克， 每24小时一次 每24小时一次 每24小时一次 每24小时一次 11-29 每次0.5克， 每次0.5克， 每次1克， 每次2克， 每24小时一次 每24小时一次 每24小时一次 每24小时一次 ＜11 每次0.25克， 每次0.25克， 每次0.5克， 每次1克， 每24小时一次 每24小时一次 每24小时一次 每24小时一次 血液透析* 每次0.5克， 每次0.5克， 每次0.5克， 每次0.5克， 每24小时一次 每24小时一次 每24小时一次 每24小时一次 *血液透析患者在治疗第一天可给予负荷剂量1克，以后每天0.5克。透析日，头孢吡肟应在透析结束后使用。每天给药时间尽可能相同。 头孢吡肟治疗同时需进行血液透析的患者，在透析开始3小时，约68％药物可被清除。血液透析患者的马斯平剂量见上表。接受持续性腹膜透析患者应每隔48小时给予常规剂量。 尚无肾功能不全的儿童患者使用头孢吡肟的资料。但是，由于成人和儿童的头孢吡肟药代动力学相似，肾功能不全儿童患者头孢吡肟的用法与成人类似。 静脉给药：对于严重或危及生命的病例，应首选静脉给药。 静脉滴注时，可将本品1～2克溶于50～100毫升0.9%氯化钠注射液，5%或10%葡萄糖注射液，M/6乳酸钠注射液，5%葡萄糖和0.9%氯化钠混合注射液，乳酸林格氏和%5葡萄糖混合注射液中，药物浓度不应超过每毫升40毫克。经约30分钟滴注完毕。 肌肉内注射：肌肉注射时，本品0.5克应加1.5毫升注射用溶液，或1克加3.0毫升溶解后，经深部肌群（如臀肌群或外侧股四头肌）注射。 | H1341: 尚无肾功能不全的儿童患者使用头孢吡肟的资料 | I1341: 但是，由于成人和儿童的头孢吡肟药代动力学相似，肾功能不全儿童患者头孢吡肟的用法与成人类似 | J1341: 静脉给药：对于严重或危及生命的病例，应首选静脉给药 | K1341: 静脉滴注时，可将本品1～2克溶于50～100毫升0.9%氯化钠注射液，5%或10%葡萄糖注射液，M/6乳酸钠注射液，5%葡萄糖和0.9%氯化钠混合注射液，乳酸林格氏和%5葡萄糖混合注射液中，药物浓度不应超过每毫升40毫克 | L1341: 经约30分钟滴注完毕 | M1341: 肌肉内注射：肌肉注射时，本品0.5克应加1.5毫升注射用溶液，或1克加3.0毫升溶解后，经深部肌群（如臀肌群或外侧股四头肌）注射
A1342: 口服 | B1342: 口服。一次6片，一日3次，饭后用温开水送服。
A1343: 用开水冲服 | B1343: 用开水冲服。一次5克，一日3次；小儿酌减。
A1344: 口服 | B1344: 口服，一次3克，一日1～2次
A1345: 日服 | B1345: 日服，一次15克，一日2次。
A1346: 口服 | B1346: 口服。一次0.2g，一日1次。首剂量加倍为0.4g。疗程5～10日。对前列腺炎的疗程可达4周。
A1347: 成人每次2.5g或5g（即哌拉西林2g或4g | B1347: 成人每次2.5g或5g（即哌拉西林2g或4g，舒巴坦0.5g或1g），每12小时一次。严重或难治性感染，每次2.5g或5g（即哌拉西林2g或4g，舒巴坦0.5g或1g），每8小时一次。肾功能不全者酌情调整剂量。疗程：7—14天，或根据病情需要调整疗程。
A1348: 本品可直接口服 | B1348: 本品可直接口服，也可以加10-15ml温开水中搅拌均匀后服用。成人一般每次0.25g（两包），每日两次，一般疗程为5-10日。儿童按体重每日20mg/kg，分两次服用，一日不超过0.5g。
A1349: 口服 | B1349: 口服。一次1.5～2.0克，一日2～3次，可在发病预兆前服用，也可预防久喘复发，一般服15天为一疗程。
A1350: 口服 | B1350: 口服，一次1支，一日2-3次。
A1351: 成人一次1片 | B1351: 成人一次1片，每日2次，儿童按体重计算（与牛奶同服，增加吸收和提高药效）。
A1352: 口服 | B1352: 口服。1～2岁 一次1/2袋，3～4岁 一次1袋，5～6岁 一次1.5袋，一日2次。
A1353: 口服 | B1353: 口服。成人及12岁以上儿童：一次10ml，1日3次，睡前服20ml。6-12岁儿童：一次5ml，1日3次，睡前服10ml。2-5岁儿童：一次2.5ml，1日3次，睡前服5ml。2岁以下儿童不宜服用。
... A1562: 阴道给药 | B1562: 阴道给药，一次一枚，每日一次，重症每日2次，或遵医嘱，六天为一个疗程。
A1563: 阴道给药 | B1563: 阴道给药，一次一粒，每日一次;重症每日二次。或遵医嘱。六次为一疗程。推荐治疗方案：1.术前用药：一天二次。于每晚及次晨各一枚。连用一周。2.各种阴道炎症：霉菌性、滴虫性、老年性、急性、细菌性等阴道炎症.一天一次。一次一枚，6天为一疗程，坚持使用两个疗程。临床症状严重者.一天二次。于每晚及次晨各一枚。6天为一疗程。坚持使用两个疗程。3.宫颈糜烂：一度宫颈糜烂，一天一次。每次一枚，6天为一疗程。坚持使用2个以上疗程。二度宫颈糜烂(或颗粒型).一天一次，每次一枚，症状重者一天二次，每次一枚。6天为一疗程。坚持使用3—4个疗程以上。三度宫颈糜烂(或乳头型).一天二次，于每晚及次晨各一枚，6天为一疗程，坚持使用5—7个疗程。乳头型合并宫颈腺体囊肿者，可采用碘酒(0.5%)局部消毒，用穿刺针头刺破囊肿壁，使液体流出后使用本品，一天二次，一次一枚。坚持用药5—7个疗程。 | H1563: 坚持用药5—7个疗程
A1564: 口服 | B1564: 口服。6岁以上儿童一次0.5～1片；成人一次1～2片，一日3次。
A1565: 口服 | B1565: 口服。成人，一次1粒，一日2-3次。
A1566: 口服 | B1566: 口服。一次6克，一日2次。
A1567: 口服 | B1567: 口服。一次3粒，一日2～3次。
A1568: 口服 | B1568: 口服。一次6片，一日3次。
A1569: 口服 | B1569: 口服。一次3粒，一日3次。
A1570: 口服 | B1570: 口服。一次2粒，一日3次，14天为一疗程；温开水送下。
A1571: 口服 | B1571: 口服。一次10丸，一日2次，一个月经周期为一疗程，经前一周开始服用。
A1572: 开水冲服 | B1572: 开水冲服。一次20克，一日2次。
A1573: 临睡前 | B1573: 临睡前，洗净外阴后，用手指将药栓放入阴道深部，每晚1次，一次1片。7日为一疗程。
A1574: 口服 | B1574: 口服。水蜜丸一次4～8克，大蜜丸一次1～2丸，一日2～3次。
A1575: 外用 | B1575: 外用。用前摇匀。阴部疾患用本品15毫升加温开水至1000毫升冲洗或坐浴，一日1～2次，一周为1疗程。
... A1620: 开水冲服 | B1620: 开水冲服。一次4克，一日2次，5天为一疗程。
A1621: 成人：1.抗风湿：一次0.4-0.8g | B1621: 成人：1.抗风湿：一次0.4-0.8g，一日3-4次。类风湿关节炎比骨性关节炎用量大。一日最大用药量不超过2.4g。2.轻、中度疼痛：(1)一次0.2-0.4g，每4-6小时1次。一日最大用药量不宜超过2.4g。(2)分散片：推荐剂量为一次0.2-0.4g，一日3次。(3)缓释片：一次0.3-0.6g，早、晚各一次。(4)缓释胶囊：一次0.3g，早、晚各一次。(5)缓释混悬剂：推荐剂量为一次0.3-0.6g，一日2次。3.发热：(1)一次0.2g，一日3-4次。(2)分散片：推荐剂量为一次0.2-0.4g，一日3次。(3)缓释混悬剂：推荐剂量为一次0.3-0.6g，一日2次。4.抗炎：(1)缓释片：一次0.3-0.6g，早、晚各一次。(2)缓释胶囊：一次0.3g，早、晚各一次。(3)缓释混悬剂：推荐剂量为一次0.3-0.6g，一日2次。局部给药乳膏：依患处面积大小，取适量轻揉患处，一日3-4次。搽剂：涂患处，一次2-4ml，一日3次。直肠给药一次100mg，如需再次用药应间隔4小时以上。 儿童：口服给药12岁以上儿童用法用量同成人(除风湿性疾病)。1-12岁儿童用法用量如下：1.发热：(1)分散片、混悬液：推荐剂量为一日20mg/kg，分3次服用。(2)缓释混悬剂：推荐剂量为一日20mg/kg，分2次服用。(3)混悬滴剂具体用法如下：一次5-10mg/kg，需要时每6-8小时重复使用，每24小时不超过4次。或参照下表，用滴管量取。使用前请摇匀使用后请清洗滴管。 | H1621: (2)缓释混悬剂：推荐剂量为一日20mg/kg，分2次服用 | I1621: (3)混悬滴剂具体用法如下：一次5-10mg/kg，需要时每6-8小时重复使用，每24小时不超过4次 | J1621: 或参照下表，用滴管量取 | K1621: 使用前请摇匀使用后请清洗滴管
A1622: 开水冲服 | B1622: 开水冲服。一次10克，一日3次。
A1623: 外用 | B1623: 外用，一日2～3次；取药膏适量涂入脐部，再粘上贴剂；其它患处可直接涂敷。
A1624: 口服 | B1624: 口服。一次1丸，一日2次。
A1625: 加水稀释5～10倍后抹洗或冲洗外阴 | B1625: 加水稀释5～10倍后抹洗或冲洗外阴，一日1～2次，10天为一疗程。
A1626: 口服 | B1626: 口服。一次4-6片，一日3次。
A1627: 口服 | B1627: 口服。一次3片，一日3次。
A1628: 开水冲服 | B1628: 开水冲服。一次15克，一日2次。
A1629: 口服 | B1629: 口服。一次15毫升，一日3次。
A1630: 开水冲服 | B1630: 开水冲服。一次14克，一日3次。
A1631: 口服（1）成人常用量：①抗风湿 | B1631: 口服（1）成人常用量：①抗风湿，一次0.25～0.5g，早晚各一次，或早晨服0.25g，晚上服0.5g；②止痛，首次0.5g，以后必要时0.25g，必要时每6～8小时一次；③痛风性关节炎急性发作，首次0.75g，以后一次0.25g，每8小时一次，直到急性发作停止；④痛经，首次0.5g，以后必要时0.25g，每6～8小时一次。（2）小儿常用量：抗风湿，按体重一次5mg/kg，一日2次
A1632: 口服 | B1632: 口服，一次4粒，一日2次。月经不调者于月经干净后服用，十二天为一疗程，带下病，十天为一疗程。
A1633: 阴道给药 | B1633: 阴道给药，洗净后将软胶囊剂置于阴道深处。每晚1次，一次1粒，连用3日为一疗程。即使症状迅速消失，也要完成治疗疗程，在月经期应持续使用。
... A1965: 口服 | B1965: 口服。一次3粒，一日3次。
A1966: 给药途径：口服1.给药方法1.1如何服用本品如果服用正确 | B1966: 给药途径：口服1.给药方法1.1如何服用本品如果服用正确，复方口服避孕药每年的避孕失败率约为1%。如果出现漏服药物或者服用方法不正确，避孕失败率会上升。必须按照包装所标明的顺序，每天约在同一时间用少量液体送服。每日1片，连服21天。停药7天后开始服用下一盒药，其间通常会出现撤退性出血。一般在该周期最后一片药服完后2-3天开始出血，而且在开始下一盒药时出血可能还未结束。1.2如何开始服用本品开始眼药前，未使用激素避孕药的妇女(过去一个月)：应该在妇女自然月经周期的第1天开始服药(即月经出血的第1天);也可以在第2-5天开始，这种情况下，推荐在第一个服周期的最初7天内，加用屏障避孕法。从另一种复方激素避孕药(复方口服避孕药/COC)，阴道环或者经皮贴剂改服的妇女：最好在服用以前所用的COC最后一片含激素药物后，第2天即开始服用本品，最晚应在以前所用COC的停药期末或使用不含激素药片期末立即开始服用本品。对于曾经使用过阴道环或者经皮贴剂的妇女，最好在取出的当天开始服用本品，但最晚应该在下一次用药时开始服用本品。从单纯孕激素方法(微丸、注射剂、埋植剂)或从释放孕激素的宫内节育系统(IUS)改服的妇女：可在任何时间从微丸(从埋植剂或从IUS改服应在取出日，从注射液改服应在下一次注射口)改服本品，但是对所有这情况，应建议在服药的最初7天内加用屏障避孕法早期妊娠流产后的妇女：可以立即开始服药。在这种情况下，不需要加用其它避孕方法。分娩后或者中期妊娠流产后：哺乳期妇女的服用方法参见【孕妇及哺乳期妇女用药】应建议妇女在分娩后或中期妊娠流产后第21-28天开始服用。如果开始较晚，应建议妇女在服药的最初7天内加用屏障避孕法。然而，如果已经发生性行为，应该先除外妊娠的可能性，再开始服用本品，或者要等第一次月经来潮时再服用。2.漏服药的处理2.1如果使用者忘记眼药的时间在12小时以内，避孕保护作用不会降低。一旦妇女想起，就必须立即补服。下一片药物物应在常规时间服用。2.2如果忘记眼药的时间超过12小时，避孕保护作用可能降低，漏服药的处理可遵循以下两项基本原则：2.3在任何情况下停止服药不能超过7天2.4需要不间断地连服7天，以保持对下丘脑-垂体-卵巢轴的充分抑制因此在日常服药中可给出如下建议：第1周使用者应该在想起来时尽快服用漏服的药片，即使这意味着同时服用两片药。然后在常规时间继续服药。此外，在以后的7天内要加用屏障避孕法如避孕套。如果此前7天内已发生性行为，应考虑有妊娠的可能，漏服的药片越多并且越接近常规的停药期，发生妊娠的风险越高。第2周使用者应该在想起来时尽快服用漏服的药片，即使这意味着同时服用两片药。然后在常规的时间继续服药。假若使用者在第1片漏服药的前7天内均正确服药，则不需要使用额外的避孕措施。但是，如果不是这种情况，或者漏服药不止1片，那么应建议她加用额外的避孕措施7天。第3周因为临近停药期，所以避孕可靠性降低的风险加大。然而，通过调整服药汁划，仍可防止避孕保护作用的降低。假如妇女在漏服第1片药的前7天内均正确服药，则遵照以下两项建议的任一项，使用者没有必要采用额外的避孕措施。如果不是这种情况，建议妇女遵循这两项建议的第一项，并在以后的7天内加用额外的避孕措施。使用者应该在想起来时尽快服用漏服的药片，即使这意味着同时服用两片药，然后在常规时间继续服药。这盒药服完后立即开始服用下一盒药，即两盒药之间没有停药期，使用者在服完第二盒药之前，不大可能有撤退性出血，但可能在服药期间出现点滴或突破性出血。还可以建议妇女小再继续服用此周期药物。该妇女应该经过一个7天的停药期，其中包括漏服的天数，然后再开始继续服用下一周期的药物。如果妇女漏服了药物，而且在随后的第一个正常停药间隔期未出现撤退性出血，则应考虑妊娠的可能性。3.对发生胃肠道紊乱者的建议如果发生重度胃肠道紊乱，则吸收可能不完全，应采取额外的避孕措施：如果服用药物后3&mdash;4小时内发生呕吐，可以采用&ldquo;漏服药的处理&rdquo;参见【用法用量】的建议。如果妇女不想改变正常的服药计划，她必须从另一盒中取出药物补服。4.如何改变月经期或推迟月经期要想推迟月经，妇女可以在服完一盒药后，接着继续服用下一盒药而没有停药间隔期，可以根据意愿将月经推迟到第二盒药物服完以前的任何时可以恢复继续规律服用本品。要希望改变目前的月经期，移到本周的另1天，可建议她缩短停药间隔期到她希望的时间。停药间隔期越短，则不发生撤退性出皿和在下一盒药服药期间发生突破性出血及点滴出血(如推迟月经所述)的风险越大。5.特殊人群用药5.1肝功能损害患者有严重肝脏疾病的妇女禁用本品。见【禁忌】和【药代动力学】。5.2肾功能损害患者有严重肾功能不全或急性肾功能衰竭的妇女禁用本品。见【禁忌】和【药代动力学】。 | H1966: 如果此前7天内已发生性行为，应考虑有妊娠的可能，漏服的药片越多并且越接近常规的停药期，发生妊娠的风险越高 | I1966: 第2周使用者应该在想起来时尽快服用漏服的药片，即使这意味着同时服用两片药 | J1966: 然后在常规的时间继续服药 | K1966: 假若使用者在第1片漏服药的前7天内均正确服药，则不需要使用额外的避孕措施 | L1966: 但是，如果不是这种情况，或者漏服药不止1片，那么应建议她加用额外的避孕措施7天 | M1966: 第3周因为临近停药期，所以避孕可靠性降低的风险加大 | N1966: 然而，通过调整服药汁划，仍可防止避孕保护作用的降低 | O1966: 假如妇女在漏服第1片药的前7天内均正确服药，则遵照以下两项建议的任一项，使用者没有必要采用额外的避孕措施 | P1966: 如果不是这种情况，建议妇女遵循这两项建议的第一项，并在以后的7天内加用额外的避孕措施 | Q1966: 使用者应该在想起来时尽快服用漏服的药片，即使这意味着同时服用两片药，然后在常规时间继续服药 | R1966: 这盒药服完后立即开始服用下一盒药，即两盒药之间没有停药期，使用者在服完第二盒药之前，不大可能有撤退性出血，但可能在服药期间出现点滴或突破性出血 | S1966: 还可以建议妇女小再继续服用此周期药物 | T1966: 该妇女应该经过一个7天的停药期，其中包括漏服的天数，然后再开始继续服用下一周期的药物 | U1966: 如果妇女漏服了药物，而且在随后的第一个正常停药间隔期未出现撤退性出血，则应考虑妊娠的可能性 | V1966: 3.对发生胃肠道紊乱者的建议如果发生重度胃肠道紊乱，则吸收可能不完全，应采取额外的避孕措施：如果服用药物后3&mdash;4小时内发生呕吐，可以采用&ldquo;漏服药的处理&rdquo;参见【用法用量】的建议 | W1966: 如果妇女不想改变正常的服药计划，她必须从另一盒中取出药物补服 | X1966: 4.如何改变月经期或推迟月经期要想推迟月经，妇女可以在服完一盒药后，接着继续服用下一盒药而没有停药间隔期，可以根据意愿将月经推迟到第二盒药物服完以前的任何时可以恢复继续规律服用本品 | Y1966: 要希望改变目前的月经期，移到本周的另1天，可建议她缩短停药间隔期到她希望的时间 | Z1966: 停药间隔期越短，则不发生撤退性出皿和在下一盒药服药期间发生突破性出血及点滴出血(如推迟月经所述)的风险越大 | AA1966: 5.特殊人群用药5.1肝功能损害患者有严重肝脏疾病的妇女禁用本品 | AB1966: 见【禁忌】和【药代动力学】 | AC1966: 5.2肾功能损害患者有严重肾功能不全或急性肾功能衰竭的妇女禁用本品 | AD1966: 见【禁忌】和【药代动力学】
A1968: 口服每日50mg | B1968: 口服每日50mg，共5日。自月经周期的第5天开始服药。若患者系闭经，则应先用黄体酮撤退性出血的第5天始服用。患者在治疗后有排卵但未受孕可重复原治疗的疗程，直到受孕，或重复3-4个疗程。若患者在治疗后无排卵，在下一次的疗程中剂量可增加到每日100mg，共5日。个别患者药量可达每天150mg时，才能排卵。
A1969: 阴道给药 | B1969: 阴道给药。使用前先洗净手及外阴，从塑壳包装上撕下栓剂1枚，从下端将前、后塑片分开，小心拉开，使二塑片分离，驭塑料指套—只，套在食指上，取出栓粒，圆锥头部分朝向阴道，轻轻塞入，并用带套食指将栓粒推入阴道深处。每晚1次，—次l枚。连续7日为一疗程。
A1970: 口服 | B1970: 口服。 1.成人一次50～100mg，一日3～4次。 2.单纯性下尿路感染用低剂量：1月以上小儿每日按体重5～7mg/kg，分4次服。疗程至少1周，或用至尿培养转阴后至少3日。对尿路感染反复发作予本品预防者，成人一日50～100mg，睡前服，儿童一日1mg/kg。
A1971: 口服 | B1971: 口服，用量如下： 成人及体重大于40kg(或年龄大于12岁)的儿童，根据病情的需要，每次1～2片(每片含阿莫西林400mg和克拉维酸57mg)，每12小时一次。或遵医嘱。 体重小于40kg(或年龄小于l2岁)的儿童，建议剂量如下： 1.对于7～12岁的儿童，每次3/4片(每片含阿莫西林400mg和克拉维酸57mg)，每12小时一次。或遵医嘱。 2.对于2～7岁的儿童，每次1/2片(每片含阿莫西林400mg和克拉维酸57mg)，每12小时一次。或遵医嘱。 3.对于9个月～2岁的儿童，每次1/4片(每片含阿莫西林400mg和克拉维酸57mg)，每12小时一次，或遵医嘱。 对于肾功能受损患者：肾功能受损的病人一般不要求减少剂量：严重肾功能受损的病人，肌酐清除率<30ml/min者，不应服用本品。 对于肝功能受损患者，应慎用本品，并且应定期检查肝功能。
A1972: 口服 | B1972: 口服。一日25-100μg（1-4片）或隔日50-200μg（2-8片），分次服用或遵医嘱。
A1973: 口服 | B1973: 口服。水蜜丸一次5克，大蜜丸一次1丸，一日2次。
A1974: 1.皮肤感染：涂于洗净患处 | B1974: 1.皮肤感染：涂于洗净患处，一日2-3次。 2.外阴阴道炎：涂于洗净患处，每晚1次，连续7日。
A1975: 口服： 1 成人及12岁以上儿童：推荐剂量为一次0.3～0.6g(10～20ml) | B1975: 口服： 1 成人及12岁以上儿童：推荐剂量为一次0.3～0.6g(10～20ml)，一日2次，或遵医嘱。2 1岁～12岁儿童患者： (1) 用于发热，推荐剂量为每日按体重20mg/kg(0.66ml)，分2次服用，或遵医嘱。 (2) 用于镇痛，推荐剂量为每日按体重30mg/kg(1ml)，分2次服用，或遵医嘱。
A1976: 口服:一日1次,一次1片(100mg),或者一日1～2次,一次1片(75mg),或遵医嘱 | B1976: 口服:一日1次,一次1片(100mg),或者一日1～2次,一次1片(75mg),或遵医嘱。晚餐后用温开水送服,需整片吞服,不要弄碎或咀嚼。
A1977: 用温黄酒或温开水送服 | B1977: 用温黄酒或温开水送服。一次1袋，一日3次，或遵医嘱。
A1978: 1 滴虫病：急性毛滴虫病：一次性服药 | B1978: 1 滴虫病：急性毛滴虫病：一次性服药，成人一次1500毫克(6片),晚上顿服。儿童25 毫克/公斤/天，一次顿服。慢性毛滴虫病：成人每次500 毫克(二片)，每日二次，共五天。性伙伴应给予同样的治疗，以避免重复感染。 2 阿米巴虫病：阿米巴虫痢疾：成人及体重35 公斤以上的儿童，每次1500 毫克(6片),晚饭后顿服，连服三天；体重60公斤以上者，每次1000毫克(4片)，每日两次，饭后口服，连服三天；体重35公斤以下儿童，40毫克/公斤，一次顿服，饭后口服，连服三天。其他阿米巴虫病：成人及体重35公斤以上儿童，每次500毫克(二片)，每日二次；体重35公斤以下儿童，25 毫克/公斤，一次顿服，连服5—10天。 3 贾第鞭毛虫病：成人及体重35 公斤以上的儿童，晚上顿服1500毫克(6片)，服药1—2天；体重35公斤以下儿童，40毫克/公斤，一次顿服，服药1—2天。 4 厌氧菌感染：预防术后感染:手术前12小时口服1500毫克(6片)，以后每次500毫克(二片)，每日二次,服药至手术后3—5天。厌氧菌感染: 成人及体重35公斤以上的儿童，每次500毫克(二片),每日二次; 体重35公斤以下儿童，40毫克/公斤，分二次口服。
A1979: 温开水冲服 | B1979: 温开水冲服。一次5克，一日3次。
... A1995: 每个包装含28天的治疗 | B1995: 每个包装含28天的治疗。治疗应连续进行，即1盒药服完后立即开始服用下1盒，中间不要间隔。使用少量液体整片吞服，且用药时间不受饮食影响。最好在每日同一时间服药。
A1996: 该部分内容囊括了21项安慰剂空白对照研究(包括LIFT研究)中所记录的不良反应 | B1996: 该部分内容囊括了21项安慰剂空白对照研究(包括LIFT研究)中所记录的不良反应，在这些研究中有4079名女性受试者接受了治疗剂量的替勃龙(1.25mg或2.5mg)治疗，3476名女性受试者接受了安慰剂的治疗。这些研究的治疗期在2个月～4.5年不等。表1列出替勃龙治疗组与安慰剂对照组之间具有统计学差异的不良反应。在上市使用的过程中，发现的其它不良反应包括：头晕、皮疹、搔痒、脂溢性皮炎、头痛、偏头疼、视觉障碍(包括视力模糊)、胃肠道不适、抑郁、水肿、对肌肉骨骼的副作用如关节痛或肌痛，以及肝功能参数的变化。乳腺癌据MWS(Million Women Study)报道，与从未使用者比较，使用不同类型的雌激素—孕激素进行激素联合治疗与乳腺癌高风险相关(RR=2.00，95%CI:1.88~2.12)，且高于单独使用雌激素治疗的风险(RR =1.30，95%CI:1.21~1.40)，或高于使用替勃龙2.5mg治疗的风险(RR=1.45，95%CI：1.25~1.68)。根据发达国家已知的乳腺癌平均发生率，MWS得出以下结论：1.年龄在50~64周岁之间设有使用过HRT或替勃龙的妇女中估计每1000人约有32人患有乳腺癌。2.在1000名正在使用或近期使用过HRT的患者中，视疗程不同，乳腺癌病例数增加的情况是：*在单独用雌激素进行替代治疗的患者中，疗程为5年时，乳腺癌病例数增加了0~3例(最佳估计为1.5例);疗程为10年时，乳腺癌病例数增加了3~7例(最佳估计为5例)。*在雌激素—孕激素合并HRT治疗的患者中，疗程为5年时，乳腺癌病例数增加了5~7例(最佳估计为6例);疗程为10年时，乳腺癌病例数增加了18~20例(最佳估计为19例)。使用替勃龙的患者乳腺癌病例的增加数与单独使用雌激素相当。子宫内膜癌一项随机安慰剂空白对照临床试验中，入组的患者是在基线水平上未被筛查有子宫内膜异常的女性(这反映了临床治疗的真实情况)，以研究其患子宫内膜癌的最高风险率(LIFT研究，平均年龄68周岁)。在该项研究中，在经过2.9年之后，安慰剂组(n=1733)中没有被诊断为子宫内膜癌的病例，而在替勃龙治疗组(n=1746)中有4例被诊断为子宫内膜癌。这与之前研究的结论相符，即，每1000名使用替勃龙治疗1年的妇女中，子宫内膜癌的患者增加0.8例。脑卒中1.一项为期2.9年的随机对照研究的结果为：与安慰剂比较，在使用1.25mg替勃龙进行治疗的妇女(平均年龄68岁)中，脑卒中的危险增加了2.2倍，分别为28/2249(替勃龙组)和13/2257(安慰剂)。发生的脑卒中中绝大多数(80%)是局部缺血造成的。2.脑卒中的基线水平的危险率与年龄密切相关。因此，以5年为一周期，对基线水平的发生率进行评估如下：每1000名年龄在50~59周岁的妇女中是3名，而每1000名年龄在60~69周岁的妇女中是11名。对于使用替勃龙治疗5年的妇女来说，预计每1000名年龄在50~59周岁的妇女中增加的病例数量约为4例，而每1000名年龄在60~69周岁的妇女中增加的病例数量约为13名。在与雌激素—孕激素有关的治疗中，关于其他不良反应已见报道：1.良性和恶性的雌激素依赖性肿瘤，例如：子宫内膜癌。2.静脉血栓栓塞，例如：在HRT使用者中出现下肢深静脉血栓或盆腔静脉血栓和肺栓塞的发生率大于未使用HRT人群。3.心肌梗死。4.胆囊疾病。5.皮肤和皮下异常：黄褐斑、多形性红斑、结节性红斑、血管性紫癜。6.可能的痴呆。 | H1996: 4.胆囊疾病 | I1996: 5.皮肤和皮下异常：黄褐斑、多形性红斑、结节性红斑、血管性紫癜 | J1996: 6.可能的痴呆
A1997: 阴道内给药 | B1997: 阴道内给药。于房事前10分钟，取药膜一片，对折2次或揉成松软小闭，以食指（或中指）将其推入阴道深处，10分钟后可行房事。最大用量每次不超过2片。
A1998: 每日3次 | B1998: 每日3次，每次1袋，饭前开水冲服。
A1999: 阴道给药一次0.2g（相当于1粒） | B1999: 阴道给药一次0.2g（相当于1粒），一日0.4g（相当于2粒）。
A2000: 口服 一日3～4次 | B2000: 口服 一日3～4次。3～5岁,一次1粒；6～10岁,一次2粒；11岁以上,一次4粒。一日不宜超过16粒。退热治疗一般不超过3天,镇痛给药不直超过10天。
A2001: 口服 | B2001: 口服，一次30丸，一日2次。
A2002: 口服 | B2002: 口服。一次1～2粒，一日1次，饭后服用。
A2003: 阴道用药 | B2003: 阴道用药。每晚1支，将软膏轻轻挤入阴道深处，连用7日为一疗程，或遵医嘱。
A2004: 用黄酒或温开水送服 | B2004: 用黄酒或温开水送服。水丸6～9袋，一日2次。
A2005: 口服 | B2005: 口服。一次5片，一日3次。
A2006: 早晚各一次 | B2006: 早晚各一次，一次10毫升口服，严重者酌情增加服用量
A2007: 饭后温开水送服 | B2007: 饭后温开水送服。一次5粒，一日3次，连服9天为一个疗程，或遵医嘱。
A2008: 口服 | B2008: 口服，一次5片，一日3次。
... A2016: 阴道感染：于每晚休息时将阴道片一枚置于阴道深部 | B2016: 阴道感染：于每晚休息时将阴道片一枚置于阴道深部，连续使用10天，如外阴同时有感染，可用2-3克油膏涂。
A2017: 口服成人常用量： 1.子宫内膜异位症 | B2017: 口服成人常用量： 1.子宫内膜异位症，一日量400-800mg，分次服用，连服3-6个月，如停药后症状再出现，可再给药一疗程(在肝功正常情况下)； 2.纤维囊性乳腺病，于月经开始后第一天服药，一次50-200mg，每日2次，如停药后一年内症状复发，可再给药； 3.遗传性血管性水肿，开始一次200mg，每日2-3次，直到疗效出现，维持量一般是开始量的50%或更少，在1-3个月或更长一段的间隔时间递减，根据治疗前发病的频率而定。 | C2017: 在1-3个月或更长一段的间隔时间递减 | D2017: 根据治疗前发病的频率而定
A2018: 口服 | B2018: 口服。一次100毫升，一日2次。
A2019: 阴道塞入 | B2019: 阴道塞入。一次1粒，每晚1次，塞入阴道深处，7天为一疗程。
...

Sheet Sheet2
A1: 属性名称 | B1: 抽取实体或属性 | C1: 属性名称 | D1: 抽取实体或属性
A2: 药品名称 | B2: 药品；用法；剂型 | C2: 注意事项 | D2: 特殊人群
A3: 指导价 | B3: 指导价（属性） | C3: 特殊人群用药 | D3: 特殊人群
A4: 处方药 | C4: 药物相互作用
A5: 成分 | B5: 成分 | C5: 药理作用
A6: 性状 | B6: 剂型 | C6: 贮藏
A7: 适应症 | B7: 功效或适应症 | C7: 规格
A8: 用法用量 | B8: 用法 | C8: 包装规格
A9: 不良反应 | C9: 有效期
A10: 禁忌 | B10: 特殊人群
A11: 注意事项 | B11: 特殊人群
A12: 特殊人群用药 | B12: 特殊人群
A13: 药物相互作用
A14: 药理作用
A15: 贮藏
A16: 规格
A17: 包装规格
A18: 有效期
